Workbook

Sheet SETTORI
P1: =DATE(2025,1,2) -> 45659 | Q1: formula alternat. | S1: =IFERROR(__xludf.DUMMYFUNCTION("(GOOGLEFINANCE(A20,""price"")-INDEX(GOOGLEFINANCE(A20,""price"",""01-01-""&YEAR(TODAY())),2,2))/INDEX(GOOGLEFINANCE(A20,""price"",""01-01-""&YEAR(TODAY())),2,2)"),0.005474705474705419) -> 0.0054747055
I2: Relative Alpha ratio
I3: Rar Day | J3: Rar week | K3: Rar month | L3: Rar quarter | M3: Rar SixM | N3: Rar Year | O3: Ra/momentum | P3: Coerenza trend | Q3: Classifica | R3: Δ-RS (5d) | S3: Situazione | T3: Operatività | U3: Trend 20gg
H4: XLK | I4: =D20-$D$31 -> 0.1 | J4: =(E20-$E$31) -> 0.0057195998 | K4: =(F20-$F$31) -> -0.0082628246 | L4: =(G20-$G$31) -> -0.035321105 | M4: =(H20-$H$31) -> 0.016738042 | N4: =(J20-$J$31) -> 0.078962231 | O4: =(N4*0.15)+(M4*0.25)+(L4*0.3)+(K4*0.2)+(J4*0.1) -> 0.0043519087 | P4: =COUNTIF(I4:M4, ">0") -> 3 | Q4: =RANK(O4, $O$4:$O$14) -> 6 | R4: =IFERROR(HLOOKUP("RS-Mom " & H4, Motore!$AA$1:$AK$2, 2, FALSE), "Dato non trovato") -> 0.02625132 | S4: =IF(O4>0, IF(P4>=4, "LEADER", "IN RECUPERO"), "DEBOLE") -> IN RECUPERO | T4: =IF(AND(R4>0.02, S4="IN RECUPERO"), "🔭 ALERT BUY", IF(AND(Q4<=3, P4>=4, R4>0), "🔥 ACCUMULA", IF(AND(Q4<=3, P4>=4, R4<=0), "📈 MANTIENI", IF(AND(Q4>3, P4>=4), "👀 OSSERVA", "❌ EVITA")))) -> 🔭 ALERT BUY | U4: =IFERROR(__xludf.DUMMYFUNCTION("SPARKLINE(CHOOSE(MATCH(H4, Motore!$C$1:$M$1, 0), Motore!AA2:AA21, Motore!AB2:AB21, Motore!AC2:AC21, Motore!AD2:AD21, Motore!AE2:AE21, Motore!AF2:AF21, Motore!AG2:AG21, Motore!AH2:AH21, Motore!AI2:AI21, Motore!AJ2:AJ21, Motore!AK2:AK21), {"""&"charttype"",""line""; ""linewidth"",2; ""color"",IF(R4>0.01, ""#008000"", IF(R4<-0.01, ""#FF0000"", ""#FFFF00""))})"),"")
H5: XLY | I5: =D21-$D$31 -> 0.38 | J5: =(E21-$E$31) -> 0.016469991 | K5: =(F21-$F$31) -> 0.010413347 | L5: =(G21-$G$31) -> 0.015663866 | M5: =(H21-$H$31) -> 0.0066832039 | N5: =(J21-$J$31) -> -0.063055354 | O5: =(N5*0.15)+(M5*0.25)+(L5*0.3)+(K5*0.2)+(J5*0.1) -> 0.00064132609 | P5: =COUNTIF(I5:M5, ">0") -> 5 | Q5: =RANK(O5, $O$4:$O$14) -> 7 | R5: =IFERROR(HLOOKUP("RS-Mom " & H5, Motore!$AA$1:$AK$2, 2, FALSE), "Dato non trovato") -> -0.019324651 | S5: =IF(O5>0, IF(P5>=4, "LEADER", "IN RECUPERO"), "DEBOLE") -> LEADER | T5: =IF(AND(R5>0.02, S5="IN RECUPERO"), "🔭 ALERT BUY", IF(AND(Q5<=3, P5>=4, R5>0), "🔥 ACCUMULA", IF(AND(Q5<=3, P5>=4, R5<=0), "📈 MANTIENI", IF(AND(Q5>3, P5>=4), "👀 OSSERVA", "❌ EVITA")))) -> 👀 OSSERVA | U5: =IFERROR(__xludf.DUMMYFUNCTION("SPARKLINE(CHOOSE(MATCH(H5, Motore!$C$1:$M$1, 0), Motore!AA3:AA22, Motore!AB3:AB22, Motore!AC3:AC22, Motore!AD3:AD22, Motore!AE3:AE22, Motore!AF3:AF22, Motore!AG3:AG22, Motore!AH3:AH22, Motore!AI3:AI22, Motore!AJ3:AJ22, Motore!AK3:AK22), {"""&"charttype"",""line""; ""linewidth"",2; ""color"",IF(R5>0.01, ""#008000"", IF(R5<-0.01, ""#FF0000"", ""#FFFF00""))})"),"")
H6: XLF | I6: =D22-$D$31 -> -1.42 | J6: =(E22-$E$31) -> -0.019637151 | K6: =(F22-$F$31) -> -0.044282303 | L6: =(G22-$G$31) -> -0.010698082 | M6: =(H22-$H$31) -> -0.082095645 | N6: =(J22-$J$31) -> -0.090000094 | O6: =(N6*0.15)+(M6*0.25)+(L6*0.3)+(K6*0.2)+(J6*0.1) -> -0.048053526 | P6: =COUNTIF(I6:M6, ">0") -> 0 | Q6: =RANK(O6, $O$4:$O$14) -> 9 | R6: =IFERROR(HLOOKUP("RS-Mom " & H6, Motore!$AA$1:$AK$2, 2, FALSE), "Dato non trovato") -> -0.022039631 | S6: =IF(O6>0, IF(P6>=4, "LEADER", "IN RECUPERO"), "DEBOLE") -> DEBOLE | T6: =IF(AND(R6>0.02, S6="IN RECUPERO"), "🔭 ALERT BUY", IF(AND(Q6<=3, P6>=4, R6>0), "🔥 ACCUMULA", IF(AND(Q6<=3, P6>=4, R6<=0), "📈 MANTIENI", IF(AND(Q6>3, P6>=4), "👀 OSSERVA", "❌ EVITA")))) -> ❌ EVITA | U6: =IFERROR(__xludf.DUMMYFUNCTION("SPARKLINE(CHOOSE(MATCH(H6, Motore!$C$1:$M$1, 0), Motore!AA4:AA23, Motore!AB4:AB23, Motore!AC4:AC23, Motore!AD4:AD23, Motore!AE4:AE23, Motore!AF4:AF23, Motore!AG4:AG23, Motore!AH4:AH23, Motore!AI4:AI23, Motore!AJ4:AJ23, Motore!AK4:AK23), {"""&"charttype"",""line""; ""linewidth"",2; ""color"",IF(R6>0.01, ""#008000"", IF(R6<-0.01, ""#FF0000"", ""#FFFF00""))})"),"")
H7: XLC | I7: =D23-$D$31 -> 0.57 | J7: =(E23-$E$31) -> 0.013563487 | K7: =(F23-$F$31) -> -0.0069969842 | L7: =(G23-$G$31) -> -0.0075298447 | M7: =(H23-$H$31) -> 0.01057999 | N7: =(J23-$J$31) -> 0.03116631 | O7: =(N7*0.15)+(M7*0.25)+(L7*0.3)+(K7*0.2)+(J7*0.1) -> 0.0050179425 | P7: =COUNTIF(I7:M7, ">0") -> 3 | Q7: =RANK(O7, $O$4:$O$14) -> 5 | R7: =IFERROR(HLOOKUP("RS-Mom " & H7, Motore!$AA$1:$AK$2, 2, FALSE), "Dato non trovato") -> -0.029163025 | S7: =IF(O7>0, IF(P7>=4, "LEADER", "IN RECUPERO"), "DEBOLE") -> IN RECUPERO | T7: =IF(AND(R7>0.02, S7="IN RECUPERO"), "🔭 ALERT BUY", IF(AND(Q7<=3, P7>=4, R7>0), "🔥 ACCUMULA", IF(AND(Q7<=3, P7>=4, R7<=0), "📈 MANTIENI", IF(AND(Q7>3, P7>=4), "👀 OSSERVA", "❌ EVITA")))) -> ❌ EVITA | U7: =IFERROR(__xludf.DUMMYFUNCTION("SPARKLINE(CHOOSE(MATCH(H7, Motore!$C$1:$M$1, 0), Motore!AA5:AA24, Motore!AB5:AB24, Motore!AC5:AC24, Motore!AD5:AD24, Motore!AE5:AE24, Motore!AF5:AF24, Motore!AG5:AG24, Motore!AH5:AH24, Motore!AI5:AI24, Motore!AJ5:AJ24, Motore!AK5:AK24), {"""&"charttype"",""line""; ""linewidth"",2; ""color"",IF(R7>0.01, ""#008000"", IF(R7<-0.01, ""#FF0000"", ""#FFFF00""))})"),"")
H8: XLV | I8: =D24-$D$31 -> -0.55 | J8: =(E24-$E$31) -> -0.0038087283 | K8: =(F24-$F$31) -> 0.010728244 | L8: =(G24-$G$31) -> 0.070080755 | M8: =(H24-$H$31) -> 0.081922391 | N8: =(J24-$J$31) -> -0.042396044 | O8: =(N8*0.15)+(M8*0.25)+(L8*0.3)+(K8*0.2)+(J8*0.1) -> 0.036910193 | P8: =COUNTIF(I8:M8, ">0") -> 3 | Q8: =RANK(O8, $O$4:$O$14) -> 3 | R8: =IFERROR(HLOOKUP("RS-Mom " & H8, Motore!$AA$1:$AK$2, 2, FALSE), "Dato non trovato") -> -0.027369692 | S8: =IF(O8>0, IF(P8>=4, "LEADER", "IN RECUPERO"), "DEBOLE") -> IN RECUPERO | T8: =IF(AND(R8>0.02, S8="IN RECUPERO"), "🔭 ALERT BUY", IF(AND(Q8<=3, P8>=4, R8>0), "🔥 ACCUMULA", IF(AND(Q8<=3, P8>=4, R8<=0), "📈 MANTIENI", IF(AND(Q8>3, P8>=4), "👀 OSSERVA", "❌ EVITA")))) -> ❌ EVITA | U8: =IFERROR(__xludf.DUMMYFUNCTION("SPARKLINE(CHOOSE(MATCH(H8, Motore!$C$1:$M$1, 0), Motore!AA6:AA25, Motore!AB6:AB25, Motore!AC6:AC25, Motore!AD6:AD25, Motore!AE6:AE25, Motore!AF6:AF25, Motore!AG6:AG25, Motore!AH6:AH25, Motore!AI6:AI25, Motore!AJ6:AJ25, Motore!AK6:AK25), {"""&"charttype"",""line""; ""linewidth"",2; ""color"",IF(R8>0.01, ""#008000"", IF(R8<-0.01, ""#FF0000"", ""#FFFF00""))})"),"")
H9: XLP | I9: =D25-$D$31 -> 0.74 | J9: =(E25-$E$31) -> -0.010515543 | K9: =(F25-$F$31) -> 0.061388112 | L9: =(G25-$G$31) -> 0.040756369 | M9: =(H25-$H$31) -> -0.054200777 | N9: =(J25-$J$31) -> -0.069344689 | O9: =(N9*0.15)+(M9*0.25)+(L9*0.3)+(K9*0.2)+(J9*0.1) -> -0.00049891884 | P9: =COUNTIF(I9:M9, ">0") -> 3 | Q9: =RANK(O9, $O$4:$O$14) -> 8 | R9: =IFERROR(HLOOKUP("RS-Mom " & H9, Motore!$AA$1:$AK$2, 2, FALSE), "Dato non trovato") -> -0.023651654 | S9: =IF(O9>0, IF(P9>=4, "LEADER", "IN RECUPERO"), "DEBOLE") -> DEBOLE | T9: =IF(AND(R9>0.02, S9="IN RECUPERO"), "🔭 ALERT BUY", IF(AND(Q9<=3, P9>=4, R9>0), "🔥 ACCUMULA", IF(AND(Q9<=3, P9>=4, R9<=0), "📈 MANTIENI", IF(AND(Q9>3, P9>=4), "👀 OSSERVA", "❌ EVITA")))) -> ❌ EVITA | U9: =IFERROR(__xludf.DUMMYFUNCTION("SPARKLINE(CHOOSE(MATCH(H9, Motore!$C$1:$M$1, 0), Motore!AA7:AA26, Motore!AB7:AB26, Motore!AC7:AC26, Motore!AD7:AD26, Motore!AE7:AE26, Motore!AF7:AF26, Motore!AG7:AG26, Motore!AH7:AH26, Motore!AI7:AI26, Motore!AJ7:AJ26, Motore!AK7:AK26), {"""&"charttype"",""line""; ""linewidth"",2; ""color"",IF(R9>0.01, ""#008000"", IF(R9<-0.01, ""#FF0000"", ""#FFFF00""))})"),"")
H10: XLI | I10: =D26-$D$31 -> -0.81 | J10: =(E26-$E$31) -> -0.012974132 | K10: =(F26-$F$31) -> 0.046154553 | L10: =(G26-$G$31) -> 0.048288526 | M10: =(H26-$H$31) -> -0.019251816 | N10: =(J26-$J$31) -> 0.030445017 | O10: =(N10*0.15)+(M10*0.25)+(L10*0.3)+(K10*0.2)+(J10*0.1) -> 0.022173854 | P10: =COUNTIF(I10:M10, ">0") -> 2 | Q10: =RANK(O10, $O$4:$O$14) -> 4 | R10: =IFERROR(HLOOKUP("RS-Mom " & H10, Motore!$AA$1:$AK$2, 2, FALSE), "Dato non trovato") -> 0.009345775 | S10: =IF(O10>0, IF(P10>=4, "LEADER", "IN RECUPERO"), "DEBOLE") -> IN RECUPERO | T10: =IF(AND(R10>0.02, S10="IN RECUPERO"), "🔭 ALERT BUY", IF(AND(Q10<=3, P10>=4, R10>0), "🔥 ACCUMULA", IF(AND(Q10<=3, P10>=4, R10<=0), "📈 MANTIENI", IF(AND(Q10>3, P10>=4), "👀 OSSERVA", "❌ EVITA")))) -> ❌ EVITA | U10: =IFERROR(__xludf.DUMMYFUNCTION("SPARKLINE(CHOOSE(MATCH(H10, Motore!$C$1:$M$1, 0), Motore!AA8:AA27, Motore!AB8:AB27, Motore!AC8:AC27, Motore!AD8:AD27, Motore!AE8:AE27, Motore!AF8:AF27, Motore!AG8:AG27, Motore!AH8:AH27, Motore!AI8:AI27, Motore!AJ8:AJ27, Motore!AK8:AK27), {"&"""charttype"",""line""; ""linewidth"",2; ""color"",IF(R10>0.01, ""#008000"", IF(R10<-0.01, ""#FF0000"", ""#FFFF00""))})"),"")
H11: XLE | I11: =D27-$D$31 -> 0.53 | J11: =(E27-$E$31) -> 0.01620982 | K11: =(F27-$F$31) -> 0.11446044 | L11: =(G27-$G$31) -> 0.10858592 | M11: =(H27-$H$31) -> 0.03458994 | N11: =(J27-$J$31) -> -0.056347354 | O11: =(N11*0.15)+(M11*0.25)+(L11*0.3)+(K11*0.2)+(J11*0.1) -> 0.057284229 | P11: =COUNTIF(I11:M11, ">0") -> 5 | Q11: =RANK(O11, $O$4:$O$14) -> 1 | R11: =IFERROR(HLOOKUP("RS-Mom " & H11, Motore!$AA$1:$AK$2, 2, FALSE), "Dato non trovato") -> 0.031449573 | S11: =IF(O11>0, IF(P11>=4, "LEADER", "IN RECUPERO"), "DEBOLE") -> LEADER | T11: =IF(AND(R11>0.02, S11="IN RECUPERO"), "🔭 ALERT BUY", IF(AND(Q11<=3, P11>=4, R11>0), "🔥 ACCUMULA", IF(AND(Q11<=3, P11>=4, R11<=0), "📈 MANTIENI", IF(AND(Q11>3, P11>=4), "👀 OSSERVA", "❌ EVITA")))) -> 🔥 ACCUMULA | U11: =IFERROR(__xludf.DUMMYFUNCTION("SPARKLINE(CHOOSE(MATCH(H11, Motore!$C$1:$M$1, 0), Motore!AA9:AA28, Motore!AB9:AB28, Motore!AC9:AC28, Motore!AD9:AD28, Motore!AE9:AE28, Motore!AF9:AF28, Motore!AG9:AG28, Motore!AH9:AH28, Motore!AI9:AI28, Motore!AJ9:AJ28, Motore!AK9:AK28), {"&"""charttype"",""line""; ""linewidth"",2; ""color"",IF(R11>0.01, ""#008000"", IF(R11<-0.01, ""#FF0000"", ""#FFFF00""))})"),"")
H12: XLB | I12: =D28-$D$31 -> 0.87 | J12: =(E28-$E$31) -> 0.019743582 | K12: =(F28-$F$31) -> 0.085277375 | L12: =(G28-$G$31) -> 0.11735097 | M12: =(H28-$H$31) -> 0.015663582 | N12: =(J28-$J$31) -> -0.010736562 | O12: =(N12*0.15)+(M12*0.25)+(L12*0.3)+(K12*0.2)+(J12*0.1) -> 0.056540535 | P12: =COUNTIF(I12:M12, ">0") -> 5 | Q12: =RANK(O12, $O$4:$O$14) -> 2 | R12: =IFERROR(HLOOKUP("RS-Mom " & H12, Motore!$AA$1:$AK$2, 2, FALSE), "Dato non trovato") -> -0.0078861614 | S12: =IF(O12>0, IF(P12>=4, "LEADER", "IN RECUPERO"), "DEBOLE") -> LEADER | T12: =IF(AND(R12>0.02, S12="IN RECUPERO"), "🔭 ALERT BUY", IF(AND(Q12<=3, P12>=4, R12>0), "🔥 ACCUMULA", IF(AND(Q12<=3, P12>=4, R12<=0), "📈 MANTIENI", IF(AND(Q12>3, P12>=4), "👀 OSSERVA", "❌ EVITA")))) -> 📈 MANTIENI | U12: =IFERROR(__xludf.DUMMYFUNCTION("SPARKLINE(CHOOSE(MATCH(H12, Motore!$C$1:$M$1, 0), Motore!AA10:AA29, Motore!AB10:AB29, Motore!AC10:AC29, Motore!AD10:AD29, Motore!AE10:AE29, Motore!AF10:AF29, Motore!AG10:AG29, Motore!AH10:AH29, Motore!AI10:AI29, Motore!AJ10:AJ29, Motore!AK10:A"&"K29), {""charttype"",""line""; ""linewidth"",2; ""color"",IF(R12>0.01, ""#008000"", IF(R12<-0.01, ""#FF0000"", ""#FFFF00""))})"),"")
H13: XLU | I13: =D29-$D$31 -> -0.39 | J13: =(E29-$E$31) -> -0.026504529 | K13: =(F29-$F$31) -> -0.0035780755 | L13: =(G29-$G$31) -> -0.076970748 | M13: =(H29-$H$31) -> -0.064157353 | N13: =(J29-$J$31) -> -0.062696663 | O13: =(N13*0.15)+(M13*0.25)+(L13*0.3)+(K13*0.2)+(J13*0.1) -> -0.05190113 | P13: =COUNTIF(I13:M13, ">0") -> 0 | Q13: =RANK(O13, $O$4:$O$14) -> 10 | R13: =IFERROR(HLOOKUP("RS-Mom " & H13, Motore!$AA$1:$AK$2, 2, FALSE), "Dato non trovato") -> 0.010220977 | S13: =IF(O13>0, IF(P13>=4, "LEADER", "IN RECUPERO"), "DEBOLE") -> DEBOLE | T13: =IF(AND(R13>0.02, S13="IN RECUPERO"), "🔭 ALERT BUY", IF(AND(Q13<=3, P13>=4, R13>0), "🔥 ACCUMULA", IF(AND(Q13<=3, P13>=4, R13<=0), "📈 MANTIENI", IF(AND(Q13>3, P13>=4), "👀 OSSERVA", "❌ EVITA")))) -> ❌ EVITA | U13: =IFERROR(__xludf.DUMMYFUNCTION("SPARKLINE(CHOOSE(MATCH(H13, Motore!$C$1:$M$1, 0), Motore!AA11:AA30, Motore!AB11:AB30, Motore!AC11:AC30, Motore!AD11:AD30, Motore!AE11:AE30, Motore!AF11:AF30, Motore!AG11:AG30, Motore!AH11:AH30, Motore!AI11:AI30, Motore!AJ11:AJ30, Motore!AK11:A"&"K30), {""charttype"",""line""; ""linewidth"",2; ""color"",IF(R13>0.01, ""#008000"", IF(R13<-0.01, ""#FF0000"", ""#FFFF00""))})"),"")
H14: XLRE | I14: =D30-$D$31 -> 0.23 | J14: =(E30-$E$31) -> -0.02081673 | K14: =(F30-$F$31) -> 0.019580309 | L14: =(G30-$G$31) -> -0.040684733 | M14: =(H30-$H$31) -> -0.10112062 | N14: =(J30-$J$31) -> -0.14087813 | O14: =(N14*0.15)+(M14*0.25)+(L14*0.3)+(K14*0.2)+(J14*0.1) -> -0.056782904 | P14: =COUNTIF(I14:M14, ">0") -> 2 | Q14: =RANK(O14, $O$4:$O$14) -> 11 | R14: =IFERROR(HLOOKUP("RS-Mom " & H14, Motore!$AA$1:$AK$2, 2, FALSE), "Dato non trovato") -> -0.007008799 | S14: =IF(O14>0, IF(P14>=4, "LEADER", "IN RECUPERO"), "DEBOLE") -> DEBOLE | T14: =IF(AND(R14>0.02, S14="IN RECUPERO"), "🔭 ALERT BUY", IF(AND(Q14<=3, P14>=4, R14>0), "🔥 ACCUMULA", IF(AND(Q14<=3, P14>=4, R14<=0), "📈 MANTIENI", IF(AND(Q14>3, P14>=4), "👀 OSSERVA", "❌ EVITA")))) -> ❌ EVITA | U14: =IFERROR(__xludf.DUMMYFUNCTION("SPARKLINE(CHOOSE(MATCH(H14, Motore!$C$1:$M$1, 0), Motore!AA12:AA31, Motore!AB12:AB31, Motore!AC12:AC31, Motore!AD12:AD31, Motore!AE12:AE31, Motore!AF12:AF31, Motore!AG12:AG31, Motore!AH12:AH31, Motore!AI12:AI31, Motore!AJ12:AJ31, Motore!AK12:A"&"K31), {""charttype"",""line""; ""linewidth"",2; ""color"",IF(R14>0.01, ""#008000"", IF(R14<-0.01, ""#FF0000"", ""#FFFF00""))})"),"")
H15: SPY | I15: =D31-$D$31 -> 0 | J15: =(E31-$E$31) -> 0 | K15: =(F31-$F$31) -> 0 | L15: =(G31-$G$31) -> 0 | M15: =(H31-$H$31) -> 0 | N15: =(J31-$J$31) -> 0
A19: ticker | B19: Nome Etf | C19: Prezzo corrente | D19: Var. % giornaliera | E19: Var. % settimanale | F19: Var. % mensile | G19: Var. % trimestrale | H19: Var.%semestrale | I19: Var. % Ytd | J19: Var. % annuale | K19: Var. % 2 anni | L19: Var. % 3 anni | M19: Var. % 5 anni | N19: Var.% 10 anni | O19: Var. % 20 anni
A20: XLK | B20: =IFERROR(__xludf.DUMMYFUNCTION("GOOGLEFINANCE(A20,""name"")"),"State Street Technology Select Sector SPDR ETF") -> State Street Technology Select Sector SPDR ETF | C20: =IFERROR(__xludf.DUMMYFUNCTION("GOOGLEFINANCE(A20,""price"")"),145.09) -> 145.09 | D20: =IFERROR(__xludf.DUMMYFUNCTION("GOOGLEFINANCE(A20,""changepct"")"),0.14) -> 0.14 | E20: =IFERROR(__xludf.DUMMYFUNCTION(" ((GOOGLEFINANCE(A20,""price"") - INDEX(GOOGLEFINANCE(A20,""price"",TODAY()-7),2,2)) / INDEX(GOOGLEFINANCE(A20,""price"",TODAY()-7),2,2)) "),0.022913141567963903) -> 0.022913142 | F20: =IFERROR(__xludf.DUMMYFUNCTION(" ((GOOGLEFINANCE(A20,""price"") - INDEX(GOOGLEFINANCE(A20,""price"",TODAY()-30),2,2)) / INDEX(GOOGLEFINANCE(A20,""price"",TODAY()-30),2,2)) "),-0.00982733911144474) -> -0.0098273391 | G20: =IFERROR(__xludf.DUMMYFUNCTION(" ((GOOGLEFINANCE(A20,""price"") - INDEX(GOOGLEFINANCE(A20,""price"",TODAY()-90),2,2)) / INDEX(GOOGLEFINANCE(A20,""price"",TODAY()-90),2,2))"),-0.0294983277591973) -> -0.029498328 | H20: =IFERROR(__xludf.DUMMYFUNCTION(" ((GOOGLEFINANCE(A20,""price"") - INDEX(GOOGLEFINANCE(A20,""price"",TODAY()-182),2,2)) / INDEX(GOOGLEFINANCE(A20,""price"",TODAY()-182),2,2))"),0.09883368676158749) -> 0.098833687 | I20: =IFERROR(__xludf.DUMMYFUNCTION("(GOOGLEFINANCE(A20,""price"")-INDEX(GOOGLEFINANCE(A20,""price"",""01-01-""&YEAR(TODAY())),2,2))/INDEX(GOOGLEFINANCE(A20,""price"",""01-01-""&YEAR(TODAY())),2,2)"),0.005474705474705419) -> 0.0054747055 | J20: =IFERROR(__xludf.DUMMYFUNCTION(" ((GOOGLEFINANCE(A20,""price"") - INDEX(GOOGLEFINANCE(A20,""price"",TODAY()-365),2,2)) / INDEX(GOOGLEFINANCE(A20,""price"",TODAY()-365),2,2)) "),0.21262014208106975) -> 0.21262014 | K20: =IFERROR(__xludf.DUMMYFUNCTION(" ((GOOGLEFINANCE(A20,""price"") - INDEX(GOOGLEFINANCE(A20,""price"",TODAY()-730),2,2)) / INDEX(GOOGLEFINANCE(A20,""price"",TODAY()-730),2,2))"),0.4217540421362078) -> 0.42175404 | L20: =IFERROR(__xludf.DUMMYFUNCTION(" ((GOOGLEFINANCE(A20,""price"") - INDEX(GOOGLEFINANCE(A20,""price"",TODAY()-1095),2,2)) / INDEX(GOOGLEFINANCE(A20,""price"",TODAY()-1095),2,2))"),1.1655223880597017) -> 1.1655224 | M20: =IFERROR(__xludf.DUMMYFUNCTION(" ((GOOGLEFINANCE(A20,""price"") - INDEX(GOOGLEFINANCE(A20,""price"",TODAY()-1825),2,2)) / INDEX(GOOGLEFINANCE(A20,""price"",TODAY()-1825),2,2))"),1.166492459310139) -> 1.1664925 | N20: =IFERROR(__xludf.DUMMYFUNCTION(" ((GOOGLEFINANCE(A20,""price"") - INDEX(GOOGLEFINANCE(A20,""price"",TODAY()-3650),2,2)) / INDEX(GOOGLEFINANCE(A20,""price"",TODAY()-3650),2,2))"),6.3500506585612975) -> 6.3500507 | O20: =IFERROR(__xludf.DUMMYFUNCTION(" ((GOOGLEFINANCE(A20,""price"") - INDEX(GOOGLEFINANCE(A20,""price"",TODAY()-7300),2,2)) / INDEX(GOOGLEFINANCE(A20,""price"",TODAY()-7300),2,2))"),12.323232323232322) -> 12.323232
A21: XLY | B21: =IFERROR(__xludf.DUMMYFUNCTION("GOOGLEFINANCE(A21,""name"")"),"State Street Cons Disc Sel Sect SPDR Income ETF") -> State Street Cons Disc Sel Sect SPDR Income ETF | C21: =IFERROR(__xludf.DUMMYFUNCTION("GOOGLEFINANCE(A21,""price"")"),123.13) -> 123.13 | D21: =IFERROR(__xludf.DUMMYFUNCTION("GOOGLEFINANCE(A21,""changepct"")"),0.42) -> 0.42 | E21: =IFERROR(__xludf.DUMMYFUNCTION(" ((GOOGLEFINANCE(A21,""price"") - INDEX(GOOGLEFINANCE(A21,""price"",TODAY()-7),2,2)) / INDEX(GOOGLEFINANCE(A21,""price"",TODAY()-7),2,2)) "),0.03366353257219603) -> 0.033663533 | F21: =IFERROR(__xludf.DUMMYFUNCTION(" ((GOOGLEFINANCE(A21,""price"") - INDEX(GOOGLEFINANCE(A21,""price"",TODAY()-30),2,2)) / INDEX(GOOGLEFINANCE(A21,""price"",TODAY()-30),2,2)) "),0.008848832445718954) -> 0.0088488324 | G21: =IFERROR(__xludf.DUMMYFUNCTION(" ((GOOGLEFINANCE(A21,""price"") - INDEX(GOOGLEFINANCE(A21,""price"",TODAY()-90),2,2)) / INDEX(GOOGLEFINANCE(A21,""price"",TODAY()-90),2,2))"),0.02148664343786286) -> 0.021486643 | H21: =IFERROR(__xludf.DUMMYFUNCTION(" ((GOOGLEFINANCE(A21,""price"") - INDEX(GOOGLEFINANCE(A21,""price"",TODAY()-182),2,2)) / INDEX(GOOGLEFINANCE(A21,""price"",TODAY()-182),2,2))"),0.0887788487045715) -> 0.088778849 | I21: =IFERROR(__xludf.DUMMYFUNCTION("(GOOGLEFINANCE(A21,""price"")-INDEX(GOOGLEFINANCE(A21,""price"",""01-01-""&YEAR(TODAY())),2,2))/INDEX(GOOGLEFINANCE(A21,""price"",""01-01-""&YEAR(TODAY())),2,2)"),0.04038867765103508) -> 0.040388678 | J21: =IFERROR(__xludf.DUMMYFUNCTION(" ((GOOGLEFINANCE(A21,""price"") - INDEX(GOOGLEFINANCE(A21,""price"",TODAY()-365),2,2)) / INDEX(GOOGLEFINANCE(A21,""price"",TODAY()-365),2,2)) "),0.07060255629945214) -> 0.070602556 | K21: =IFERROR(__xludf.DUMMYFUNCTION(" ((GOOGLEFINANCE(A21,""price"") - INDEX(GOOGLEFINANCE(A21,""price"",TODAY()-730),2,2)) / INDEX(GOOGLEFINANCE(A21,""price"",TODAY()-730),2,2))"),0.4409596255119952) -> 0.44095963 | L21: =IFERROR(__xludf.DUMMYFUNCTION(" ((GOOGLEFINANCE(A21,""price"") - INDEX(GOOGLEFINANCE(A21,""price"",TODAY()-1095),2,2)) / INDEX(GOOGLEFINANCE(A21,""price"",TODAY()-1095),2,2))"),0.7376517075924357) -> 0.73765171 | M21: =IFERROR(__xludf.DUMMYFUNCTION(" ((GOOGLEFINANCE(A21,""price"") - INDEX(GOOGLEFINANCE(A21,""price"",TODAY()-1825),2,2)) / INDEX(GOOGLEFINANCE(A21,""price"",TODAY()-1825),2,2))"),0.4423099449455311) -> 0.44230994 | N21: =IFERROR(__xludf.DUMMYFUNCTION(" ((GOOGLEFINANCE(A21,""price"") - INDEX(GOOGLEFINANCE(A21,""price"",TODAY()-3650),2,2)) / INDEX(GOOGLEFINANCE(A21,""price"",TODAY()-3650),2,2))"),2.402321083172147) -> 2.4023211 | O21: =IFERROR(__xludf.DUMMYFUNCTION(" ((GOOGLEFINANCE(A21,""price"") - INDEX(GOOGLEFINANCE(A21,""price"",TODAY()-7300),2,2)) / INDEX(GOOGLEFINANCE(A21,""price"",TODAY()-7300),2,2))"),6.381894484412469) -> 6.3818945
A22: XLF | B22: =IFERROR(__xludf.DUMMYFUNCTION("GOOGLEFINANCE(A22,""name"")"),"State Street Financial Sel Sec SPDR ETF") -> State Street Financial Sel Sec SPDR ETF | C22: =IFERROR(__xludf.DUMMYFUNCTION("GOOGLEFINANCE(A22,""price"")"),53.07) -> 53.07 | D22: =IFERROR(__xludf.DUMMYFUNCTION("GOOGLEFINANCE(A22,""changepct"")"),-1.38) -> -1.38 | E22: =IFERROR(__xludf.DUMMYFUNCTION(" ((GOOGLEFINANCE(A22,""price"") - INDEX(GOOGLEFINANCE(A22,""price"",TODAY()-7),2,2)) / INDEX(GOOGLEFINANCE(A22,""price"",TODAY()-7),2,2)) "),-0.0024436090225564387) -> -0.002443609 | F22: =IFERROR(__xludf.DUMMYFUNCTION(" ((GOOGLEFINANCE(A22,""price"") - INDEX(GOOGLEFINANCE(A22,""price"",TODAY()-30),2,2)) / INDEX(GOOGLEFINANCE(A22,""price"",TODAY()-30),2,2)) "),-0.04584681769147784) -> -0.045846818 | G22: =IFERROR(__xludf.DUMMYFUNCTION(" ((GOOGLEFINANCE(A22,""price"") - INDEX(GOOGLEFINANCE(A22,""price"",TODAY()-90),2,2)) / INDEX(GOOGLEFINANCE(A22,""price"",TODAY()-90),2,2))"),-0.004875304706544122) -> -0.0048753047 | H22: =IFERROR(__xludf.DUMMYFUNCTION(" ((GOOGLEFINANCE(A22,""price"") - INDEX(GOOGLEFINANCE(A22,""price"",TODAY()-182),2,2)) / INDEX(GOOGLEFINANCE(A22,""price"",TODAY()-182),2,2))"),0.0) -> 0 | I22: =IFERROR(__xludf.DUMMYFUNCTION("(GOOGLEFINANCE(A22,""price"")-INDEX(GOOGLEFINANCE(A22,""price"",""01-01-""&YEAR(TODAY())),2,2))/INDEX(GOOGLEFINANCE(A22,""price"",""01-01-""&YEAR(TODAY())),2,2)"),-0.033861277990169296) -> -0.033861278 | J22: =IFERROR(__xludf.DUMMYFUNCTION(" ((GOOGLEFINANCE(A22,""price"") - INDEX(GOOGLEFINANCE(A22,""price"",TODAY()-365),2,2)) / INDEX(GOOGLEFINANCE(A22,""price"",TODAY()-365),2,2)) "),0.04365781710914452) -> 0.043657817 | K22: =IFERROR(__xludf.DUMMYFUNCTION(" ((GOOGLEFINANCE(A22,""price"") - INDEX(GOOGLEFINANCE(A22,""price"",TODAY()-730),2,2)) / INDEX(GOOGLEFINANCE(A22,""price"",TODAY()-730),2,2))"),0.3780836146455467) -> 0.37808361 | L22: =IFERROR(__xludf.DUMMYFUNCTION(" ((GOOGLEFINANCE(A22,""price"") - INDEX(GOOGLEFINANCE(A22,""price"",TODAY()-1095),2,2)) / INDEX(GOOGLEFINANCE(A22,""price"",TODAY()-1095),2,2))"),0.4717138103161397) -> 0.47171381 | M22: =IFERROR(__xludf.DUMMYFUNCTION(" ((GOOGLEFINANCE(A22,""price"") - INDEX(GOOGLEFINANCE(A22,""price"",TODAY()-1825),2,2)) / INDEX(GOOGLEFINANCE(A22,""price"",TODAY()-1825),2,2))"),0.7619521912350598) -> 0.76195219 | N22: =IFERROR(__xludf.DUMMYFUNCTION(" ((GOOGLEFINANCE(A22,""price"") - INDEX(GOOGLEFINANCE(A22,""price"",TODAY()-3650),2,2)) / INDEX(GOOGLEFINANCE(A22,""price"",TODAY()-3650),2,2))"),2.809763101220388) -> 2.8097631 | O22: =IFERROR(__xludf.DUMMYFUNCTION(" ((GOOGLEFINANCE(A22,""price"") - INDEX(GOOGLEFINANCE(A22,""price"",TODAY()-7300),2,2)) / INDEX(GOOGLEFINANCE(A22,""price"",TODAY()-7300),2,2))"),1.5092198581560285) -> 1.5092199
A23: XLC | B23: =IFERROR(__xludf.DUMMYFUNCTION("GOOGLEFINANCE(A23,""name"")"),"State Street Com Svc Sel Sec SPDR ETF") -> State Street Com Svc Sel Sec SPDR ETF | C23: =IFERROR(__xludf.DUMMYFUNCTION("GOOGLEFINANCE(A23,""price"")"),116.96) -> 116.96 | D23: =IFERROR(__xludf.DUMMYFUNCTION("GOOGLEFINANCE(A23,""changepct"")"),0.61) -> 0.61 | E23: =IFERROR(__xludf.DUMMYFUNCTION(" ((GOOGLEFINANCE(A23,""price"") - INDEX(GOOGLEFINANCE(A23,""price"",TODAY()-7),2,2)) / INDEX(GOOGLEFINANCE(A23,""price"",TODAY()-7),2,2)) "),0.03075702828941566) -> 0.030757028 | F23: =IFERROR(__xludf.DUMMYFUNCTION(" ((GOOGLEFINANCE(A23,""price"") - INDEX(GOOGLEFINANCE(A23,""price"",TODAY()-30),2,2)) / INDEX(GOOGLEFINANCE(A23,""price"",TODAY()-30),2,2)) "),-0.008561498686106681) -> -0.0085614987 | G23: =IFERROR(__xludf.DUMMYFUNCTION(" ((GOOGLEFINANCE(A23,""price"") - INDEX(GOOGLEFINANCE(A23,""price"",TODAY()-90),2,2)) / INDEX(GOOGLEFINANCE(A23,""price"",TODAY()-90),2,2))"),-0.0017070672584500073) -> -0.0017070673 | H23: =IFERROR(__xludf.DUMMYFUNCTION(" ((GOOGLEFINANCE(A23,""price"") - INDEX(GOOGLEFINANCE(A23,""price"",TODAY()-182),2,2)) / INDEX(GOOGLEFINANCE(A23,""price"",TODAY()-182),2,2))"),0.09267563527653201) -> 0.092675635 | I23: =IFERROR(__xludf.DUMMYFUNCTION("(GOOGLEFINANCE(A23,""price"")-INDEX(GOOGLEFINANCE(A23,""price"",""01-01-""&YEAR(TODAY())),2,2))/INDEX(GOOGLEFINANCE(A23,""price"",""01-01-""&YEAR(TODAY())),2,2)"),5.132591958938243E-4) -> 0.0005132592 | J23: =IFERROR(__xludf.DUMMYFUNCTION(" ((GOOGLEFINANCE(A23,""price"") - INDEX(GOOGLEFINANCE(A23,""price"",TODAY()-365),2,2)) / INDEX(GOOGLEFINANCE(A23,""price"",TODAY()-365),2,2)) "),0.16482422069514988) -> 0.16482422 | K23: =IFERROR(__xludf.DUMMYFUNCTION(" ((GOOGLEFINANCE(A23,""price"") - INDEX(GOOGLEFINANCE(A23,""price"",TODAY()-730),2,2)) / INDEX(GOOGLEFINANCE(A23,""price"",TODAY()-730),2,2))"),0.5105256360583751) -> 0.51052564 | L23: =IFERROR(__xludf.DUMMYFUNCTION(" ((GOOGLEFINANCE(A23,""price"") - INDEX(GOOGLEFINANCE(A23,""price"",TODAY()-1095),2,2)) / INDEX(GOOGLEFINANCE(A23,""price"",TODAY()-1095),2,2))"),1.1631218790456814) -> 1.1631219 | M23: =IFERROR(__xludf.DUMMYFUNCTION(" ((GOOGLEFINANCE(A23,""price"") - INDEX(GOOGLEFINANCE(A23,""price"",TODAY()-1825),2,2)) / INDEX(GOOGLEFINANCE(A23,""price"",TODAY()-1825),2,2))"),0.6891969959560947) -> 0.689197
A24: XLV | B24: =IFERROR(__xludf.DUMMYFUNCTION("GOOGLEFINANCE(A24,""name"")"),"State Street Health Care Select Sector SPDR ETF") -> State Street Health Care Select Sector SPDR ETF | C24: =IFERROR(__xludf.DUMMYFUNCTION("GOOGLEFINANCE(A24,""price"")"),157.48) -> 157.48 | D24: =IFERROR(__xludf.DUMMYFUNCTION("GOOGLEFINANCE(A24,""changepct"")"),-0.51) -> -0.51 | E24: =IFERROR(__xludf.DUMMYFUNCTION(" ((GOOGLEFINANCE(A24,""price"") - INDEX(GOOGLEFINANCE(A24,""price"",TODAY()-7),2,2)) / INDEX(GOOGLEFINANCE(A24,""price"",TODAY()-7),2,2)) "),0.013384813384813283) -> 0.013384813 | F24: =IFERROR(__xludf.DUMMYFUNCTION(" ((GOOGLEFINANCE(A24,""price"") - INDEX(GOOGLEFINANCE(A24,""price"",TODAY()-30),2,2)) / INDEX(GOOGLEFINANCE(A24,""price"",TODAY()-30),2,2)) "),0.009163729573854395) -> 0.0091637296 | G24: =IFERROR(__xludf.DUMMYFUNCTION(" ((GOOGLEFINANCE(A24,""price"") - INDEX(GOOGLEFINANCE(A24,""price"",TODAY()-90),2,2)) / INDEX(GOOGLEFINANCE(A24,""price"",TODAY()-90),2,2))"),0.07590353214456504) -> 0.075903532 | H24: =IFERROR(__xludf.DUMMYFUNCTION(" ((GOOGLEFINANCE(A24,""price"") - INDEX(GOOGLEFINANCE(A24,""price"",TODAY()-182),2,2)) / INDEX(GOOGLEFINANCE(A24,""price"",TODAY()-182),2,2))"),0.16401803533151008) -> 0.16401804 | I24: =IFERROR(__xludf.DUMMYFUNCTION("(GOOGLEFINANCE(A24,""price"")-INDEX(GOOGLEFINANCE(A24,""price"",""01-01-""&YEAR(TODAY())),2,2))/INDEX(GOOGLEFINANCE(A24,""price"",""01-01-""&YEAR(TODAY())),2,2)"),0.012667995627290842) -> 0.012667996 | J24: =IFERROR(__xludf.DUMMYFUNCTION(" ((GOOGLEFINANCE(A24,""price"") - INDEX(GOOGLEFINANCE(A24,""price"",TODAY()-365),2,2)) / INDEX(GOOGLEFINANCE(A24,""price"",TODAY()-365),2,2)) "),0.09126186681449648) -> 0.091261867 | K24: =IFERROR(__xludf.DUMMYFUNCTION(" ((GOOGLEFINANCE(A24,""price"") - INDEX(GOOGLEFINANCE(A24,""price"",TODAY()-730),2,2)) / INDEX(GOOGLEFINANCE(A24,""price"",TODAY()-730),2,2))"),0.1372039283651069) -> 0.13720393 | L24: =IFERROR(__xludf.DUMMYFUNCTION(" ((GOOGLEFINANCE(A24,""price"") - INDEX(GOOGLEFINANCE(A24,""price"",TODAY()-1095),2,2)) / INDEX(GOOGLEFINANCE(A24,""price"",TODAY()-1095),2,2))"),0.1794487717195924) -> 0.17944877 | M24: =IFERROR(__xludf.DUMMYFUNCTION(" ((GOOGLEFINANCE(A24,""price"") - INDEX(GOOGLEFINANCE(A24,""price"",TODAY()-1825),2,2)) / INDEX(GOOGLEFINANCE(A24,""price"",TODAY()-1825),2,2))"),0.33051706657654606) -> 0.33051707 | N24: =IFERROR(__xludf.DUMMYFUNCTION(" ((GOOGLEFINANCE(A24,""price"") - INDEX(GOOGLEFINANCE(A24,""price"",TODAY()-3650),2,2)) / INDEX(GOOGLEFINANCE(A24,""price"",TODAY()-3650),2,2))"),1.3518518518518519) -> 1.3518519 | O24: =IFERROR(__xludf.DUMMYFUNCTION(" ((GOOGLEFINANCE(A24,""price"") - INDEX(GOOGLEFINANCE(A24,""price"",TODAY()-7300),2,2)) / INDEX(GOOGLEFINANCE(A24,""price"",TODAY()-7300),2,2))"),3.8998133167392655) -> 3.8998133
A25: XLP | B25: =IFERROR(__xludf.DUMMYFUNCTION("GOOGLEFINANCE(A25,""name"")"),"State Street Cons Staples Sel Sec SPDR Inc ETF") -> State Street Cons Staples Sel Sec SPDR Inc ETF | C25: =IFERROR(__xludf.DUMMYFUNCTION("GOOGLEFINANCE(A25,""price"")"),82.91) -> 82.91 | D25: =IFERROR(__xludf.DUMMYFUNCTION("GOOGLEFINANCE(A25,""changepct"")"),0.78) -> 0.78 | E25: =IFERROR(__xludf.DUMMYFUNCTION(" ((GOOGLEFINANCE(A25,""price"") - INDEX(GOOGLEFINANCE(A25,""price"",TODAY()-7),2,2)) / INDEX(GOOGLEFINANCE(A25,""price"",TODAY()-7),2,2)) "),0.006677999028654652) -> 0.006677999 | F25: =IFERROR(__xludf.DUMMYFUNCTION(" ((GOOGLEFINANCE(A25,""price"") - INDEX(GOOGLEFINANCE(A25,""price"",TODAY()-30),2,2)) / INDEX(GOOGLEFINANCE(A25,""price"",TODAY()-30),2,2)) "),0.05982359708551697) -> 0.059823597 | G25: =IFERROR(__xludf.DUMMYFUNCTION(" ((GOOGLEFINANCE(A25,""price"") - INDEX(GOOGLEFINANCE(A25,""price"",TODAY()-90),2,2)) / INDEX(GOOGLEFINANCE(A25,""price"",TODAY()-90),2,2))"),0.04657914668013125) -> 0.046579147 | H25: =IFERROR(__xludf.DUMMYFUNCTION(" ((GOOGLEFINANCE(A25,""price"") - INDEX(GOOGLEFINANCE(A25,""price"",TODAY()-182),2,2)) / INDEX(GOOGLEFINANCE(A25,""price"",TODAY()-182),2,2))"),0.02789486734440863) -> 0.027894867 | I25: =IFERROR(__xludf.DUMMYFUNCTION("(GOOGLEFINANCE(A25,""price"")-INDEX(GOOGLEFINANCE(A25,""price"",""01-01-""&YEAR(TODAY())),2,2))/INDEX(GOOGLEFINANCE(A25,""price"",""01-01-""&YEAR(TODAY())),2,2)"),0.06719011455785814) -> 0.067190115 | J25: =IFERROR(__xludf.DUMMYFUNCTION(" ((GOOGLEFINANCE(A25,""price"") - INDEX(GOOGLEFINANCE(A25,""price"",TODAY()-365),2,2)) / INDEX(GOOGLEFINANCE(A25,""price"",TODAY()-365),2,2)) "),0.0643132220795891) -> 0.064313222 | K25: =IFERROR(__xludf.DUMMYFUNCTION(" ((GOOGLEFINANCE(A25,""price"") - INDEX(GOOGLEFINANCE(A25,""price"",TODAY()-730),2,2)) / INDEX(GOOGLEFINANCE(A25,""price"",TODAY()-730),2,2))"),0.14706696181516318) -> 0.14706696 | L25: =IFERROR(__xludf.DUMMYFUNCTION(" ((GOOGLEFINANCE(A25,""price"") - INDEX(GOOGLEFINANCE(A25,""price"",TODAY()-1095),2,2)) / INDEX(GOOGLEFINANCE(A25,""price"",TODAY()-1095),2,2))"),0.13064230192281465) -> 0.1306423 | M25: =IFERROR(__xludf.DUMMYFUNCTION(" ((GOOGLEFINANCE(A25,""price"") - INDEX(GOOGLEFINANCE(A25,""price"",TODAY()-1825),2,2)) / INDEX(GOOGLEFINANCE(A25,""price"",TODAY()-1825),2,2))"),0.26156421180766887) -> 0.26156421 | N25: =IFERROR(__xludf.DUMMYFUNCTION(" ((GOOGLEFINANCE(A25,""price"") - INDEX(GOOGLEFINANCE(A25,""price"",TODAY()-3650),2,2)) / INDEX(GOOGLEFINANCE(A25,""price"",TODAY()-3650),2,2))"),0.6834517766497461) -> 0.68345178 | O25: =IFERROR(__xludf.DUMMYFUNCTION(" ((GOOGLEFINANCE(A25,""price"") - INDEX(GOOGLEFINANCE(A25,""price"",TODAY()-7300),2,2)) / INDEX(GOOGLEFINANCE(A25,""price"",TODAY()-7300),2,2))"),2.537116040955631) -> 2.537116
A26: XLI | B26: =IFERROR(__xludf.DUMMYFUNCTION("GOOGLEFINANCE(A26,""name"")"),"State Street Industrial Select Sector SPDR ETF") -> State Street Industrial Select Sector SPDR ETF | C26: =IFERROR(__xludf.DUMMYFUNCTION("GOOGLEFINANCE(A26,""price"")"),164.22) -> 164.22 | D26: =IFERROR(__xludf.DUMMYFUNCTION("GOOGLEFINANCE(A26,""changepct"")"),-0.77) -> -0.77 | E26: =IFERROR(__xludf.DUMMYFUNCTION(" ((GOOGLEFINANCE(A26,""price"") - INDEX(GOOGLEFINANCE(A26,""price"",TODAY()-7),2,2)) / INDEX(GOOGLEFINANCE(A26,""price"",TODAY()-7),2,2)) "),0.004219409282700408) -> 0.0042194093 | F26: =IFERROR(__xludf.DUMMYFUNCTION(" ((GOOGLEFINANCE(A26,""price"") - INDEX(GOOGLEFINANCE(A26,""price"",TODAY()-30),2,2)) / INDEX(GOOGLEFINANCE(A26,""price"",TODAY()-30),2,2)) "),0.044590038801602894) -> 0.044590039 | G26: =IFERROR(__xludf.DUMMYFUNCTION(" ((GOOGLEFINANCE(A26,""price"") - INDEX(GOOGLEFINANCE(A26,""price"",TODAY()-90),2,2)) / INDEX(GOOGLEFINANCE(A26,""price"",TODAY()-90),2,2))"),0.05411130367802816) -> 0.054111304 | H26: =IFERROR(__xludf.DUMMYFUNCTION(" ((GOOGLEFINANCE(A26,""price"") - INDEX(GOOGLEFINANCE(A26,""price"",TODAY()-182),2,2)) / INDEX(GOOGLEFINANCE(A26,""price"",TODAY()-182),2,2))"),0.06284382887838981) -> 0.062843829 | I26: =IFERROR(__xludf.DUMMYFUNCTION("(GOOGLEFINANCE(A26,""price"")-INDEX(GOOGLEFINANCE(A26,""price"",""01-01-""&YEAR(TODAY())),2,2))/INDEX(GOOGLEFINANCE(A26,""price"",""01-01-""&YEAR(TODAY())),2,2)"),0.03949867071781244) -> 0.039498671 | J26: =IFERROR(__xludf.DUMMYFUNCTION(" ((GOOGLEFINANCE(A26,""price"") - INDEX(GOOGLEFINANCE(A26,""price"",TODAY()-365),2,2)) / INDEX(GOOGLEFINANCE(A26,""price"",TODAY()-365),2,2)) "),0.1641029276245836) -> 0.16410293 | K26: =IFERROR(__xludf.DUMMYFUNCTION(" ((GOOGLEFINANCE(A26,""price"") - INDEX(GOOGLEFINANCE(A26,""price"",TODAY()-730),2,2)) / INDEX(GOOGLEFINANCE(A26,""price"",TODAY()-730),2,2))"),0.4454713493530499) -> 0.44547135 | L26: =IFERROR(__xludf.DUMMYFUNCTION(" ((GOOGLEFINANCE(A26,""price"") - INDEX(GOOGLEFINANCE(A26,""price"",TODAY()-1095),2,2)) / INDEX(GOOGLEFINANCE(A26,""price"",TODAY()-1095),2,2))"),0.6394129979035639) -> 0.639413 | M26: =IFERROR(__xludf.DUMMYFUNCTION(" ((GOOGLEFINANCE(A26,""price"") - INDEX(GOOGLEFINANCE(A26,""price"",TODAY()-1825),2,2)) / INDEX(GOOGLEFINANCE(A26,""price"",TODAY()-1825),2,2))"),0.8680468661130702) -> 0.86804687 | N26: =IFERROR(__xludf.DUMMYFUNCTION(" ((GOOGLEFINANCE(A26,""price"") - INDEX(GOOGLEFINANCE(A26,""price"",TODAY()-3650),2,2)) / INDEX(GOOGLEFINANCE(A26,""price"",TODAY()-3650),2,2))"),2.3929752066115704) -> 2.3929752 | O26: =IFERROR(__xludf.DUMMYFUNCTION(" ((GOOGLEFINANCE(A26,""price"") - INDEX(GOOGLEFINANCE(A26,""price"",TODAY()-7300),2,2)) / INDEX(GOOGLEFINANCE(A26,""price"",TODAY()-7300),2,2))"),4.1820763647838435) -> 4.1820764
A27: XLE | B27: =IFERROR(__xludf.DUMMYFUNCTION("GOOGLEFINANCE(A27,""name"")"),"State Street Energy Select Sector SPDR ETF") -> State Street Energy Select Sector SPDR ETF | C27: =IFERROR(__xludf.DUMMYFUNCTION("GOOGLEFINANCE(A27,""price"")"),49.19) -> 49.19 | D27: =IFERROR(__xludf.DUMMYFUNCTION("GOOGLEFINANCE(A27,""changepct"")"),0.57) -> 0.57 | E27: =IFERROR(__xludf.DUMMYFUNCTION(" ((GOOGLEFINANCE(A27,""price"") - INDEX(GOOGLEFINANCE(A27,""price"",TODAY()-7),2,2)) / INDEX(GOOGLEFINANCE(A27,""price"",TODAY()-7),2,2)) "),0.03340336134453774) -> 0.033403361 | F27: =IFERROR(__xludf.DUMMYFUNCTION(" ((GOOGLEFINANCE(A27,""price"") - INDEX(GOOGLEFINANCE(A27,""price"",TODAY()-30),2,2)) / INDEX(GOOGLEFINANCE(A27,""price"",TODAY()-30),2,2)) "),0.11289592760180983) -> 0.11289593 | G27: =IFERROR(__xludf.DUMMYFUNCTION(" ((GOOGLEFINANCE(A27,""price"") - INDEX(GOOGLEFINANCE(A27,""price"",TODAY()-90),2,2)) / INDEX(GOOGLEFINANCE(A27,""price"",TODAY()-90),2,2))"),0.11440869959220655) -> 0.1144087 | H27: =IFERROR(__xludf.DUMMYFUNCTION(" ((GOOGLEFINANCE(A27,""price"") - INDEX(GOOGLEFINANCE(A27,""price"",TODAY()-182),2,2)) / INDEX(GOOGLEFINANCE(A27,""price"",TODAY()-182),2,2))"),0.11668558456299662) -> 0.11668558 | I27: =IFERROR(__xludf.DUMMYFUNCTION("(GOOGLEFINANCE(A27,""price"")-INDEX(GOOGLEFINANCE(A27,""price"",""01-01-""&YEAR(TODAY())),2,2))/INDEX(GOOGLEFINANCE(A27,""price"",""01-01-""&YEAR(TODAY())),2,2)"),0.07754654983570644) -> 0.07754655 | J27: =IFERROR(__xludf.DUMMYFUNCTION(" ((GOOGLEFINANCE(A27,""price"") - INDEX(GOOGLEFINANCE(A27,""price"",TODAY()-365),2,2)) / INDEX(GOOGLEFINANCE(A27,""price"",TODAY()-365),2,2)) "),0.07731055628558917) -> 0.077310556 | K27: =IFERROR(__xludf.DUMMYFUNCTION(" ((GOOGLEFINANCE(A27,""price"") - INDEX(GOOGLEFINANCE(A27,""price"",TODAY()-730),2,2)) / INDEX(GOOGLEFINANCE(A27,""price"",TODAY()-730),2,2))"),0.17623146819703486) -> 0.17623147 | L27: =IFERROR(__xludf.DUMMYFUNCTION(" ((GOOGLEFINANCE(A27,""price"") - INDEX(GOOGLEFINANCE(A27,""price"",TODAY()-1095),2,2)) / INDEX(GOOGLEFINANCE(A27,""price"",TODAY()-1095),2,2))"),0.08996233104365156) -> 0.089962331 | M27: =IFERROR(__xludf.DUMMYFUNCTION(" ((GOOGLEFINANCE(A27,""price"") - INDEX(GOOGLEFINANCE(A27,""price"",TODAY()-1825),2,2)) / INDEX(GOOGLEFINANCE(A27,""price"",TODAY()-1825),2,2))"),1.3626320845341018) -> 1.3626321 | N27: =IFERROR(__xludf.DUMMYFUNCTION(" ((GOOGLEFINANCE(A27,""price"") - INDEX(GOOGLEFINANCE(A27,""price"",TODAY()-3650),2,2)) / INDEX(GOOGLEFINANCE(A27,""price"",TODAY()-3650),2,2))"),0.7919854280510018) -> 0.79198543 | O27: =IFERROR(__xludf.DUMMYFUNCTION(" ((GOOGLEFINANCE(A27,""price"") - INDEX(GOOGLEFINANCE(A27,""price"",TODAY()-7300),2,2)) / INDEX(GOOGLEFINANCE(A27,""price"",TODAY()-7300),2,2))"),0.6973775017253278) -> 0.6973775
A28: XLB | B28: =IFERROR(__xludf.DUMMYFUNCTION("GOOGLEFINANCE(A28,""name"")"),"State Street Materials Select Sector SPDR ETF") -> State Street Materials Select Sector SPDR ETF | C28: =IFERROR(__xludf.DUMMYFUNCTION("GOOGLEFINANCE(A28,""price"")"),49.97) -> 49.97 | D28: =IFERROR(__xludf.DUMMYFUNCTION("GOOGLEFINANCE(A28,""changepct"")"),0.91) -> 0.91 | E28: =IFERROR(__xludf.DUMMYFUNCTION(" ((GOOGLEFINANCE(A28,""price"") - INDEX(GOOGLEFINANCE(A28,""price"",TODAY()-7),2,2)) / INDEX(GOOGLEFINANCE(A28,""price"",TODAY()-7),2,2)) "),0.03693712388462339) -> 0.036937124 | F28: =IFERROR(__xludf.DUMMYFUNCTION(" ((GOOGLEFINANCE(A28,""price"") - INDEX(GOOGLEFINANCE(A28,""price"",TODAY()-30),2,2)) / INDEX(GOOGLEFINANCE(A28,""price"",TODAY()-30),2,2)) "),0.08371286055085664) -> 0.083712861 | G28: =IFERROR(__xludf.DUMMYFUNCTION(" ((GOOGLEFINANCE(A28,""price"") - INDEX(GOOGLEFINANCE(A28,""price"",TODAY()-90),2,2)) / INDEX(GOOGLEFINANCE(A28,""price"",TODAY()-90),2,2))"),0.12317374690941778) -> 0.12317375 | H28: =IFERROR(__xludf.DUMMYFUNCTION(" ((GOOGLEFINANCE(A28,""price"") - INDEX(GOOGLEFINANCE(A28,""price"",TODAY()-182),2,2)) / INDEX(GOOGLEFINANCE(A28,""price"",TODAY()-182),2,2))"),0.09775922671353242) -> 0.097759227 | I28: =IFERROR(__xludf.DUMMYFUNCTION("(GOOGLEFINANCE(A28,""price"")-INDEX(GOOGLEFINANCE(A28,""price"",""01-01-""&YEAR(TODAY())),2,2))/INDEX(GOOGLEFINANCE(A28,""price"",""01-01-""&YEAR(TODAY())),2,2)"),0.08347788378143976) -> 0.083477884 | J28: =IFERROR(__xludf.DUMMYFUNCTION(" ((GOOGLEFINANCE(A28,""price"") - INDEX(GOOGLEFINANCE(A28,""price"",TODAY()-365),2,2)) / INDEX(GOOGLEFINANCE(A28,""price"",TODAY()-365),2,2)) "),0.12292134831460672) -> 0.12292135 | K28: =IFERROR(__xludf.DUMMYFUNCTION(" ((GOOGLEFINANCE(A28,""price"") - INDEX(GOOGLEFINANCE(A28,""price"",TODAY()-730),2,2)) / INDEX(GOOGLEFINANCE(A28,""price"",TODAY()-730),2,2))"),0.21168768186226955) -> 0.21168768 | L28: =IFERROR(__xludf.DUMMYFUNCTION(" ((GOOGLEFINANCE(A28,""price"") - INDEX(GOOGLEFINANCE(A28,""price"",TODAY()-1095),2,2)) / INDEX(GOOGLEFINANCE(A28,""price"",TODAY()-1095),2,2))"),0.20004803073967334) -> 0.20004803 | M28: =IFERROR(__xludf.DUMMYFUNCTION(" ((GOOGLEFINANCE(A28,""price"") - INDEX(GOOGLEFINANCE(A28,""price"",TODAY()-1825),2,2)) / INDEX(GOOGLEFINANCE(A28,""price"",TODAY()-1825),2,2))"),0.35090565017572306) -> 0.35090565 | N28: =IFERROR(__xludf.DUMMYFUNCTION(" ((GOOGLEFINANCE(A28,""price"") - INDEX(GOOGLEFINANCE(A28,""price"",TODAY()-3650),2,2)) / INDEX(GOOGLEFINANCE(A28,""price"",TODAY()-3650),2,2))"),1.6565656565656568) -> 1.6565657 | O28: =IFERROR(__xludf.DUMMYFUNCTION(" ((GOOGLEFINANCE(A28,""price"") - INDEX(GOOGLEFINANCE(A28,""price"",TODAY()-7300),2,2)) / INDEX(GOOGLEFINANCE(A28,""price"",TODAY()-7300),2,2))"),2.1526813880126183) -> 2.1526814
A29: XLU | B29: =IFERROR(__xludf.DUMMYFUNCTION("GOOGLEFINANCE(A29,""name"")"),"State Street Utilities Select Sector SPDR ETF") -> State Street Utilities Select Sector SPDR ETF | C29: =IFERROR(__xludf.DUMMYFUNCTION("GOOGLEFINANCE(A29,""price"")"),42.56) -> 42.56 | D29: =IFERROR(__xludf.DUMMYFUNCTION("GOOGLEFINANCE(A29,""changepct"")"),-0.35) -> -0.35 | E29: =IFERROR(__xludf.DUMMYFUNCTION(" ((GOOGLEFINANCE(A29,""price"") - INDEX(GOOGLEFINANCE(A29,""price"",TODAY()-7),2,2)) / INDEX(GOOGLEFINANCE(A29,""price"",TODAY()-7),2,2)) "),-0.009310986964618215) -> -0.009310987 | F29: =IFERROR(__xludf.DUMMYFUNCTION(" ((GOOGLEFINANCE(A29,""price"") - INDEX(GOOGLEFINANCE(A29,""price"",TODAY()-30),2,2)) / INDEX(GOOGLEFINANCE(A29,""price"",TODAY()-30),2,2)) "),-0.0051425899953248914) -> -0.00514259 | G29: =IFERROR(__xludf.DUMMYFUNCTION(" ((GOOGLEFINANCE(A29,""price"") - INDEX(GOOGLEFINANCE(A29,""price"",TODAY()-90),2,2)) / INDEX(GOOGLEFINANCE(A29,""price"",TODAY()-90),2,2))"),-0.0711479703186381) -> -0.07114797 | H29: =IFERROR(__xludf.DUMMYFUNCTION(" ((GOOGLEFINANCE(A29,""price"") - INDEX(GOOGLEFINANCE(A29,""price"",TODAY()-182),2,2)) / INDEX(GOOGLEFINANCE(A29,""price"",TODAY()-182),2,2))"),0.01793829227457546) -> 0.017938292 | I29: =IFERROR(__xludf.DUMMYFUNCTION("(GOOGLEFINANCE(A29,""price"")-INDEX(GOOGLEFINANCE(A29,""price"",""01-01-""&YEAR(TODAY())),2,2))/INDEX(GOOGLEFINANCE(A29,""price"",""01-01-""&YEAR(TODAY())),2,2)"),-0.014358499305233845) -> -0.014358499 | J29: =IFERROR(__xludf.DUMMYFUNCTION(" ((GOOGLEFINANCE(A29,""price"") - INDEX(GOOGLEFINANCE(A29,""price"",TODAY()-365),2,2)) / INDEX(GOOGLEFINANCE(A29,""price"",TODAY()-365),2,2)) "),0.07096124811273277) -> 0.070961248 | K29: =IFERROR(__xludf.DUMMYFUNCTION(" ((GOOGLEFINANCE(A29,""price"") - INDEX(GOOGLEFINANCE(A29,""price"",TODAY()-730),2,2)) / INDEX(GOOGLEFINANCE(A29,""price"",TODAY()-730),2,2))"),0.3944954128440368) -> 0.39449541 | L29: =IFERROR(__xludf.DUMMYFUNCTION(" ((GOOGLEFINANCE(A29,""price"") - INDEX(GOOGLEFINANCE(A29,""price"",TODAY()-1095),2,2)) / INDEX(GOOGLEFINANCE(A29,""price"",TODAY()-1095),2,2))"),0.23973201281677844) -> 0.23973201 | M29: =IFERROR(__xludf.DUMMYFUNCTION(" ((GOOGLEFINANCE(A29,""price"") - INDEX(GOOGLEFINANCE(A29,""price"",TODAY()-1825),2,2)) / INDEX(GOOGLEFINANCE(A29,""price"",TODAY()-1825),2,2))"),0.32792511700468036) -> 0.32792512 | N29: =IFERROR(__xludf.DUMMYFUNCTION(" ((GOOGLEFINANCE(A29,""price"") - INDEX(GOOGLEFINANCE(A29,""price"",TODAY()-3650),2,2)) / INDEX(GOOGLEFINANCE(A29,""price"",TODAY()-3650),2,2))"),0.9416058394160584) -> 0.94160584 | O29: =IFERROR(__xludf.DUMMYFUNCTION(" ((GOOGLEFINANCE(A29,""price"") - INDEX(GOOGLEFINANCE(A29,""price"",TODAY()-7300),2,2)) / INDEX(GOOGLEFINANCE(A29,""price"",TODAY()-7300),2,2))"),1.6451211932877565) -> 1.6451212
A30: XLRE | B30: =IFERROR(__xludf.DUMMYFUNCTION("GOOGLEFINANCE(A30,""name"")"),"State Street Real Estate Select Sector SPDR ETF") -> State Street Real Estate Select Sector SPDR ETF | C30: =IFERROR(__xludf.DUMMYFUNCTION("GOOGLEFINANCE(A30,""price"")"),41.25) -> 41.25 | D30: =IFERROR(__xludf.DUMMYFUNCTION("GOOGLEFINANCE(A30,""changepct"")"),0.27) -> 0.27 | E30: =IFERROR(__xludf.DUMMYFUNCTION(" ((GOOGLEFINANCE(A30,""price"") - INDEX(GOOGLEFINANCE(A30,""price"",TODAY()-7),2,2)) / INDEX(GOOGLEFINANCE(A30,""price"",TODAY()-7),2,2)) "),-0.0036231884057970672) -> -0.0036231884 | F30: =IFERROR(__xludf.DUMMYFUNCTION(" ((GOOGLEFINANCE(A30,""price"") - INDEX(GOOGLEFINANCE(A30,""price"",TODAY()-30),2,2)) / INDEX(GOOGLEFINANCE(A30,""price"",TODAY()-30),2,2)) "),0.018015794669299035) -> 0.018015795 | G30: =IFERROR(__xludf.DUMMYFUNCTION(" ((GOOGLEFINANCE(A30,""price"") - INDEX(GOOGLEFINANCE(A30,""price"",TODAY()-90),2,2)) / INDEX(GOOGLEFINANCE(A30,""price"",TODAY()-90),2,2))"),-0.034861956013102526) -> -0.034861956 | H30: =IFERROR(__xludf.DUMMYFUNCTION(" ((GOOGLEFINANCE(A30,""price"") - INDEX(GOOGLEFINANCE(A30,""price"",TODAY()-182),2,2)) / INDEX(GOOGLEFINANCE(A30,""price"",TODAY()-182),2,2))"),-0.01902497027348388) -> -0.01902497 | I30: =IFERROR(__xludf.DUMMYFUNCTION("(GOOGLEFINANCE(A30,""price"")-INDEX(GOOGLEFINANCE(A30,""price"",""01-01-""&YEAR(TODAY())),2,2))/INDEX(GOOGLEFINANCE(A30,""price"",""01-01-""&YEAR(TODAY())),2,2)"),0.021545319465081657) -> 0.021545319 | J30: =IFERROR(__xludf.DUMMYFUNCTION(" ((GOOGLEFINANCE(A30,""price"") - INDEX(GOOGLEFINANCE(A30,""price"",TODAY()-365),2,2)) / INDEX(GOOGLEFINANCE(A30,""price"",TODAY()-365),2,2)) "),-0.007220216606498127) -> -0.0072202166 | K30: =IFERROR(__xludf.DUMMYFUNCTION(" ((GOOGLEFINANCE(A30,""price"") - INDEX(GOOGLEFINANCE(A30,""price"",TODAY()-730),2,2)) / INDEX(GOOGLEFINANCE(A30,""price"",TODAY()-730),2,2))"),0.06699430936368349) -> 0.066994309 | L30: =IFERROR(__xludf.DUMMYFUNCTION(" ((GOOGLEFINANCE(A30,""price"") - INDEX(GOOGLEFINANCE(A30,""price"",TODAY()-1095),2,2)) / INDEX(GOOGLEFINANCE(A30,""price"",TODAY()-1095),2,2))"),0.04324734446130503) -> 0.043247344 | M30: =IFERROR(__xludf.DUMMYFUNCTION(" ((GOOGLEFINANCE(A30,""price"") - INDEX(GOOGLEFINANCE(A30,""price"",TODAY()-1825),2,2)) / INDEX(GOOGLEFINANCE(A30,""price"",TODAY()-1825),2,2))"),0.11036339165545092) -> 0.11036339
A31: SPY | B31: =IFERROR(__xludf.DUMMYFUNCTION("GOOGLEFINANCE(A31,""name"")"),"SPDR S&P 500 ETF Trust") -> SPDR S&P 500 ETF Trust | C31: =IFERROR(__xludf.DUMMYFUNCTION("GOOGLEFINANCE(A31,""price"")"),689.23) -> 689.23 | D31: =IFERROR(__xludf.DUMMYFUNCTION("GOOGLEFINANCE(A31,""changepct"")"),0.04) -> 0.04 | E31: =IFERROR(__xludf.DUMMYFUNCTION(" ((GOOGLEFINANCE(A31,""price"") - INDEX(GOOGLEFINANCE(A31,""price"",TODAY()-7),2,2)) / INDEX(GOOGLEFINANCE(A31,""price"",TODAY()-7),2,2)) "),0.01719354172201065) -> 0.017193542 | F31: =IFERROR(__xludf.DUMMYFUNCTION(" ((GOOGLEFINANCE(A31,""price"") - INDEX(GOOGLEFINANCE(A31,""price"",TODAY()-30),2,2)) / INDEX(GOOGLEFINANCE(A31,""price"",TODAY()-30),2,2)) "),-0.0015645144934883274) -> -0.0015645145 | G31: =IFERROR(__xludf.DUMMYFUNCTION(" ((GOOGLEFINANCE(A31,""price"") - INDEX(GOOGLEFINANCE(A31,""price"",TODAY()-90),2,2)) / INDEX(GOOGLEFINANCE(A31,""price"",TODAY()-90),2,2))"),0.005822777421049572) -> 0.0058227774 | H31: =IFERROR(__xludf.DUMMYFUNCTION(" ((GOOGLEFINANCE(A31,""price"") - INDEX(GOOGLEFINANCE(A31,""price"",TODAY()-182),2,2)) / INDEX(GOOGLEFINANCE(A31,""price"",TODAY()-182),2,2))"),0.0820956448017081) -> 0.082095645 | I31: =IFERROR(__xludf.DUMMYFUNCTION("(GOOGLEFINANCE(A31,""price"")-INDEX(GOOGLEFINANCE(A31,""price"",""01-01-""&YEAR(TODAY())),2,2))/INDEX(GOOGLEFINANCE(A31,""price"",""01-01-""&YEAR(TODAY())),2,2)"),0.008870412927968236) -> 0.0088704129 | J31: =IFERROR(__xludf.DUMMYFUNCTION(" ((GOOGLEFINANCE(A31,""price"") - INDEX(GOOGLEFINANCE(A31,""price"",TODAY()-365),2,2)) / INDEX(GOOGLEFINANCE(A31,""price"",TODAY()-365),2,2)) "),0.13365791075217526) -> 0.13365791 | K31: =IFERROR(__xludf.DUMMYFUNCTION(" ((GOOGLEFINANCE(A31,""price"") - INDEX(GOOGLEFINANCE(A31,""price"",TODAY()-730),2,2)) / INDEX(GOOGLEFINANCE(A31,""price"",TODAY()-730),2,2))"),0.41226973751613644) -> 0.41226974 | L31: =IFERROR(__xludf.DUMMYFUNCTION(" ((GOOGLEFINANCE(A31,""price"") - INDEX(GOOGLEFINANCE(A31,""price"",TODAY()-1095),2,2)) / INDEX(GOOGLEFINANCE(A31,""price"",TODAY()-1095),2,2))"),0.7215686274509804) -> 0.72156863 | M31: =IFERROR(__xludf.DUMMYFUNCTION(" ((GOOGLEFINANCE(A31,""price"") - INDEX(GOOGLEFINANCE(A31,""price"",TODAY()-1825),2,2)) / INDEX(GOOGLEFINANCE(A31,""price"",TODAY()-1825),2,2))"),0.7930487265537606) -> 0.79304873 | N31: =IFERROR(__xludf.DUMMYFUNCTION(" ((GOOGLEFINANCE(A31,""price"") - INDEX(GOOGLEFINANCE(A31,""price"",TODAY()-3650),2,2)) / INDEX(GOOGLEFINANCE(A31,""price"",TODAY()-3650),2,2))"),2.663583692127784) -> 2.6635837 | O31: =IFERROR(__xludf.DUMMYFUNCTION(" ((GOOGLEFINANCE(A31,""price"") - INDEX(GOOGLEFINANCE(A31,""price"",TODAY()-7300),2,2)) / INDEX(GOOGLEFINANCE(A31,""price"",TODAY()-7300),2,2))"),4.366163189037683) -> 4.3661632
A51: Utilizzare FundFlow e Aum come indicatore di interesse/disinteresse sui settori.
A53: | CATEGORIA | CONDIZIONE / FILTRO | SIGNIFICATO / INTERPRETAZIONE | COMMENTO OPERATIVO |
A55: | ETF selezionabili | AUM > $5 miliardi | Solo ETF liquidi e seguiti dagli istituzionali | SPY, QQQ, XLK, XLV, ecc. |
A56: | Volume medio | > 1M giornaliero | Evita rumore da ETF illiquidi
A57: | Flusso Anomalo | Fund Flow > ±2% dell’AUM in 1 giorno | Segnale forte di ingresso/uscita capitale | Va tracciato e confermato |
A58: | Divergenza AUM | AUM sale/scende ma prezzo va nella direzione opposta | Possibile segnale contrarian o accumulo/distribuzione nascosta | Osservare evoluzione nei giorni successivi |
A59: | Combinazione 1 | Prezzo in calo + Afflussi forti | Accumulo istituzionale, contrarian bullish | Potenziale bottom, osservare follow-through |
A60: | Combinazione 2 | Prezzo in rialzo + Deflussi forti | Distribuzione, riduzione esposizione | Potenziale esaurimento rally |
A61: | Combinazione 3 | AUM in calo costante + prezzo stabile | Perdita d’interesse, rotazione lenta | Bearish debole, trend in deterioramento |
A62: | Combinazione 4 | AUM picco dopo rally forte | Capitale "late" in entrata | Segnale contrarian, attenzione a top di breve |
A63: | Combinazione 5 | Flussi elevati senza notizie macro evidenti | Mossa istituzionale o anticipazione informata | Va monitorata con molta attenzione |
A67: Rotazionali su Momentum | C67: : si compra il migliore sul momentum e si vende il peggiore in PTF in base alla tabella | H67: al 22.01 | I67: changepct | J67: Classifica
A68: xlb | B68: 21 | C68: 49.6 | D68: =B68*C68 -> 1041.6 | E68: =IFERROR(__xludf.DUMMYFUNCTION("GOOGLEFINANCE(A68,""price"")"),49.97) -> 49.97 | F68: =B68*E68 -> 1049.37 | G68: =F68-D68 -> 7.77 | H68: =G68/D68 -> 0.0074596774 | I68: =IFERROR(__xludf.DUMMYFUNCTION("GOOGLEFINANCE(A68,""changepct"")/100"),0.0091) -> 0.0091 | J68: =Q12 -> 2
A69: XLV | B69: 6 | C69: 158.91 | D69: =B69*C69 -> 953.46 | E69: =IFERROR(__xludf.DUMMYFUNCTION("GOOGLEFINANCE(A69,""price"")"),157.48) -> 157.48 | F69: =B69*E69 -> 944.88 | G69: =F69-D69 -> -8.58 | H69: =G69/D69 -> -0.0089988044 | I69: =IFERROR(__xludf.DUMMYFUNCTION("GOOGLEFINANCE(A69,""changepct"")/100"),-0.0051) -> -0.0051 | J69: =Q8 -> 3
A70: XLE | B70: 19 | C70: 48.67 | D70: =B70*C70 -> 924.73 | E70: =IFERROR(__xludf.DUMMYFUNCTION("GOOGLEFINANCE(A70,""price"")"),49.19) -> 49.19 | F70: =B70*E70 -> 934.61 | G70: =F70-D70 -> 9.88 | H70: =G70/D70 -> 0.0106842 | I70: =IFERROR(__xludf.DUMMYFUNCTION("GOOGLEFINANCE(A70,""changepct"")/100"),0.005699999999999999) -> 0.0057 | J70: =Q11 -> 1
G72: =SUM(G68:G70) -> 9.07

Sheet Fattori
D1: CAMBIO | E1: =IFERROR(__xludf.DUMMYFUNCTION("GOOGLEFINANCE(""CURRENCY:GBPEUR"")"),1.1538) -> 1.1538
A14: ticker | B14: Fattori | C14: Prezzo corrente | D14: Var. % giornaliera | E14: Var. % settimanale | F14: Var. % mensile | G14: Var. % trimestrale | H14: Var.%semestrale | I14: Variaz .% YTD | J14: Var. % annuale | K14: Var. % 2 anni | L14: Var. % 3 anni | M14: Var. % 5 anni | N14: Var.% 10anni
A15: LON:MVOL | B15: Minimum Volat. | C15: =IFERROR(__xludf.DUMMYFUNCTION("GOOGLEFINANCE(A15,""PRICE"")"),73.38) -> 73.38 | D15: =IFERROR(__xludf.DUMMYFUNCTION("GOOGLEFINANCE(A15,""changepct"")/100"),0.0) -> 0 | E15: =IFERROR(__xludf.DUMMYFUNCTION(" ((GOOGLEFINANCE(A15,""price"") - INDEX(GOOGLEFINANCE(A15,""price"",TODAY()-7),2,2)) / INDEX(GOOGLEFINANCE(A15,""price"",TODAY()-7),2,2)) "),0.0025959830577947495) -> 0.0025959831 | F15: =IFERROR(__xludf.DUMMYFUNCTION(" ((GOOGLEFINANCE(A15,""price"") - INDEX(GOOGLEFINANCE(A15,""price"",TODAY()-30),2,2)) / INDEX(GOOGLEFINANCE(A15,""price"",TODAY()-30),2,2)) "),-0.003801248981808324) -> -0.003801249 | G15: =IFERROR(__xludf.DUMMYFUNCTION(" ((GOOGLEFINANCE(A15,""price"") - INDEX(GOOGLEFINANCE(A15,""price"",TODAY()-90),2,2)) / INDEX(GOOGLEFINANCE(A15,""price"",TODAY()-90),2,2))"),-0.0012249897917517819) -> -0.0012249898 | H15: =IFERROR(__xludf.DUMMYFUNCTION(" ((GOOGLEFINANCE(A15,""price"") - INDEX(GOOGLEFINANCE(A15,""price"",TODAY()-182),2,2)) / INDEX(GOOGLEFINANCE(A15,""price"",TODAY()-182),2,2))"),0.012696660226331794) -> 0.01269666 | I15: =IFERROR(__xludf.DUMMYFUNCTION("(GOOGLEFINANCE(A15,""price"")-INDEX(GOOGLEFINANCE(A15,""price"",""01-01-""&YEAR(TODAY())),2,2))/INDEX(GOOGLEFINANCE(A15,""price"",""01-01-""&YEAR(TODAY())),2,2)"),0.005205479452054732) -> 0.0052054795 | J15: =IFERROR(__xludf.DUMMYFUNCTION(" ((GOOGLEFINANCE(A15,""price"") - INDEX(GOOGLEFINANCE(A15,""price"",TODAY()-365),2,2)) / INDEX(GOOGLEFINANCE(A15,""price"",TODAY()-365),2,2)) "),0.08969408969408957) -> 0.08969409 | K15: =IFERROR(__xludf.DUMMYFUNCTION(" ((GOOGLEFINANCE(A15,""price"") - INDEX(GOOGLEFINANCE(A15,""price"",TODAY()-730),2,2)) / INDEX(GOOGLEFINANCE(A15,""price"",TODAY()-730),2,2))"),0.21009234828496035) -> 0.21009235 | L15: =IFERROR(__xludf.DUMMYFUNCTION(" ((GOOGLEFINANCE(A15,""price"") - INDEX(GOOGLEFINANCE(A15,""price"",TODAY()-1095),2,2)) / INDEX(GOOGLEFINANCE(A15,""price"",TODAY()-1095),2,2))"),0.30708941930887057) -> 0.30708942 | M15: =IFERROR(__xludf.DUMMYFUNCTION(" ((GOOGLEFINANCE(A15,""price"") - INDEX(GOOGLEFINANCE(A15,""price"",TODAY()-1825),2,2)) / INDEX(GOOGLEFINANCE(A15,""price"",TODAY()-1825),2,2))"),0.3573806881243062) -> 0.35738069 | N15: =IFERROR(__xludf.DUMMYFUNCTION(" ((GOOGLEFINANCE(A15,""price"") - INDEX(GOOGLEFINANCE(A15,""price"",TODAY()-3650),2,2)) / INDEX(GOOGLEFINANCE(A15,""price"",TODAY()-3650),2,2))"),1.1937219730941702) -> 1.193722
A16: LON:IWQU | B16: World Quality | C16: =IFERROR(__xludf.DUMMYFUNCTION("GOOGLEFINANCE(A16,""price"")"),81.96) -> 81.96 | D16: =IFERROR(__xludf.DUMMYFUNCTION("GOOGLEFINANCE(A16,""changepct"")/100"),0.0019) -> 0.0019 | E16: =IFERROR(__xludf.DUMMYFUNCTION(" ((GOOGLEFINANCE(A16,""price"") - INDEX(GOOGLEFINANCE(A16,""price"",TODAY()-7),2,2)) / INDEX(GOOGLEFINANCE(A16,""price"",TODAY()-7),2,2)) "),0.009981515711644955) -> 0.0099815157 | F16: =IFERROR(__xludf.DUMMYFUNCTION(" ((GOOGLEFINANCE(A16,""price"") - INDEX(GOOGLEFINANCE(A16,""price"",TODAY()-30),2,2)) / INDEX(GOOGLEFINANCE(A16,""price"",TODAY()-30),2,2)) "),0.022072577628133135) -> 0.022072578 | G16: =IFERROR(__xludf.DUMMYFUNCTION(" ((GOOGLEFINANCE(A16,""price"") - INDEX(GOOGLEFINANCE(A16,""price"",TODAY()-90),2,2)) / INDEX(GOOGLEFINANCE(A16,""price"",TODAY()-90),2,2))"),0.03917839482693025) -> 0.039178395 | H16: =IFERROR(__xludf.DUMMYFUNCTION(" ((GOOGLEFINANCE(A16,""price"") - INDEX(GOOGLEFINANCE(A16,""price"",TODAY()-182),2,2)) / INDEX(GOOGLEFINANCE(A16,""price"",TODAY()-182),2,2))"),0.10176098938029296) -> 0.10176099 | I16: =IFERROR(__xludf.DUMMYFUNCTION("(GOOGLEFINANCE(A16,""price"")-INDEX(GOOGLEFINANCE(A16,""price"",""01-01-""&YEAR(TODAY())),2,2))/INDEX(GOOGLEFINANCE(A16,""price"",""01-01-""&YEAR(TODAY())),2,2)"),0.025012506253126565) -> 0.025012506 | J16: =IFERROR(__xludf.DUMMYFUNCTION(" ((GOOGLEFINANCE(A16,""price"") - INDEX(GOOGLEFINANCE(A16,""price"",TODAY()-365),2,2)) / INDEX(GOOGLEFINANCE(A16,""price"",TODAY()-365),2,2)) "),0.14485263304930843) -> 0.14485263 | K16: =IFERROR(__xludf.DUMMYFUNCTION(" ((GOOGLEFINANCE(A16,""price"") - INDEX(GOOGLEFINANCE(A16,""price"",TODAY()-730),2,2)) / INDEX(GOOGLEFINANCE(A16,""price"",TODAY()-730),2,2))"),0.35672901837444126) -> 0.35672902 | L16: =IFERROR(__xludf.DUMMYFUNCTION(" ((GOOGLEFINANCE(A16,""price"") - INDEX(GOOGLEFINANCE(A16,""price"",TODAY()-1095),2,2)) / INDEX(GOOGLEFINANCE(A16,""price"",TODAY()-1095),2,2))"),0.6618004866180047) -> 0.66180049 | M16: =IFERROR(__xludf.DUMMYFUNCTION(" ((GOOGLEFINANCE(A16,""price"") - INDEX(GOOGLEFINANCE(A16,""price"",TODAY()-1825),2,2)) / INDEX(GOOGLEFINANCE(A16,""price"",TODAY()-1825),2,2))"),0.7135688898181057) -> 0.71356889 | N16: =IFERROR(__xludf.DUMMYFUNCTION(" ((GOOGLEFINANCE(A16,""price"") - INDEX(GOOGLEFINANCE(A16,""price"",TODAY()-3650),2,2)) / INDEX(GOOGLEFINANCE(A16,""price"",TODAY()-3650),2,2))"),"#N/A") -> #N/A
A17: LON:IWMO | B17: World Momentum | C17: =IFERROR(__xludf.DUMMYFUNCTION("GOOGLEFINANCE(A17,""price"")"),100.06) -> 100.06 | D17: =IFERROR(__xludf.DUMMYFUNCTION("GOOGLEFINANCE(A17,""changepct"")/100"),-0.0014000000000000002) -> -0.0014 | E17: =IFERROR(__xludf.DUMMYFUNCTION(" ((GOOGLEFINANCE(A17,""price"") - INDEX(GOOGLEFINANCE(A17,""price"",TODAY()-7),2,2)) / INDEX(GOOGLEFINANCE(A17,""price"",TODAY()-7),2,2)) "),-0.0028898854010960843) -> -0.0028898854 | F17: =IFERROR(__xludf.DUMMYFUNCTION(" ((GOOGLEFINANCE(A17,""price"") - INDEX(GOOGLEFINANCE(A17,""price"",TODAY()-30),2,2)) / INDEX(GOOGLEFINANCE(A17,""price"",TODAY()-30),2,2)) "),0.022794643769804803) -> 0.022794644 | G17: =IFERROR(__xludf.DUMMYFUNCTION(" ((GOOGLEFINANCE(A17,""price"") - INDEX(GOOGLEFINANCE(A17,""price"",TODAY()-90),2,2)) / INDEX(GOOGLEFINANCE(A17,""price"",TODAY()-90),2,2))"),0.03926049023680932) -> 0.03926049 | H17: =IFERROR(__xludf.DUMMYFUNCTION(" ((GOOGLEFINANCE(A17,""price"") - INDEX(GOOGLEFINANCE(A17,""price"",TODAY()-182),2,2)) / INDEX(GOOGLEFINANCE(A17,""price"",TODAY()-182),2,2))"),0.10600198960981545) -> 0.10600199 | I17: =IFERROR(__xludf.DUMMYFUNCTION("(GOOGLEFINANCE(A17,""price"")-INDEX(GOOGLEFINANCE(A17,""price"",""01-01-""&YEAR(TODAY())),2,2))/INDEX(GOOGLEFINANCE(A17,""price"",""01-01-""&YEAR(TODAY())),2,2)"),0.020812079167516897) -> 0.020812079 | J17: =IFERROR(__xludf.DUMMYFUNCTION(" ((GOOGLEFINANCE(A17,""price"") - INDEX(GOOGLEFINANCE(A17,""price"",TODAY()-365),2,2)) / INDEX(GOOGLEFINANCE(A17,""price"",TODAY()-365),2,2)) "),0.1831618777344213) -> 0.18316188 | K17: =IFERROR(__xludf.DUMMYFUNCTION(" ((GOOGLEFINANCE(A17,""price"") - INDEX(GOOGLEFINANCE(A17,""price"",TODAY()-730),2,2)) / INDEX(GOOGLEFINANCE(A17,""price"",TODAY()-730),2,2))"),0.5304374426430102) -> 0.53043744 | L17: =IFERROR(__xludf.DUMMYFUNCTION(" ((GOOGLEFINANCE(A17,""price"") - INDEX(GOOGLEFINANCE(A17,""price"",TODAY()-1095),2,2)) / INDEX(GOOGLEFINANCE(A17,""price"",TODAY()-1095),2,2))"),0.7986697824914614) -> 0.79866978 | M17: =IFERROR(__xludf.DUMMYFUNCTION(" ((GOOGLEFINANCE(A17,""price"") - INDEX(GOOGLEFINANCE(A17,""price"",TODAY()-1825),2,2)) / INDEX(GOOGLEFINANCE(A17,""price"",TODAY()-1825),2,2))"),0.6240869988638209) -> 0.624087 | N17: =IFERROR(__xludf.DUMMYFUNCTION(" ((GOOGLEFINANCE(A17,""price"") - INDEX(GOOGLEFINANCE(A17,""price"",TODAY()-3650),2,2)) / INDEX(GOOGLEFINANCE(A17,""price"",TODAY()-3650),2,2))"),2.9177760375880974) -> 2.917776
A18: LON:IWVL | B18: World Value | C18: =IFERROR(__xludf.DUMMYFUNCTION("GOOGLEFINANCE(A18,""price"")"),62.72) -> 62.72 | D18: =IFERROR(__xludf.DUMMYFUNCTION("GOOGLEFINANCE(A18,""changepct"")/100"),-0.0084) -> -0.0084 | E18: =IFERROR(__xludf.DUMMYFUNCTION(" ((GOOGLEFINANCE(A18,""price"") - INDEX(GOOGLEFINANCE(A18,""price"",TODAY()-7),2,2)) / INDEX(GOOGLEFINANCE(A18,""price"",TODAY()-7),2,2)) "),0.013247172859450733) -> 0.013247173 | F18: =IFERROR(__xludf.DUMMYFUNCTION(" ((GOOGLEFINANCE(A18,""price"") - INDEX(GOOGLEFINANCE(A18,""price"",TODAY()-30),2,2)) / INDEX(GOOGLEFINANCE(A18,""price"",TODAY()-30),2,2)) "),0.043767681810617326) -> 0.043767682 | G18: =IFERROR(__xludf.DUMMYFUNCTION(" ((GOOGLEFINANCE(A18,""price"") - INDEX(GOOGLEFINANCE(A18,""price"",TODAY()-90),2,2)) / INDEX(GOOGLEFINANCE(A18,""price"",TODAY()-90),2,2))"),0.1108749557208643) -> 0.11087496 | H18: =IFERROR(__xludf.DUMMYFUNCTION(" ((GOOGLEFINANCE(A18,""price"") - INDEX(GOOGLEFINANCE(A18,""price"",TODAY()-182),2,2)) / INDEX(GOOGLEFINANCE(A18,""price"",TODAY()-182),2,2))"),0.24001581652827206) -> 0.24001582 | I18: =IFERROR(__xludf.DUMMYFUNCTION("(GOOGLEFINANCE(A18,""price"")-INDEX(GOOGLEFINANCE(A18,""price"",""01-01-""&YEAR(TODAY())),2,2))/INDEX(GOOGLEFINANCE(A18,""price"",""01-01-""&YEAR(TODAY())),2,2)"),0.03378935223339372) -> 0.033789352 | J18: =IFERROR(__xludf.DUMMYFUNCTION(" ((GOOGLEFINANCE(A18,""price"") - INDEX(GOOGLEFINANCE(A18,""price"",TODAY()-365),2,2)) / INDEX(GOOGLEFINANCE(A18,""price"",TODAY()-365),2,2)) "),0.40912154572006293) -> 0.40912155 | K18: =IFERROR(__xludf.DUMMYFUNCTION(" ((GOOGLEFINANCE(A18,""price"") - INDEX(GOOGLEFINANCE(A18,""price"",TODAY()-730),2,2)) / INDEX(GOOGLEFINANCE(A18,""price"",TODAY()-730),2,2))"),0.5410319410319409) -> 0.54103194 | L18: =IFERROR(__xludf.DUMMYFUNCTION(" ((GOOGLEFINANCE(A18,""price"") - INDEX(GOOGLEFINANCE(A18,""price"",TODAY()-1095),2,2)) / INDEX(GOOGLEFINANCE(A18,""price"",TODAY()-1095),2,2))"),0.7340337296101741) -> 0.73403373 | M18: =IFERROR(__xludf.DUMMYFUNCTION(" ((GOOGLEFINANCE(A18,""price"") - INDEX(GOOGLEFINANCE(A18,""price"",TODAY()-1825),2,2)) / INDEX(GOOGLEFINANCE(A18,""price"",TODAY()-1825),2,2))"),0.9198041016222833) -> 0.9198041 | N18: =IFERROR(__xludf.DUMMYFUNCTION(" ((GOOGLEFINANCE(A18,""price"") - INDEX(GOOGLEFINANCE(A18,""price"",TODAY()-3650),2,2)) / INDEX(GOOGLEFINANCE(A18,""price"",TODAY()-3650),2,2))"),"#N/A") -> #N/A
A19: LON:WOSC | B19: World Small Cap | C19: =IFERROR(__xludf.DUMMYFUNCTION("GOOGLEFINANCE(A19,""price"")"),100.85) -> 100.85 | D19: =IFERROR(__xludf.DUMMYFUNCTION("GOOGLEFINANCE(A19,""changepct"")/100"),-0.0139) -> -0.0139 | E19: =IFERROR(__xludf.DUMMYFUNCTION(" ((GOOGLEFINANCE(A19,""price"") - INDEX(GOOGLEFINANCE(A19,""price"",TODAY()-7),2,2)) / INDEX(GOOGLEFINANCE(A19,""price"",TODAY()-7),2,2)) "),0.005684084563222907) -> 0.0056840846 | F19: =IFERROR(__xludf.DUMMYFUNCTION(" ((GOOGLEFINANCE(A19,""price"") - INDEX(GOOGLEFINANCE(A19,""price"",TODAY()-30),2,2)) / INDEX(GOOGLEFINANCE(A19,""price"",TODAY()-30),2,2)) "),0.053153717627401724) -> 0.053153718 | G19: =IFERROR(__xludf.DUMMYFUNCTION(" ((GOOGLEFINANCE(A19,""price"") - INDEX(GOOGLEFINANCE(A19,""price"",TODAY()-90),2,2)) / INDEX(GOOGLEFINANCE(A19,""price"",TODAY()-90),2,2))"),0.05823714585519409) -> 0.058237146 | H19: =IFERROR(__xludf.DUMMYFUNCTION(" ((GOOGLEFINANCE(A19,""price"") - INDEX(GOOGLEFINANCE(A19,""price"",TODAY()-182),2,2)) / INDEX(GOOGLEFINANCE(A19,""price"",TODAY()-182),2,2))"),0.14863325740318903) -> 0.14863326 | I19: =IFERROR(__xludf.DUMMYFUNCTION("(GOOGLEFINANCE(A19,""price"")-INDEX(GOOGLEFINANCE(A19,""price"",""01-01-""&YEAR(TODAY())),2,2))/INDEX(GOOGLEFINANCE(A19,""price"",""01-01-""&YEAR(TODAY())),2,2)"),0.056463440184370425) -> 0.05646344 | J19: =IFERROR(__xludf.DUMMYFUNCTION(" ((GOOGLEFINANCE(A19,""price"") - INDEX(GOOGLEFINANCE(A19,""price"",TODAY()-365),2,2)) / INDEX(GOOGLEFINANCE(A19,""price"",TODAY()-365),2,2)) "),0.13212842388863938) -> 0.13212842 | K19: =IFERROR(__xludf.DUMMYFUNCTION(" ((GOOGLEFINANCE(A19,""price"") - INDEX(GOOGLEFINANCE(A19,""price"",TODAY()-730),2,2)) / INDEX(GOOGLEFINANCE(A19,""price"",TODAY()-730),2,2))"),0.32366452290326814) -> 0.32366452 | L19: =IFERROR(__xludf.DUMMYFUNCTION(" ((GOOGLEFINANCE(A19,""price"") - INDEX(GOOGLEFINANCE(A19,""price"",TODAY()-1095),2,2)) / INDEX(GOOGLEFINANCE(A19,""price"",TODAY()-1095),2,2))"),0.3567872998789183) -> 0.3567873 | M19: =IFERROR(__xludf.DUMMYFUNCTION(" ((GOOGLEFINANCE(A19,""price"") - INDEX(GOOGLEFINANCE(A19,""price"",TODAY()-1825),2,2)) / INDEX(GOOGLEFINANCE(A19,""price"",TODAY()-1825),2,2))"),0.4327319221480323) -> 0.43273192 | N19: =IFERROR(__xludf.DUMMYFUNCTION(" ((GOOGLEFINANCE(A19,""price"") - INDEX(GOOGLEFINANCE(A19,""price"",TODAY()-3650),2,2)) / INDEX(GOOGLEFINANCE(A19,""price"",TODAY()-3650),2,2))"),"#N/A") -> #N/A
A20: LON:SWDA | B20: Msci World | C20: =IFERROR(__xludf.DUMMYFUNCTION("GOOGLEFINANCE(A20,""price"")"),9781.0) -> 9781 | D20: =IFERROR(__xludf.DUMMYFUNCTION("GOOGLEFINANCE(A20,""changepct"")/100"),-0.005699999999999999) -> -0.0057 | E20: =IFERROR(__xludf.DUMMYFUNCTION(" ((GOOGLEFINANCE(A20,""price"") - INDEX(GOOGLEFINANCE(A20,""price"",TODAY()-7),2,2)) / INDEX(GOOGLEFINANCE(A20,""price"",TODAY()-7),2,2)) "),-0.002651167533394514) -> -0.0026511675 | F20: =IFERROR(__xludf.DUMMYFUNCTION(" ((GOOGLEFINANCE(A20,""price"") - INDEX(GOOGLEFINANCE(A20,""price"",TODAY()-30),2,2)) / INDEX(GOOGLEFINANCE(A20,""price"",TODAY()-30),2,2)) "),0.005965237066748946) -> 0.0059652371 | G20: =IFERROR(__xludf.DUMMYFUNCTION(" ((GOOGLEFINANCE(A20,""price"") - INDEX(GOOGLEFINANCE(A20,""price"",TODAY()-90),2,2)) / INDEX(GOOGLEFINANCE(A20,""price"",TODAY()-90),2,2))"),0.006275720164609053) -> 0.0062757202 | H20: =IFERROR(__xludf.DUMMYFUNCTION(" ((GOOGLEFINANCE(A20,""price"") - INDEX(GOOGLEFINANCE(A20,""price"",TODAY()-182),2,2)) / INDEX(GOOGLEFINANCE(A20,""price"",TODAY()-182),2,2))"),0.0865363252610531) -> 0.086536325 | I20: =IFERROR(__xludf.DUMMYFUNCTION("(GOOGLEFINANCE(A20,""price"")-INDEX(GOOGLEFINANCE(A20,""price"",""01-01-""&YEAR(TODAY())),2,2))/INDEX(GOOGLEFINANCE(A20,""price"",""01-01-""&YEAR(TODAY())),2,2)"),0.009599504541701073) -> 0.0095995045 | J20: =IFERROR(__xludf.DUMMYFUNCTION(" ((GOOGLEFINANCE(A20,""price"") - INDEX(GOOGLEFINANCE(A20,""price"",TODAY()-365),2,2)) / INDEX(GOOGLEFINANCE(A20,""price"",TODAY()-365),2,2)) "),0.08744232586580689) -> 0.087442326 | K20: =IFERROR(__xludf.DUMMYFUNCTION(" ((GOOGLEFINANCE(A20,""price"") - INDEX(GOOGLEFINANCE(A20,""price"",TODAY()-730),2,2)) / INDEX(GOOGLEFINANCE(A20,""price"",TODAY()-730),2,2))"),0.35059375863021264) -> 0.35059376 | L20: =IFERROR(__xludf.DUMMYFUNCTION(" ((GOOGLEFINANCE(A20,""price"") - INDEX(GOOGLEFINANCE(A20,""price"",TODAY()-1095),2,2)) / INDEX(GOOGLEFINANCE(A20,""price"",TODAY()-1095),2,2))"),0.569228300978662) -> 0.5692283 | M20: =IFERROR(__xludf.DUMMYFUNCTION(" ((GOOGLEFINANCE(A20,""price"") - INDEX(GOOGLEFINANCE(A20,""price"",TODAY()-1825),2,2)) / INDEX(GOOGLEFINANCE(A20,""price"",TODAY()-1825),2,2))"),0.7894255396999634) -> 0.78942554 | N20: =IFERROR(__xludf.DUMMYFUNCTION(" ((GOOGLEFINANCE(A20,""price"") - INDEX(GOOGLEFINANCE(A20,""price"",TODAY()-3650),2,2)) / INDEX(GOOGLEFINANCE(A20,""price"",TODAY()-3650),2,2))"),2.666729147141518) -> 2.6667291
A21: LON:IQSA | B21: Multifactor | C21: =IFERROR(__xludf.DUMMYFUNCTION("GOOGLEFINANCE(A21,""price"")"),96.84) -> 96.84 | D21: =IFERROR(__xludf.DUMMYFUNCTION("GOOGLEFINANCE(A21,""changepct"")/100"),-0.0040999999999999995) -> -0.0041 | E21: =IFERROR(__xludf.DUMMYFUNCTION(" ((GOOGLEFINANCE(A21,""price"") - INDEX(GOOGLEFINANCE(A21,""price"",TODAY()-7),2,2)) / INDEX(GOOGLEFINANCE(A21,""price"",TODAY()-7),2,2)) "),0.006338979528213649) -> 0.0063389795 | F21: =IFERROR(__xludf.DUMMYFUNCTION(" ((GOOGLEFINANCE(A21,""price"") - INDEX(GOOGLEFINANCE(A21,""price"",TODAY()-30),2,2)) / INDEX(GOOGLEFINANCE(A21,""price"",TODAY()-30),2,2)) "),0.014243820695433592) -> 0.014243821 | G21: =IFERROR(__xludf.DUMMYFUNCTION(" ((GOOGLEFINANCE(A21,""price"") - INDEX(GOOGLEFINANCE(A21,""price"",TODAY()-90),2,2)) / INDEX(GOOGLEFINANCE(A21,""price"",TODAY()-90),2,2))"),0.047938534790607154) -> 0.047938535 | H21: =IFERROR(__xludf.DUMMYFUNCTION(" ((GOOGLEFINANCE(A21,""price"") - INDEX(GOOGLEFINANCE(A21,""price"",TODAY()-182),2,2)) / INDEX(GOOGLEFINANCE(A21,""price"",TODAY()-182),2,2))"),0.11966701352757554) -> 0.11966701 | I21: =IFERROR(__xludf.DUMMYFUNCTION("(GOOGLEFINANCE(A21,""price"")-INDEX(GOOGLEFINANCE(A21,""price"",""01-01-""&YEAR(TODAY())),2,2))/INDEX(GOOGLEFINANCE(A21,""price"",""01-01-""&YEAR(TODAY())),2,2)"),0.014987946756105302) -> 0.014987947 | J21: =IFERROR(__xludf.DUMMYFUNCTION(" ((GOOGLEFINANCE(A21,""price"") - INDEX(GOOGLEFINANCE(A21,""price"",TODAY()-365),2,2)) / INDEX(GOOGLEFINANCE(A21,""price"",TODAY()-365),2,2)) "),0.18836667075714822) -> 0.18836667 | K21: =IFERROR(__xludf.DUMMYFUNCTION(" ((GOOGLEFINANCE(A21,""price"") - INDEX(GOOGLEFINANCE(A21,""price"",TODAY()-730),2,2)) / INDEX(GOOGLEFINANCE(A21,""price"",TODAY()-730),2,2))"),0.4852760736196319) -> 0.48527607 | L21: =IFERROR(__xludf.DUMMYFUNCTION(" ((GOOGLEFINANCE(A21,""price"") - INDEX(GOOGLEFINANCE(A21,""price"",TODAY()-1095),2,2)) / INDEX(GOOGLEFINANCE(A21,""price"",TODAY()-1095),2,2))"),0.7910116515627891) -> 0.79101165 | M21: =IFERROR(__xludf.DUMMYFUNCTION(" ((GOOGLEFINANCE(A21,""price"") - INDEX(GOOGLEFINANCE(A21,""price"",TODAY()-1825),2,2)) / INDEX(GOOGLEFINANCE(A21,""price"",TODAY()-1825),2,2))"),0.9646987218502739) -> 0.96469872
A22: I rendimenti degli ETF sopra sono espressi in €uro, quindi differiscono in % dagli omologhi prezzati in $dollari. Inoltre i fattori del World non hanno lo stesso andamento di quelli USA.

Sheet Settori&Mktcap
A1: Select Sector SPDR ETFs - primi 5 titoli di ogni settore e relativa percentuale su MarketCap dell'indice S&P 500
B2: Titoli | D2: MktCap Billions | E2: % su SP mktcap | F2: S&P 500 indice | G2: Market cap al 29/10/2025
A3: Communication | B3: XLC 22 | F3: =IFERROR(__xludf.DUMMYFUNCTION("GOOGLEFINANCE(""INDEXSP:.INX"")"),6915.61) -> 6915.61 | G3: 57894 | H3: billions(miliardi)
B4: alphabet a | D4: =IFERROR(__xludf.DUMMYFUNCTION("GOOGLEFINANCE(""goog"",""marketcap"")/1000000000"),3958.738078582) -> 3958.7381 | E4: =(D4/$G$3)*100 -> 6.8379073
B5: alphabet c | D5: =IFERROR(__xludf.DUMMYFUNCTION("GOOGLEFINANCE(""googl"",""marketcap"")/1000000000"),3958.738078582) -> 3958.7381 | E5: =(D5/$G$3)*100 -> 6.8379073
B6: meta | D6: =IFERROR(__xludf.DUMMYFUNCTION("GOOGLEFINANCE(""meta"",""marketcap"")/1000000000"),1660.422391134) -> 1660.4224 | E6: =(D6/$G$3)*100 -> 2.8680388 | G6: SOCIETA' CON MARKETCAP > 1Trillion
B7: Nflx | D7: =IFERROR(__xludf.DUMMYFUNCTION("GOOGLEFINANCE(""nasdaq:NFLX"",""marketcap"")/1000000000"),393.52483583) -> 393.52484 | E7: =(D7/$G$3)*100 -> 0.67973337 | G7: =IFERROR(__xludf.DUMMYFUNCTION("FILTER(B4:B78,D4:D78>=1000)"),"alphabet a") -> alphabet a
B8: Warner Bros | D8: =IFERROR(__xludf.DUMMYFUNCTION("GOOGLEFINANCE(""NASDAQ:wbd"",""marketcap"")/1000000000"),70.83261465) -> 70.832615 | E8: =(D8/$G$3)*100 -> 0.1223488 | G8: =IFERROR(__xludf.DUMMYFUNCTION("""COMPUTED_VALUE"""),"alphabet c") -> alphabet c
E9: =SUM(E4:E8) -> 17.345936 | G9: =IFERROR(__xludf.DUMMYFUNCTION("""COMPUTED_VALUE"""),"meta") -> meta
A10: Discrezionali | B10: XLY 52 | G10: =IFERROR(__xludf.DUMMYFUNCTION("""COMPUTED_VALUE"""),"amazon") -> amazon
B11: amazon | D11: =IFERROR(__xludf.DUMMYFUNCTION("GOOGLEFINANCE(""AMZN"",""marketcap"")/1000000000"),2556.670662748) -> 2556.6707 | E11: =(D11/$G$3)*100 -> 4.4161237 | G11: =IFERROR(__xludf.DUMMYFUNCTION("""COMPUTED_VALUE"""),"tesla") -> tesla | I11: =COUNTA(G7:G17) -> 11
B12: tesla | D12: =IFERROR(__xludf.DUMMYFUNCTION("GOOGLEFINANCE(""TSLA"",""marketcap"")/1000000000"),1407.116030549) -> 1407.116 | E12: =(D12/$G$3)*100 -> 2.4305041 | G12: =IFERROR(__xludf.DUMMYFUNCTION("""COMPUTED_VALUE"""),"berkshire") -> berkshire
B13: home depot | D13: =IFERROR(__xludf.DUMMYFUNCTION("GOOGLEFINANCE(""HD"",""marketcap"")/1000000000"),382.047475794) -> 382.04748 | E13: =(D13/$G$3)*100 -> 0.65990858 | G13: =IFERROR(__xludf.DUMMYFUNCTION("""COMPUTED_VALUE"""),"ely lilly") -> ely lilly
B14: mc donald's | D14: =IFERROR(__xludf.DUMMYFUNCTION("GOOGLEFINANCE(""MCD"",""marketcap"")/1000000000"),220.233717275) -> 220.23372 | E14: =(D14/$G$3)*100 -> 0.38040853 | G14: =IFERROR(__xludf.DUMMYFUNCTION("""COMPUTED_VALUE"""),"nvidia") -> nvidia
B15: TJX | D15: =IFERROR(__xludf.DUMMYFUNCTION("GOOGLEFINANCE(""tjx"",""marketcap"")/1000000000"),170.167969179) -> 170.16797 | E15: =(D15/$G$3)*100 -> 0.29393023 | G15: =IFERROR(__xludf.DUMMYFUNCTION("""COMPUTED_VALUE"""),"apple") -> apple
E16: =SUM(E11:E15) -> 8.1808751 | G16: =IFERROR(__xludf.DUMMYFUNCTION("""COMPUTED_VALUE"""),"microsoft") -> microsoft
A17: Consum. staples | B17: XLP 38 | G17: =IFERROR(__xludf.DUMMYFUNCTION("""COMPUTED_VALUE"""),"broadcom") -> broadcom
B18: WMT | D18: =IFERROR(__xludf.DUMMYFUNCTION("GOOGLEFINANCE(""WMT"",""marketcap"")/1000000000"),938.327787665) -> 938.32779 | E18: =(D18/$G$3)*100 -> 1.6207686
B19: COST | D19: =IFERROR(__xludf.DUMMYFUNCTION("GOOGLEFINANCE(""cost"",""marketcap"")/1000000000"),436.43458755) -> 436.43459 | E19: =(D19/$G$3)*100 -> 0.75385115
B20: PG | D20: =IFERROR(__xludf.DUMMYFUNCTION("GOOGLEFINANCE(""PG"",""marketcap"")/1000000000"),350.860445687) -> 350.86045 | E20: =(D20/$G$3)*100 -> 0.60603939
B21: KO | D21: =IFERROR(__xludf.DUMMYFUNCTION("GOOGLEFINANCE(""KO"",""marketcap"")/1000000000"),313.501179225) -> 313.50118 | E21: =(D21/$G$3)*100 -> 0.54150893
B22: PM | D22: =IFERROR(__xludf.DUMMYFUNCTION("GOOGLEFINANCE(""pm"",""marketcap"")/1000000000"),269.32951341) -> 269.32951 | E22: =(D22/$G$3)*100 -> 0.46521144
E23: =SUM(E17:E22) -> 3.9873795
A24: Energy | B24: XLE 22
B25: Exxon | D25: =IFERROR(__xludf.DUMMYFUNCTION("GOOGLEFINANCE(""XOM"",""marketcap"")/1000000000"),569.190765197) -> 569.19077 | E25: =(D25/$G$3)*100 -> 0.9831602
B26: Chevron | D26: =IFERROR(__xludf.DUMMYFUNCTION("GOOGLEFINANCE(""CVX"",""marketcap"")/1000000000"),335.694223577) -> 335.69422 | E26: =(D26/$G$3)*100 -> 0.57984286
B27: conoco phillips | D27: =IFERROR(__xludf.DUMMYFUNCTION("GOOGLEFINANCE(""COP"",""marketcap"")/1000000000"),121.532863414) -> 121.53286 | E27: =(D27/$G$3)*100 -> 0.20992307
B28: The Williams Co. | D28: =IFERROR(__xludf.DUMMYFUNCTION("GOOGLEFINANCE(""wmb"",""marketcap"")/1000000000"),79.330320161) -> 79.33032 | E28: =(D28/$G$3)*100 -> 0.13702684
B29: Marathon Petr. | D29: =IFERROR(__xludf.DUMMYFUNCTION("GOOGLEFINANCE(""mpc"",""marketcap"")/1000000000"),52.719650379) -> 52.71965 | E29: =(D29/$G$3)*100 -> 0.091062373
E30: =SUM(E25:E29) -> 2.0010153
A31: Financial | B31: XLF 71
B32: berkshire | D32: =IFERROR(__xludf.DUMMYFUNCTION("GOOGLEFINANCE(""BRK.B"",""marketcap"")/1000000000"),1037.347882729) -> 1037.3479 | E32: =(D32/$G$3)*100 -> 1.7918055
B33: jp morgan | D33: =IFERROR(__xludf.DUMMYFUNCTION("GOOGLEFINANCE(""JPM"",""marketcap"")/1000000000"),818.656466516) -> 818.65647 | E33: =(D33/$G$3)*100 -> 1.414061
B34: visa | D34: =IFERROR(__xludf.DUMMYFUNCTION("GOOGLEFINANCE(""V"",""marketcap"")/1000000000"),623.733450654) -> 623.73345 | E34: =(D34/$G$3)*100 -> 1.0773715
B35: mastercard | D35: =IFERROR(__xludf.DUMMYFUNCTION("GOOGLEFINANCE(""MA"",""marketcap"")/1000000000"),471.214359796) -> 471.21436 | E35: =(D35/$G$3)*100 -> 0.81392607
B36: bank of america | D36: =IFERROR(__xludf.DUMMYFUNCTION("GOOGLEFINANCE(""BAC"",""marketcap"")/1000000000"),373.028698604) -> 373.0287 | E36: =(D36/$G$3)*100 -> 0.6443305
E37: =SUM(E32:E36) -> 5.7414946
A38: Healthcare | B38: XLV 63
B39: ely lilly | D39: =IFERROR(__xludf.DUMMYFUNCTION("GOOGLEFINANCE(""LLY"",""marketcap"")/1000000000"),1006.162029286) -> 1006.162 | E39: =(D39/$G$3)*100 -> 1.7379384
B40: johnson & johns. | D40: =IFERROR(__xludf.DUMMYFUNCTION("GOOGLEFINANCE(""JNJ"",""marketcap"")/1000000000"),530.382199829) -> 530.3822 | E40: =(D40/$G$3)*100 -> 0.91612637
B41: abbvie | D41: =IFERROR(__xludf.DUMMYFUNCTION("GOOGLEFINANCE(""ABBV"",""marketcap"")/1000000000"),387.516606131) -> 387.51661 | E41: =(D41/$G$3)*100 -> 0.66935538
B42: unitedhealth | D42: =IFERROR(__xludf.DUMMYFUNCTION("GOOGLEFINANCE(""UNH"",""marketcap"")/1000000000"),322.714032856) -> 322.71403 | E42: =(D42/$G$3)*100 -> 0.55742224
B43: merck | D43: =IFERROR(__xludf.DUMMYFUNCTION("GOOGLEFINANCE(""mrk"",""marketcap"")/1000000000"),268.505140717) -> 268.50514 | E43: =(D43/$G$3)*100 -> 0.46378751 | F43: XLV ETF Financial Ratios from Holdings | Composite Fundamental Summary
E44: =SUM(E39:E43) -> 4.3446299
A45: Industrial | B45: XLI 78
B46: ge aerospace | D46: =IFERROR(__xludf.DUMMYFUNCTION("GOOGLEFINANCE(""GE"",""marketcap"")/1000000000"),309.977891159) -> 309.97789 | E46: =(D46/$G$3)*100 -> 0.53542317
B47: caterpillar | D47: =IFERROR(__xludf.DUMMYFUNCTION("GOOGLEFINANCE(""CAT"",""marketcap"")/1000000000"),293.245374666) -> 293.24537 | E47: =(D47/$G$3)*100 -> 0.50652118
B48: rtx | D48: =IFERROR(__xludf.DUMMYFUNCTION("GOOGLEFINANCE(""rtx"",""marketcap"")/1000000000"),262.697448139) -> 262.69745 | E48: =(D48/$G$3)*100 -> 0.45375591
B49: uber | D49: =IFERROR(__xludf.DUMMYFUNCTION("GOOGLEFINANCE(""UBER"",""marketcap"")/1000000000"),171.026182227) -> 171.02618 | E49: =(D49/$G$3)*100 -> 0.29541262
B50: GEV | D50: =IFERROR(__xludf.DUMMYFUNCTION("GOOGLEFINANCE(B50,""marketcap"")/1000000000"),178.46914066) -> 178.46914 | E50: =(D50/$G$3)*100 -> 0.3082688
E51: =SUM(E46:E50) -> 2.0993817
A52: Materials | B52: XLB 28
B53: linde | D53: =IFERROR(__xludf.DUMMYFUNCTION("GOOGLEFINANCE(""LIN"",""marketcap"")/1000000000"),210.860073036) -> 210.86007 | E53: =(D53/$G$3)*100 -> 0.36421749
B54: sherwin willliams | D54: =IFERROR(__xludf.DUMMYFUNCTION("GOOGLEFINANCE(""SHW"",""marketcap"")/1000000000"),86.395839896) -> 86.39584 | E54: =(D54/$G$3)*100 -> 0.14923108
B55: newmont | D55: =IFERROR(__xludf.DUMMYFUNCTION("GOOGLEFINANCE(""nem"",""marketcap"")/1000000000"),135.654900865) -> 135.6549 | E55: =(D55/$G$3)*100 -> 0.23431599
B56: ecolab | D56: =IFERROR(__xludf.DUMMYFUNCTION("GOOGLEFINANCE(""ecl"",""marketcap"")/1000000000"),79.844113911) -> 79.844114 | E56: =(D56/$G$3)*100 -> 0.13791432
B57: nucor corp. | D57: =IFERROR(__xludf.DUMMYFUNCTION("GOOGLEFINANCE(""NUE"",""marketcap"")/1000000000"),41.572163293) -> 41.572163 | E57: =(D57/$G$3)*100 -> 0.071807378
E58: =SUM(E53:E57) -> 0.95748625
A59: Real Estate | B59: XLRE 31
B60: welltower | D60: =IFERROR(__xludf.DUMMYFUNCTION("GOOGLEFINANCE(""WELL"",""marketcap"")/1000000000"),126.064777117) -> 126.06478 | E60: =(D60/$G$3)*100 -> 0.21775102
B61: prologis | D61: =IFERROR(__xludf.DUMMYFUNCTION("GOOGLEFINANCE(""PLD"",""marketcap"")/1000000000"),118.105453182) -> 118.10545 | E61: =(D61/$G$3)*100 -> 0.20400292
B62: american tower | D62: =IFERROR(__xludf.DUMMYFUNCTION("GOOGLEFINANCE(""AMT"",""marketcap"")/1000000000"),83.68120475) -> 83.681205 | E62: =(D62/$G$3)*100 -> 0.1445421
B63: equinix | D63: =IFERROR(__xludf.DUMMYFUNCTION("GOOGLEFINANCE(""EQIX"",""marketcap"")/1000000000"),77.691693526) -> 77.691694 | E63: =(D63/$G$3)*100 -> 0.13419645
B64: simon property | D64: =IFERROR(__xludf.DUMMYFUNCTION("GOOGLEFINANCE(""spg"",""marketcap"")/1000000000"),60.308801705) -> 60.308802 | E64: =(D64/$G$3)*100 -> 0.10417107
E65: =SUM(E60:E64) -> 0.80466358
A66: Technology | B66: XLK 67
B67: nvidia | D67: =IFERROR(__xludf.DUMMYFUNCTION("GOOGLEFINANCE(""NVDA"",""marketcap"")/1000000000"),4560.380955505) -> 4560.381 | E67: =(D67/$G$3)*100 -> 7.8771219
B68: apple | D68: =IFERROR(__xludf.DUMMYFUNCTION("GOOGLEFINANCE(""AAPL"",""marketcap"")/1000000000"),3645.67197812) -> 3645.672 | E68: =(D68/$G$3)*100 -> 6.2971499
B69: microsoft | D69: =IFERROR(__xludf.DUMMYFUNCTION("GOOGLEFINANCE(""MSFT"",""marketcap"")/1000000000"),3463.116153877) -> 3463.1162 | E69: =(D69/$G$3)*100 -> 5.9818222
B70: broadcom | D70: =IFERROR(__xludf.DUMMYFUNCTION("GOOGLEFINANCE(""AVGO"",""marketcap"")/1000000000"),1517.444365773) -> 1517.4444 | E70: =(D70/$G$3)*100 -> 2.6210736
B71: palantir | D71: =IFERROR(__xludf.DUMMYFUNCTION("GOOGLEFINANCE(""pltr"",""marketcap"")/1000000000"),404.060142541) -> 404.06014 | E71: =(D71/$G$3)*100 -> 0.69793095
E72: =SUM(E68:E71) -> 15.597977
A73: Utilities | B73: XLU 31
B74: nextera | D74: =IFERROR(__xludf.DUMMYFUNCTION("GOOGLEFINANCE(""NEE"",""marketcap"")/1000000000"),176.626064205) -> 176.62606 | E74: =(D74/$G$3)*100 -> 0.30508527
B75: constellation en | D75: =IFERROR(__xludf.DUMMYFUNCTION("GOOGLEFINANCE(""CEG"",""marketcap"")/1000000000"),90.236199312) -> 90.236199 | E75: =(D75/$G$3)*100 -> 0.15586451
B76: southern co | D76: =IFERROR(__xludf.DUMMYFUNCTION("GOOGLEFINANCE(""SO"",""marketcap"")/1000000000"),96.390645168) -> 96.390645 | E76: =(D76/$G$3)*100 -> 0.16649505
B77: duke energy | D77: =IFERROR(__xludf.DUMMYFUNCTION("GOOGLEFINANCE(""DUK"",""marketcap"")/1000000000"),91.320754953) -> 91.320755 | E77: =(D77/$G$3)*100 -> 0.15773786
B78: aep | D78: =IFERROR(__xludf.DUMMYFUNCTION("GOOGLEFINANCE(""aep"",""marketcap"")/1000000000"),62.291440068) -> 62.29144 | E78: =(D78/$G$3)*100 -> 0.10759568
E79: =SUM(E74:E78) -> 0.89277836
B81: al 2025 il peso di Technology+communications è del 52% sul totale indice | K81: Mio calc.P/E
J82: eps oct 24 196,76 | K82: =5823/196.76 -> 29.59443
B83: tot titoli 502 | J83: fw eps 267 sep.24 secondo Carson | M83: 241 secodo Ycharts
A84: Le prime 5 aziende di ogni settore, insieme capitalizzano il : | E84: =SUM(E9,E16,E23,E30,E37,E51,E58,E65,E72,E79) -> 57.608987 | F84: % dell'intero indice S&p 500 | H84: Guru Focus Sp 500 P/E Ratio | J84: Fw /P/E tra | K84: =5732/267 -> 21.468165 | L84: =5733/241 -> 23.788382
A85: S&P 500 Index - 90 Year Historical Chart | MacroTrends | E85: dati al 04/09/2024
A86: Year | B86: Average Closing Price | D86: Year High | E86: Year Low | F86: Year Close | G86: Annual % Change | H86: Diff H-L | I86: Percent
A87: 2024 | B87: 5,389.98 | D87: 6090.27 | E87: 4688.68 | F87: 5823 | G87: 18.42% | H87: =D87-E87 -> 1401.59 | I87: =H87/D87 -> 0.23013594 | K87: S&P 500 P/E Ratio
A88: 2023 | B88: 4,283.73 | D88: 4783.35 | E88: 3808.1 | F88: 4,769.83 | G88: 24.23% | H88: =D88-E88 -> 975.25 | I88: =H88/D88 -> 0.20388431 | K88: Date | L88: Value | M88: Date | N88: Value
A89: 2022 | B89: 4,097.49 | D89: 4796.56 | E89: 3577.03 | F89: 3,839.50 | G89: -19.44% | H89: =D89-E89 -> 1219.53 | I89: =H89/D89 -> 0.25425096 | K89: Oct. 29,2024 | L89: 29.653
A90: 2021 | B90: 4,273.41 | D90: 4793.03 | E90: 3700.65 | F90: 4,766.18 | G90: 26.89% | H90: =D90-E90 -> 1092.38 | I90: =H90/D90 -> 0.22791011 | K90: March 31, 2024 | L90: 1.15625 | M90: Dec. 31, 2017 | N90: 1.0229167
A91: 2020 | B91: 3,217.86 | D91: 3756.07 | E91: 2237.4 | F91: 3,756.07 | G91: 16.26% | H91: =D91-E91 -> 1518.67 | I91: =H91/D91 -> 0.4043242 | K91: Dec. 31, 2023 | L91: 1.0548611 | M91: Sept. 30, 2017 | N91: 0.99513889
A92: 2019 | B92: 2,913.36 | D92: 3240.02 | E92: 2247.89 | F92: 3,230.78 | G92: 28.88% | H92: =D92-E92 -> 992.13 | I92: =H92/D92 -> 0.30621107 | K92: Sept. 30, 2023 | L92: 0.97708333 | M92: June 30, 2017 | N92: 0.97916667
A93: 2018 | B93: 2,746.21 | D93: 2930.75 | E93: 2351.1 | F93: 2,506.85 | G93: -6.24% | H93: =D93-E93 -> 579.65 | I93: =H93/D93 -> 0.19778214 | K93: June 30, 2023 | L93: 1.0409722 | M93: March 31, 2017 | N93: 0.99722222
A94: 2017 | B94: 2,449.08 | D94: 2690.16 | E94: 2257.83 | F94: 2,673.61 | G94: 19.42% | H94: =D94-E94 -> 432.33 | I94: =H94/D94 -> 0.16070791 | K94: March 31, 2023 | L94: 0.99027778 | M94: Dec. 31, 2016 | N94: 1.0055556
A95: 2016 | B95: 2,094.65 | D95: 2271.72 | E95: 1829.08 | F95: 2,238.83 | G95: 9.54% | H95: =D95-E95 -> 442.64 | I95: =H95/D95 -> 0.19484796 | K95: Dec. 31, 2022 | L95: 0.93263889 | M95: Sept. 30, 2016 | N95: 1.0236111
A96: 2015 | B96: 2,061.07 | D96: 2130.82 | E96: 1867.61 | F96: 2,043.94 | G96: -0.73% | H96: =D96-E96 -> 263.21 | I96: =H96/D96 -> 0.12352522 | K96: September 30, 2022 | L96: 0.80347222 | M96: June 30, 2016 | N96: 1.0104167
A97: 2014 | B97: 1,931.38 | D97: 2090.57 | E97: 1741.89 | F97: 2,058.90 | G97: 11.39% | H97: =D97-E97 -> 348.68 | I97: =H97/D97 -> 0.16678705 | K97: June 30, 2022 | L97: 0.83958333 | M97: March 31, 2016 | N97: 1.0159722
A98: 2013 | B98: 1,643.80 | D98: 1848.36 | E98: 1457.15 | F98: 1,848.36 | G98: 29.60% | H98: =D98-E98 -> 391.21 | I98: =H98/D98 -> 0.21165249 | K98: March 31, 2022 | L98: 0.97847222 | M98: Dec. 31, 2015 | N98: 1.0013889
A99: 2012 | B99: 1,379.61 | D99: 1456.77 | E99: 1277.06 | F99: 1,426.19 | G99: 13.41% | H99: =D99-E99 -> 179.71 | I99: =H99/D99 -> 0.12336196 | K99: December 31, 2021 | L99: 1.00625 | M99: Sept. 30, 2015 | N99: 0.8875
A100: 2011 | B100: 1,267.64 | D100: 1363.61 | E100: 1099.23 | F100: 1,257.60 | G100: 0.00% | H100: =D100-E100 -> 264.38 | I100: =H100/D100 -> 0.19388242 | K100: September 30, 2021 | L100: 1.0388889 | M100: June 30, 2015 | N100: 0.92638889
A101: 2010 | B101: 1,139.97 | D101: 1259.78 | E101: 1022.58 | F101: 1,257.64 | G101: 12.78% | H101: =D101-E101 -> 237.2 | I101: =H101/D101 -> 0.18828684 | K101: June 30, 2021 | L101: 1.1298611 | M101: March 31, 2015 | N101: 0.89166667
...

Sheet Motore
A1: =IFERROR(__xludf.DUMMYFUNCTION("GOOGLEFINANCE(""SPY"", ""price"", TODAY()-365, TODAY())"),"Date") -> Date | B1: =IFERROR(__xludf.DUMMYFUNCTION("""COMPUTED_VALUE"""),"Close") -> Close | C1: XLK | D1: XLY | E1: XLF | F1: XLC | G1: XLV | H1: XLP | I1: XLI | J1: XLE | K1: XLB | L1: XLU | M1: XLRE | O1: XLK/SPY | P1: XLY/SPY | Q1: XLF/SPY | R1: XLC/SPY | S1: XLV/SPY | T1: XLP/SPY | U1: XLI/SPY | V1: XLE/SPY | W1: XLB/SPY | X1: XLU/SPY | Y1: XLRE/SPY | AA1: {="RS-Mom " & C1:M1} -> RS-Mom XLK | AB1: RS-Mom XLY | AC1: RS-Mom XLF | AD1: RS-Mom XLC | AE1: RS-Mom XLV | AF1: RS-Mom XLP | AG1: RS-Mom XLI | AH1: RS-Mom XLE | AI1: RS-Mom XLB | AJ1: RS-Mom XLU | AK1: RS-Mom XLRE
A2: =IFERROR(__xludf.DUMMYFUNCTION("""COMPUTED_VALUE"""),45681.66666666667) -> 45681.667 | B2: =IFERROR(__xludf.DUMMYFUNCTION("""COMPUTED_VALUE"""),607.97) -> 607.97 | C2: =IFERROR(__xludf.DUMMYFUNCTION("IFERROR(VLOOKUP($A2, GOOGLEFINANCE(C$1, ""price"", $A$2, TODAY()), 2, FALSE), """")"),119.65) -> 119.65 | D2: =IFERROR(__xludf.DUMMYFUNCTION("IFERROR(VLOOKUP($A2, GOOGLEFINANCE(D$1, ""price"", $A$2, TODAY()), 2, FALSE), """")"),115.01) -> 115.01 | E2: =IFERROR(__xludf.DUMMYFUNCTION("IFERROR(VLOOKUP($A2, GOOGLEFINANCE(E$1, ""price"", $A$2, TODAY()), 2, FALSE), """")"),50.85) -> 50.85 | F2: =IFERROR(__xludf.DUMMYFUNCTION("IFERROR(VLOOKUP($A2, GOOGLEFINANCE(F$1, ""price"", $A$2, TODAY()), 2, FALSE), """")"),100.41) -> 100.41 | G2: =IFERROR(__xludf.DUMMYFUNCTION("IFERROR(VLOOKUP($A2, GOOGLEFINANCE(G$1, ""price"", $A$2, TODAY()), 2, FALSE), """")"),144.31) -> 144.31 | H2: =IFERROR(__xludf.DUMMYFUNCTION("IFERROR(VLOOKUP($A2, GOOGLEFINANCE(H$1, ""price"", $A$2, TODAY()), 2, FALSE), """")"),77.9) -> 77.9 | I2: =IFERROR(__xludf.DUMMYFUNCTION("IFERROR(VLOOKUP($A2, GOOGLEFINANCE(I$1, ""price"", $A$2, TODAY()), 2, FALSE), """")"),141.07) -> 141.07 | J2: =IFERROR(__xludf.DUMMYFUNCTION("IFERROR(VLOOKUP($A2, GOOGLEFINANCE(J$1, ""price"", $A$2, TODAY()), 2, FALSE), """")"),45.66) -> 45.66 | K2: =IFERROR(__xludf.DUMMYFUNCTION("IFERROR(VLOOKUP($A2, GOOGLEFINANCE(K$1, ""price"", $A$2, TODAY()), 2, FALSE), """")"),44.5) -> 44.5 | L2: =IFERROR(__xludf.DUMMYFUNCTION("IFERROR(VLOOKUP($A2, GOOGLEFINANCE(L$1, ""price"", $A$2, TODAY()), 2, FALSE), """")"),39.74) -> 39.74 | M2: =IFERROR(__xludf.DUMMYFUNCTION("IFERROR(VLOOKUP($A2, GOOGLEFINANCE(M$1, ""price"", $A$2, TODAY()), 2, FALSE), """")"),41.55) -> 41.55 | O2: {=C2:M252 / $B2:B252} -> 0.19680247 | P2: 0.18917052 | Q2: 0.083638995 | R2: 0.16515618 | S2: 0.23736369 | T2: 0.12813132 | U2: 0.23203448 | V2: 0.07510239 | W2: 0.073194401 | X2: 0.065365067 | Y2: 0.068342188 | AA2: {=IFERROR(IF(O2:Y252="", "", (O2:Y252 / O7:Y257) - 1), "")} -> 0.02625132 | AB2: -0.019324651 | AC2: -0.022039631 | AD2: -0.029163025 | AE2: -0.027369692 | AF2: -0.023651654 | AG2: 0.009345775 | AH2: 0.031449573 | AI2: -0.0078861614 | AJ2: 0.010220977 | AK2: -0.007008799
A3: =IFERROR(__xludf.DUMMYFUNCTION("""COMPUTED_VALUE"""),45684.66666666667) -> 45684.667 | B3: =IFERROR(__xludf.DUMMYFUNCTION("""COMPUTED_VALUE"""),599.37) -> 599.37 | C3: =IFERROR(__xludf.DUMMYFUNCTION("IFERROR(VLOOKUP($A3, GOOGLEFINANCE(C$1, ""price"", $A$2, TODAY()), 2, FALSE), """")"),113.79) -> 113.79 | D3: =IFERROR(__xludf.DUMMYFUNCTION("IFERROR(VLOOKUP($A3, GOOGLEFINANCE(D$1, ""price"", $A$2, TODAY()), 2, FALSE), """")"),115.66) -> 115.66 | E3: =IFERROR(__xludf.DUMMYFUNCTION("IFERROR(VLOOKUP($A3, GOOGLEFINANCE(E$1, ""price"", $A$2, TODAY()), 2, FALSE), """")"),51.41) -> 51.41 | F3: =IFERROR(__xludf.DUMMYFUNCTION("IFERROR(VLOOKUP($A3, GOOGLEFINANCE(F$1, ""price"", $A$2, TODAY()), 2, FALSE), """")"),100.93) -> 100.93 | G3: =IFERROR(__xludf.DUMMYFUNCTION("IFERROR(VLOOKUP($A3, GOOGLEFINANCE(G$1, ""price"", $A$2, TODAY()), 2, FALSE), """")"),147.55) -> 147.55 | H3: =IFERROR(__xludf.DUMMYFUNCTION("IFERROR(VLOOKUP($A3, GOOGLEFINANCE(H$1, ""price"", $A$2, TODAY()), 2, FALSE), """")"),80.01) -> 80.01 | I3: =IFERROR(__xludf.DUMMYFUNCTION("IFERROR(VLOOKUP($A3, GOOGLEFINANCE(I$1, ""price"", $A$2, TODAY()), 2, FALSE), """")"),139.18) -> 139.18 | J3: =IFERROR(__xludf.DUMMYFUNCTION("IFERROR(VLOOKUP($A3, GOOGLEFINANCE(J$1, ""price"", $A$2, TODAY()), 2, FALSE), """")"),45.18) -> 45.18 | K3: =IFERROR(__xludf.DUMMYFUNCTION("IFERROR(VLOOKUP($A3, GOOGLEFINANCE(K$1, ""price"", $A$2, TODAY()), 2, FALSE), """")"),44.53) -> 44.53 | L3: =IFERROR(__xludf.DUMMYFUNCTION("IFERROR(VLOOKUP($A3, GOOGLEFINANCE(L$1, ""price"", $A$2, TODAY()), 2, FALSE), """")"),38.83) -> 38.83 | M3: =IFERROR(__xludf.DUMMYFUNCTION("IFERROR(VLOOKUP($A3, GOOGLEFINANCE(M$1, ""price"", $A$2, TODAY()), 2, FALSE), """")"),41.96) -> 41.96 | O3: 0.18984934 | P3: 0.19296928 | Q3: 0.085773395 | R3: 0.16839348 | S3: 0.24617515 | T3: 0.13349016 | U3: 0.23221049 | V3: 0.075379148 | W3: 0.074294676 | X3: 0.064784691 | Y3: 0.070006841 | AA3: -0.003195072 | AB3: 0.0069947546 | AC3: 0.00024897712 | AD3: -0.018902822 | AE3: -0.001925395 | AF3: 0.0063868803 | AG3: 0.013348396 | AH3: 0.021754952 | AI3: -0.00064967331 | AJ3: -0.010821341 | AK3: 0.012043266
A4: =IFERROR(__xludf.DUMMYFUNCTION("""COMPUTED_VALUE"""),45685.66666666667) -> 45685.667 | B4: =IFERROR(__xludf.DUMMYFUNCTION("""COMPUTED_VALUE"""),604.52) -> 604.52 | C4: =IFERROR(__xludf.DUMMYFUNCTION("IFERROR(VLOOKUP($A4, GOOGLEFINANCE(C$1, ""price"", $A$2, TODAY()), 2, FALSE), """")"),116.82) -> 116.82 | D4: =IFERROR(__xludf.DUMMYFUNCTION("IFERROR(VLOOKUP($A4, GOOGLEFINANCE(D$1, ""price"", $A$2, TODAY()), 2, FALSE), """")"),115.8) -> 115.8 | E4: =IFERROR(__xludf.DUMMYFUNCTION("IFERROR(VLOOKUP($A4, GOOGLEFINANCE(E$1, ""price"", $A$2, TODAY()), 2, FALSE), """")"),51.32) -> 51.32 | F4: =IFERROR(__xludf.DUMMYFUNCTION("IFERROR(VLOOKUP($A4, GOOGLEFINANCE(F$1, ""price"", $A$2, TODAY()), 2, FALSE), """")"),101.42) -> 101.42 | G4: =IFERROR(__xludf.DUMMYFUNCTION("IFERROR(VLOOKUP($A4, GOOGLEFINANCE(G$1, ""price"", $A$2, TODAY()), 2, FALSE), """")"),146.52) -> 146.52 | H4: =IFERROR(__xludf.DUMMYFUNCTION("IFERROR(VLOOKUP($A4, GOOGLEFINANCE(H$1, ""price"", $A$2, TODAY()), 2, FALSE), """")"),78.76) -> 78.76 | I4: =IFERROR(__xludf.DUMMYFUNCTION("IFERROR(VLOOKUP($A4, GOOGLEFINANCE(I$1, ""price"", $A$2, TODAY()), 2, FALSE), """")"),138.26) -> 138.26 | J4: =IFERROR(__xludf.DUMMYFUNCTION("IFERROR(VLOOKUP($A4, GOOGLEFINANCE(J$1, ""price"", $A$2, TODAY()), 2, FALSE), """")"),44.75) -> 44.75 | K4: =IFERROR(__xludf.DUMMYFUNCTION("IFERROR(VLOOKUP($A4, GOOGLEFINANCE(K$1, ""price"", $A$2, TODAY()), 2, FALSE), """")"),44.38) -> 44.38 | L4: =IFERROR(__xludf.DUMMYFUNCTION("IFERROR(VLOOKUP($A4, GOOGLEFINANCE(L$1, ""price"", $A$2, TODAY()), 2, FALSE), """")"),38.29) -> 38.29 | M4: =IFERROR(__xludf.DUMMYFUNCTION("IFERROR(VLOOKUP($A4, GOOGLEFINANCE(M$1, ""price"", $A$2, TODAY()), 2, FALSE), """")"),41.45) -> 41.45 | O4: 0.19324423 | P4: 0.19155694 | Q4: 0.0848938 | R4: 0.16776947 | S4: 0.24237412 | T4: 0.13028518 | U4: 0.22871038 | V4: 0.074025673 | W4: 0.073413617 | X4: 0.063339509 | Y4: 0.068566797 | AA4: 0.0069314297 | AB4: -0.0053914237 | AC4: -0.0010287253 | AD4: -0.02472651 | AE4: -0.0080529453 | AF4: -0.0027598754 | AG4: 0.0044762338 | AH4: -0.010502673 | AI4: -0.0087761569 | AJ4: -0.017870401 | AK4: -0.0021251033
A5: =IFERROR(__xludf.DUMMYFUNCTION("""COMPUTED_VALUE"""),45686.66666666667) -> 45686.667 | B5: =IFERROR(__xludf.DUMMYFUNCTION("""COMPUTED_VALUE"""),601.81) -> 601.81 | C5: =IFERROR(__xludf.DUMMYFUNCTION("IFERROR(VLOOKUP($A5, GOOGLEFINANCE(C$1, ""price"", $A$2, TODAY()), 2, FALSE), """")"),115.87) -> 115.87 | D5: =IFERROR(__xludf.DUMMYFUNCTION("IFERROR(VLOOKUP($A5, GOOGLEFINANCE(D$1, ""price"", $A$2, TODAY()), 2, FALSE), """")"),115.47) -> 115.47 | E5: =IFERROR(__xludf.DUMMYFUNCTION("IFERROR(VLOOKUP($A5, GOOGLEFINANCE(E$1, ""price"", $A$2, TODAY()), 2, FALSE), """")"),51.28) -> 51.28 | F5: =IFERROR(__xludf.DUMMYFUNCTION("IFERROR(VLOOKUP($A5, GOOGLEFINANCE(F$1, ""price"", $A$2, TODAY()), 2, FALSE), """")"),101.87) -> 101.87 | G5: =IFERROR(__xludf.DUMMYFUNCTION("IFERROR(VLOOKUP($A5, GOOGLEFINANCE(G$1, ""price"", $A$2, TODAY()), 2, FALSE), """")"),145.66) -> 145.66 | H5: =IFERROR(__xludf.DUMMYFUNCTION("IFERROR(VLOOKUP($A5, GOOGLEFINANCE(H$1, ""price"", $A$2, TODAY()), 2, FALSE), """")"),78.95) -> 78.95 | I5: =IFERROR(__xludf.DUMMYFUNCTION("IFERROR(VLOOKUP($A5, GOOGLEFINANCE(I$1, ""price"", $A$2, TODAY()), 2, FALSE), """")"),137.79) -> 137.79 | J5: =IFERROR(__xludf.DUMMYFUNCTION("IFERROR(VLOOKUP($A5, GOOGLEFINANCE(J$1, ""price"", $A$2, TODAY()), 2, FALSE), """")"),44.85) -> 44.85 | K5: =IFERROR(__xludf.DUMMYFUNCTION("IFERROR(VLOOKUP($A5, GOOGLEFINANCE(K$1, ""price"", $A$2, TODAY()), 2, FALSE), """")"),44.3) -> 44.3 | L5: =IFERROR(__xludf.DUMMYFUNCTION("IFERROR(VLOOKUP($A5, GOOGLEFINANCE(L$1, ""price"", $A$2, TODAY()), 2, FALSE), """")"),38.37) -> 38.37 | M5: =IFERROR(__xludf.DUMMYFUNCTION("IFERROR(VLOOKUP($A5, GOOGLEFINANCE(M$1, ""price"", $A$2, TODAY()), 2, FALSE), """")"),40.97) -> 40.97 | O5: 0.19253585 | P5: 0.19187119 | Q5: 0.085209618 | R5: 0.16927269 | S5: 0.24203652 | T5: 0.13118758 | U5: 0.22895931 | V5: 0.074525182 | W5: 0.073611273 | X5: 0.063757664 | Y5: 0.068077965 | AA5: -0.0065413202 | AB5: 0.011714893 | AC5: -0.0037663472 | AD5: -0.0023610301 | AE5: -0.014864884 | AF5: 0.0019739866 | AG5: 0.0089103845 | AH5: -0.00200342 | AI5: -0.0014054071 | AJ5: -0.017253674 | AK5: -0.020617431
A6: =IFERROR(__xludf.DUMMYFUNCTION("""COMPUTED_VALUE"""),45687.66666666667) -> 45687.667 | B6: =IFERROR(__xludf.DUMMYFUNCTION("""COMPUTED_VALUE"""),605.04) -> 605.04 | C6: =IFERROR(__xludf.DUMMYFUNCTION("IFERROR(VLOOKUP($A6, GOOGLEFINANCE(C$1, ""price"", $A$2, TODAY()), 2, FALSE), """")"),116.09) -> 116.09 | D6: =IFERROR(__xludf.DUMMYFUNCTION("IFERROR(VLOOKUP($A6, GOOGLEFINANCE(D$1, ""price"", $A$2, TODAY()), 2, FALSE), """")"),116.6) -> 116.6 | E6: =IFERROR(__xludf.DUMMYFUNCTION("IFERROR(VLOOKUP($A6, GOOGLEFINANCE(E$1, ""price"", $A$2, TODAY()), 2, FALSE), """")"),51.77) -> 51.77 | F6: =IFERROR(__xludf.DUMMYFUNCTION("IFERROR(VLOOKUP($A6, GOOGLEFINANCE(F$1, ""price"", $A$2, TODAY()), 2, FALSE), """")"),101.97) -> 101.97 | G6: =IFERROR(__xludf.DUMMYFUNCTION("IFERROR(VLOOKUP($A6, GOOGLEFINANCE(G$1, ""price"", $A$2, TODAY()), 2, FALSE), """")"),147.34) -> 147.34 | H6: =IFERROR(__xludf.DUMMYFUNCTION("IFERROR(VLOOKUP($A6, GOOGLEFINANCE(H$1, ""price"", $A$2, TODAY()), 2, FALSE), """")"),79.73) -> 79.73 | I6: =IFERROR(__xludf.DUMMYFUNCTION("IFERROR(VLOOKUP($A6, GOOGLEFINANCE(I$1, ""price"", $A$2, TODAY()), 2, FALSE), """")"),139.33) -> 139.33 | J6: =IFERROR(__xludf.DUMMYFUNCTION("IFERROR(VLOOKUP($A6, GOOGLEFINANCE(J$1, ""price"", $A$2, TODAY()), 2, FALSE), """")"),45.08) -> 45.08 | K6: =IFERROR(__xludf.DUMMYFUNCTION("IFERROR(VLOOKUP($A6, GOOGLEFINANCE(K$1, ""price"", $A$2, TODAY()), 2, FALSE), """")"),44.72) -> 44.72 | L6: =IFERROR(__xludf.DUMMYFUNCTION("IFERROR(VLOOKUP($A6, GOOGLEFINANCE(L$1, ""price"", $A$2, TODAY()), 2, FALSE), """")"),39.17) -> 39.17 | M6: =IFERROR(__xludf.DUMMYFUNCTION("IFERROR(VLOOKUP($A6, GOOGLEFINANCE(M$1, ""price"", $A$2, TODAY()), 2, FALSE), """")"),41.51) -> 41.51 | O6: 0.19187161 | P6: 0.19271453 | Q6: 0.085564591 | R6: 0.16853431 | S6: 0.24352109 | T6: 0.13177641 | U6: 0.2302823 | V6: 0.074507471 | W6: 0.073912469 | X6: 0.064739521 | Y6: 0.068607034 | AA6: -0.0092352609 | AB6: 0.015704751 | AC6: -0.0044229001 | AD6: -0.007520164 | AE6: 0.0036141041 | AF6: 0.0053941589 | AG6: 0.013683471 | AH6: 0.019990281 | AI6: 0.0027882739 | AJ6: 0.002627499 | AK6: -0.012397507
A7: =IFERROR(__xludf.DUMMYFUNCTION("""COMPUTED_VALUE"""),45688.66666666667) -> 45688.667 | B7: =IFERROR(__xludf.DUMMYFUNCTION("""COMPUTED_VALUE"""),601.82) -> 601.82 | C7: =IFERROR(__xludf.DUMMYFUNCTION("IFERROR(VLOOKUP($A7, GOOGLEFINANCE(C$1, ""price"", $A$2, TODAY()), 2, FALSE), """")"),115.41) -> 115.41 | D7: =IFERROR(__xludf.DUMMYFUNCTION("IFERROR(VLOOKUP($A7, GOOGLEFINANCE(D$1, ""price"", $A$2, TODAY()), 2, FALSE), """")"),116.09) -> 116.09 | E7: =IFERROR(__xludf.DUMMYFUNCTION("IFERROR(VLOOKUP($A7, GOOGLEFINANCE(E$1, ""price"", $A$2, TODAY()), 2, FALSE), """")"),51.47) -> 51.47 | F7: =IFERROR(__xludf.DUMMYFUNCTION("IFERROR(VLOOKUP($A7, GOOGLEFINANCE(F$1, ""price"", $A$2, TODAY()), 2, FALSE), """")"),102.38) -> 102.38 | G7: =IFERROR(__xludf.DUMMYFUNCTION("IFERROR(VLOOKUP($A7, GOOGLEFINANCE(G$1, ""price"", $A$2, TODAY()), 2, FALSE), """")"),146.87) -> 146.87 | H7: =IFERROR(__xludf.DUMMYFUNCTION("IFERROR(VLOOKUP($A7, GOOGLEFINANCE(H$1, ""price"", $A$2, TODAY()), 2, FALSE), """")"),78.98) -> 78.98 | I7: =IFERROR(__xludf.DUMMYFUNCTION("IFERROR(VLOOKUP($A7, GOOGLEFINANCE(I$1, ""price"", $A$2, TODAY()), 2, FALSE), """")"),138.35) -> 138.35 | J7: =IFERROR(__xludf.DUMMYFUNCTION("IFERROR(VLOOKUP($A7, GOOGLEFINANCE(J$1, ""price"", $A$2, TODAY()), 2, FALSE), """")"),43.82) -> 43.82 | K7: =IFERROR(__xludf.DUMMYFUNCTION("IFERROR(VLOOKUP($A7, GOOGLEFINANCE(K$1, ""price"", $A$2, TODAY()), 2, FALSE), """")"),44.4) -> 44.4 | L7: =IFERROR(__xludf.DUMMYFUNCTION("IFERROR(VLOOKUP($A7, GOOGLEFINANCE(L$1, ""price"", $A$2, TODAY()), 2, FALSE), """")"),38.94) -> 38.94 | M7: =IFERROR(__xludf.DUMMYFUNCTION("IFERROR(VLOOKUP($A7, GOOGLEFINANCE(M$1, ""price"", $A$2, TODAY()), 2, FALSE), """")"),41.42) -> 41.42 | O7: 0.1917683 | P7: 0.19289821 | Q7: 0.085523911 | R7: 0.17011731 | S7: 0.24404307 | T7: 0.13123525 | U7: 0.22988601 | V7: 0.072812469 | W7: 0.073776212 | X7: 0.064703732 | Y7: 0.068824565 | AA7: -0.010320047 | AB7: 0.027462159 | AC7: -0.0084870727 | AD7: -0.0052425849 | AE7: 0.0012548984 | AF7: -0.0063994583 | AG7: 0.0056696984 | AH7: -0.01211502 | AI7: 0.003907927 | AJ7: -0.0050662636 | AK7: -0.014826443
A8: =IFERROR(__xludf.DUMMYFUNCTION("""COMPUTED_VALUE"""),45691.66666666667) -> 45691.667 | B8: =IFERROR(__xludf.DUMMYFUNCTION("""COMPUTED_VALUE"""),597.77) -> 597.77 | C8: =IFERROR(__xludf.DUMMYFUNCTION("IFERROR(VLOOKUP($A8, GOOGLEFINANCE(C$1, ""price"", $A$2, TODAY()), 2, FALSE), """")"),113.85) -> 113.85 | D8: =IFERROR(__xludf.DUMMYFUNCTION("IFERROR(VLOOKUP($A8, GOOGLEFINANCE(D$1, ""price"", $A$2, TODAY()), 2, FALSE), """")"),114.55) -> 114.55 | E8: =IFERROR(__xludf.DUMMYFUNCTION("IFERROR(VLOOKUP($A8, GOOGLEFINANCE(E$1, ""price"", $A$2, TODAY()), 2, FALSE), """")"),51.26) -> 51.26 | F8: =IFERROR(__xludf.DUMMYFUNCTION("IFERROR(VLOOKUP($A8, GOOGLEFINANCE(F$1, ""price"", $A$2, TODAY()), 2, FALSE), """")"),102.6) -> 102.6 | G8: =IFERROR(__xludf.DUMMYFUNCTION("IFERROR(VLOOKUP($A8, GOOGLEFINANCE(G$1, ""price"", $A$2, TODAY()), 2, FALSE), """")"),147.44) -> 147.44 | H8: =IFERROR(__xludf.DUMMYFUNCTION("IFERROR(VLOOKUP($A8, GOOGLEFINANCE(H$1, ""price"", $A$2, TODAY()), 2, FALSE), """")"),79.29) -> 79.29 | I8: =IFERROR(__xludf.DUMMYFUNCTION("IFERROR(VLOOKUP($A8, GOOGLEFINANCE(I$1, ""price"", $A$2, TODAY()), 2, FALSE), """")"),136.98) -> 136.98 | J8: =IFERROR(__xludf.DUMMYFUNCTION("IFERROR(VLOOKUP($A8, GOOGLEFINANCE(J$1, ""price"", $A$2, TODAY()), 2, FALSE), """")"),44.1) -> 44.1 | K8: =IFERROR(__xludf.DUMMYFUNCTION("IFERROR(VLOOKUP($A8, GOOGLEFINANCE(K$1, ""price"", $A$2, TODAY()), 2, FALSE), """")"),44.44) -> 44.44 | L8: =IFERROR(__xludf.DUMMYFUNCTION("IFERROR(VLOOKUP($A8, GOOGLEFINANCE(L$1, ""price"", $A$2, TODAY()), 2, FALSE), """")"),39.15) -> 39.15 | M8: =IFERROR(__xludf.DUMMYFUNCTION("IFERROR(VLOOKUP($A8, GOOGLEFINANCE(M$1, ""price"", $A$2, TODAY()), 2, FALSE), """")"),41.35) -> 41.35 | O8: 0.19045787 | P8: 0.19162889 | Q8: 0.085752045 | R8: 0.17163792 | S8: 0.24665005 | T8: 0.13264299 | U8: 0.22915168 | V8: 0.073774194 | W8: 0.074342975 | X8: 0.065493417 | Y8: 0.069173762 | AA8: -0.024651243 | AB8: 0.024092 | AC8: 0.0088917424 | AD8: 0.0059612062 | AE8: 0.019728519 | AF8: 0.0048736519 | AG8: 0.00030596058 | AH8: -0.014089233 | AI8: 0.013440348 | AJ8: 0.0031322713 | AK8: -0.004526523
A9: =IFERROR(__xludf.DUMMYFUNCTION("""COMPUTED_VALUE"""),45692.66666666667) -> 45692.667 | B9: =IFERROR(__xludf.DUMMYFUNCTION("""COMPUTED_VALUE"""),601.78) -> 601.78 | C9: =IFERROR(__xludf.DUMMYFUNCTION("IFERROR(VLOOKUP($A9, GOOGLEFINANCE(C$1, ""price"", $A$2, TODAY()), 2, FALSE), """")"),115.49) -> 115.49 | D9: =IFERROR(__xludf.DUMMYFUNCTION("IFERROR(VLOOKUP($A9, GOOGLEFINANCE(D$1, ""price"", $A$2, TODAY()), 2, FALSE), """")"),115.9) -> 115.9 | E9: =IFERROR(__xludf.DUMMYFUNCTION("IFERROR(VLOOKUP($A9, GOOGLEFINANCE(E$1, ""price"", $A$2, TODAY()), 2, FALSE), """")"),51.14) -> 51.14 | F9: =IFERROR(__xludf.DUMMYFUNCTION("IFERROR(VLOOKUP($A9, GOOGLEFINANCE(F$1, ""price"", $A$2, TODAY()), 2, FALSE), """")"),103.52) -> 103.52 | G9: =IFERROR(__xludf.DUMMYFUNCTION("IFERROR(VLOOKUP($A9, GOOGLEFINANCE(G$1, ""price"", $A$2, TODAY()), 2, FALSE), """")"),147.04) -> 147.04 | H9: =IFERROR(__xludf.DUMMYFUNCTION("IFERROR(VLOOKUP($A9, GOOGLEFINANCE(H$1, ""price"", $A$2, TODAY()), 2, FALSE), """")"),78.62) -> 78.62 | I9: =IFERROR(__xludf.DUMMYFUNCTION("IFERROR(VLOOKUP($A9, GOOGLEFINANCE(I$1, ""price"", $A$2, TODAY()), 2, FALSE), """")"),137.02) -> 137.02 | J9: =IFERROR(__xludf.DUMMYFUNCTION("IFERROR(VLOOKUP($A9, GOOGLEFINANCE(J$1, ""price"", $A$2, TODAY()), 2, FALSE), """")"),45.02) -> 45.02 | K9: =IFERROR(__xludf.DUMMYFUNCTION("IFERROR(VLOOKUP($A9, GOOGLEFINANCE(K$1, ""price"", $A$2, TODAY()), 2, FALSE), """")"),44.57) -> 44.57 | L9: =IFERROR(__xludf.DUMMYFUNCTION("IFERROR(VLOOKUP($A9, GOOGLEFINANCE(L$1, ""price"", $A$2, TODAY()), 2, FALSE), """")"),38.81) -> 38.81 | M9: =IFERROR(__xludf.DUMMYFUNCTION("IFERROR(VLOOKUP($A9, GOOGLEFINANCE(M$1, ""price"", $A$2, TODAY()), 2, FALSE), """")"),41.35) -> 41.35 | O9: 0.19191399 | P9: 0.1925953 | Q9: 0.084981222 | R9: 0.172023 | S9: 0.24434179 | T9: 0.13064575 | U9: 0.22769118 | V9: 0.074811393 | W9: 0.074063611 | X9: 0.064492007 | Y9: 0.068712819 | AA9: -0.016946294 | AB9: 0.041914929 | AC9: -0.0019405566 | AD9: 0.0073255411 | AE9: 0.012822889 | AF9: -0.018965643 | AG9: -0.0056723911 | AH9: -0.0073633447 | AI9: 0.0045136578 | AJ9: -0.016683708 | AK9: -0.015793747
A10: =IFERROR(__xludf.DUMMYFUNCTION("""COMPUTED_VALUE"""),45693.66666666667) -> 45693.667 | B10: =IFERROR(__xludf.DUMMYFUNCTION("""COMPUTED_VALUE"""),604.22) -> 604.22 | C10: =IFERROR(__xludf.DUMMYFUNCTION("IFERROR(VLOOKUP($A10, GOOGLEFINANCE(C$1, ""price"", $A$2, TODAY()), 2, FALSE), """")"),117.1) -> 117.1 | D10: =IFERROR(__xludf.DUMMYFUNCTION("IFERROR(VLOOKUP($A10, GOOGLEFINANCE(D$1, ""price"", $A$2, TODAY()), 2, FALSE), """")"),114.59) -> 114.59 | E10: =IFERROR(__xludf.DUMMYFUNCTION("IFERROR(VLOOKUP($A10, GOOGLEFINANCE(E$1, ""price"", $A$2, TODAY()), 2, FALSE), """")"),51.68) -> 51.68 | F10: =IFERROR(__xludf.DUMMYFUNCTION("IFERROR(VLOOKUP($A10, GOOGLEFINANCE(F$1, ""price"", $A$2, TODAY()), 2, FALSE), """")"),102.52) -> 102.52 | G10: =IFERROR(__xludf.DUMMYFUNCTION("IFERROR(VLOOKUP($A10, GOOGLEFINANCE(G$1, ""price"", $A$2, TODAY()), 2, FALSE), """")"),148.45) -> 148.45 | H10: =IFERROR(__xludf.DUMMYFUNCTION("IFERROR(VLOOKUP($A10, GOOGLEFINANCE(H$1, ""price"", $A$2, TODAY()), 2, FALSE), """")"),79.11) -> 79.11 | I10: =IFERROR(__xludf.DUMMYFUNCTION("IFERROR(VLOOKUP($A10, GOOGLEFINANCE(I$1, ""price"", $A$2, TODAY()), 2, FALSE), """")"),137.12) -> 137.12 | J10: =IFERROR(__xludf.DUMMYFUNCTION("IFERROR(VLOOKUP($A10, GOOGLEFINANCE(J$1, ""price"", $A$2, TODAY()), 2, FALSE), """")"),45.12) -> 45.12 | K10: =IFERROR(__xludf.DUMMYFUNCTION("IFERROR(VLOOKUP($A10, GOOGLEFINANCE(K$1, ""price"", $A$2, TODAY()), 2, FALSE), """")"),44.54) -> 44.54 | L10: =IFERROR(__xludf.DUMMYFUNCTION("IFERROR(VLOOKUP($A10, GOOGLEFINANCE(L$1, ""price"", $A$2, TODAY()), 2, FALSE), """")"),39.2) -> 39.2 | M10: =IFERROR(__xludf.DUMMYFUNCTION("IFERROR(VLOOKUP($A10, GOOGLEFINANCE(M$1, ""price"", $A$2, TODAY()), 2, FALSE), """")"),42.0) -> 42 | O10: 0.19380358 | P10: 0.18964947 | Q10: 0.08553176 | R10: 0.1696733 | S10: 0.24568866 | T10: 0.13092913 | U10: 0.22693721 | V10: 0.074674787 | W10: 0.073714872 | X10: 0.064877032 | Y10: 0.069511105 | AA10: -0.0082831912 | AB10: 0.022856007 | AC10: 0.0047983389 | AD10: -0.010687273 | AE10: 0.016586941 | AF10: -0.019274973 | AG10: -0.0059903158 | AH10: 0.012034584 | AI10: 0.0037599912 | AJ10: -0.012258245 | AK10: 0.00095991526
A11: =IFERROR(__xludf.DUMMYFUNCTION("""COMPUTED_VALUE"""),45694.66666666667) -> 45694.667 | B11: =IFERROR(__xludf.DUMMYFUNCTION("""COMPUTED_VALUE"""),606.32) -> 606.32 | C11: =IFERROR(__xludf.DUMMYFUNCTION("IFERROR(VLOOKUP($A11, GOOGLEFINANCE(C$1, ""price"", $A$2, TODAY()), 2, FALSE), """")"),117.42) -> 117.42 | D11: =IFERROR(__xludf.DUMMYFUNCTION("IFERROR(VLOOKUP($A11, GOOGLEFINANCE(D$1, ""price"", $A$2, TODAY()), 2, FALSE), """")"),115.04) -> 115.04 | E11: =IFERROR(__xludf.DUMMYFUNCTION("IFERROR(VLOOKUP($A11, GOOGLEFINANCE(E$1, ""price"", $A$2, TODAY()), 2, FALSE), """")"),52.11) -> 52.11 | F11: =IFERROR(__xludf.DUMMYFUNCTION("IFERROR(VLOOKUP($A11, GOOGLEFINANCE(F$1, ""price"", $A$2, TODAY()), 2, FALSE), """")"),102.96) -> 102.96 | G11: =IFERROR(__xludf.DUMMYFUNCTION("IFERROR(VLOOKUP($A11, GOOGLEFINANCE(G$1, ""price"", $A$2, TODAY()), 2, FALSE), """")"),147.12) -> 147.12 | H11: =IFERROR(__xludf.DUMMYFUNCTION("IFERROR(VLOOKUP($A11, GOOGLEFINANCE(H$1, ""price"", $A$2, TODAY()), 2, FALSE), """")"),79.47) -> 79.47 | I11: =IFERROR(__xludf.DUMMYFUNCTION("IFERROR(VLOOKUP($A11, GOOGLEFINANCE(I$1, ""price"", $A$2, TODAY()), 2, FALSE), """")"),137.74) -> 137.74 | J11: =IFERROR(__xludf.DUMMYFUNCTION("IFERROR(VLOOKUP($A11, GOOGLEFINANCE(J$1, ""price"", $A$2, TODAY()), 2, FALSE), """")"),44.29) -> 44.29 | K11: =IFERROR(__xludf.DUMMYFUNCTION("IFERROR(VLOOKUP($A11, GOOGLEFINANCE(K$1, ""price"", $A$2, TODAY()), 2, FALSE), """")"),44.69) -> 44.69 | L11: =IFERROR(__xludf.DUMMYFUNCTION("IFERROR(VLOOKUP($A11, GOOGLEFINANCE(L$1, ""price"", $A$2, TODAY()), 2, FALSE), """")"),39.15) -> 39.15 | M11: =IFERROR(__xludf.DUMMYFUNCTION("IFERROR(VLOOKUP($A11, GOOGLEFINANCE(M$1, ""price"", $A$2, TODAY()), 2, FALSE), """")"),42.12) -> 42.12 | O11: 0.19366011 | P11: 0.18973479 | Q11: 0.085944716 | R11: 0.16981132 | S11: 0.24264415 | T11: 0.1310694 | U11: 0.22717377 | V11: 0.073047236 | W11: 0.073706953 | X11: 0.064569864 | Y11: 0.069468268 | AA11: -0.012540718 | AB11: 0.018819865 | AC11: 0.013599062 | AD11: -0.010804848 | AE11: 0.010638818 | AF11: -0.018460493 | AG11: 0.0045301512 | AH11: -0.007153565 | AI11: -0.0030758494 | AJ11: -0.0088070686 | AK11: 0.00300466
A12: =IFERROR(__xludf.DUMMYFUNCTION("""COMPUTED_VALUE"""),45695.66666666667) -> 45695.667 | B12: =IFERROR(__xludf.DUMMYFUNCTION("""COMPUTED_VALUE"""),600.77) -> 600.77 | C12: =IFERROR(__xludf.DUMMYFUNCTION("IFERROR(VLOOKUP($A12, GOOGLEFINANCE(C$1, ""price"", $A$2, TODAY()), 2, FALSE), """")"),116.41) -> 116.41 | D12: =IFERROR(__xludf.DUMMYFUNCTION("IFERROR(VLOOKUP($A12, GOOGLEFINANCE(D$1, ""price"", $A$2, TODAY()), 2, FALSE), """")"),112.79) -> 112.79 | E12: =IFERROR(__xludf.DUMMYFUNCTION("IFERROR(VLOOKUP($A12, GOOGLEFINANCE(E$1, ""price"", $A$2, TODAY()), 2, FALSE), """")"),51.82) -> 51.82 | F12: =IFERROR(__xludf.DUMMYFUNCTION("IFERROR(VLOOKUP($A12, GOOGLEFINANCE(F$1, ""price"", $A$2, TODAY()), 2, FALSE), """")"),102.74) -> 102.74 | G12: =IFERROR(__xludf.DUMMYFUNCTION("IFERROR(VLOOKUP($A12, GOOGLEFINANCE(G$1, ""price"", $A$2, TODAY()), 2, FALSE), """")"),146.43) -> 146.43 | H12: =IFERROR(__xludf.DUMMYFUNCTION("IFERROR(VLOOKUP($A12, GOOGLEFINANCE(H$1, ""price"", $A$2, TODAY()), 2, FALSE), """")"),79.35) -> 79.35 | I12: =IFERROR(__xludf.DUMMYFUNCTION("IFERROR(VLOOKUP($A12, GOOGLEFINANCE(I$1, ""price"", $A$2, TODAY()), 2, FALSE), """")"),137.33) -> 137.33 | J12: =IFERROR(__xludf.DUMMYFUNCTION("IFERROR(VLOOKUP($A12, GOOGLEFINANCE(J$1, ""price"", $A$2, TODAY()), 2, FALSE), """")"),44.28) -> 44.28 | K12: =IFERROR(__xludf.DUMMYFUNCTION("IFERROR(VLOOKUP($A12, GOOGLEFINANCE(K$1, ""price"", $A$2, TODAY()), 2, FALSE), """")"),44.15) -> 44.15 | L12: =IFERROR(__xludf.DUMMYFUNCTION("IFERROR(VLOOKUP($A12, GOOGLEFINANCE(L$1, ""price"", $A$2, TODAY()), 2, FALSE), """")"),39.07) -> 39.07 | M12: =IFERROR(__xludf.DUMMYFUNCTION("IFERROR(VLOOKUP($A12, GOOGLEFINANCE(M$1, ""price"", $A$2, TODAY()), 2, FALSE), """")"),41.97) -> 41.97 | O12: 0.193768 | P12: 0.1877424 | Q12: 0.086255972 | R12: 0.17101387 | S12: 0.2437372 | T12: 0.1320805 | U12: 0.22858998 | V12: 0.073705411 | W12: 0.073489022 | X12: 0.065033207 | Y12: 0.069860346 | AA12: -0.015415049 | AB12: 0.0085157675 | AC12: 0.015256097 | AD12: -0.009902632 | AE12: 0.026288489 | AF12: -0.00099889796 | AG12: 0.013241065 | AH12: -0.0022604502 | AI12: -0.0027541293 | AJ12: 0.0025473209 | AK12: 0.012692651
A13: =IFERROR(__xludf.DUMMYFUNCTION("""COMPUTED_VALUE"""),45698.66666666667) -> 45698.667 | B13: =IFERROR(__xludf.DUMMYFUNCTION("""COMPUTED_VALUE"""),604.85) -> 604.85 | C13: =IFERROR(__xludf.DUMMYFUNCTION("IFERROR(VLOOKUP($A13, GOOGLEFINANCE(C$1, ""price"", $A$2, TODAY()), 2, FALSE), """")"),118.11) -> 118.11 | D13: =IFERROR(__xludf.DUMMYFUNCTION("IFERROR(VLOOKUP($A13, GOOGLEFINANCE(D$1, ""price"", $A$2, TODAY()), 2, FALSE), """")"),113.18) -> 113.18 | E13: =IFERROR(__xludf.DUMMYFUNCTION("IFERROR(VLOOKUP($A13, GOOGLEFINANCE(E$1, ""price"", $A$2, TODAY()), 2, FALSE), """")"),51.41) -> 51.41 | F13: =IFERROR(__xludf.DUMMYFUNCTION("IFERROR(VLOOKUP($A13, GOOGLEFINANCE(F$1, ""price"", $A$2, TODAY()), 2, FALSE), """")"),103.2) -> 103.2 | G13: =IFERROR(__xludf.DUMMYFUNCTION("IFERROR(VLOOKUP($A13, GOOGLEFINANCE(G$1, ""price"", $A$2, TODAY()), 2, FALSE), """")"),146.3) -> 146.3 | H13: =IFERROR(__xludf.DUMMYFUNCTION("IFERROR(VLOOKUP($A13, GOOGLEFINANCE(H$1, ""price"", $A$2, TODAY()), 2, FALSE), """")"),79.84) -> 79.84 | I13: =IFERROR(__xludf.DUMMYFUNCTION("IFERROR(VLOOKUP($A13, GOOGLEFINANCE(I$1, ""price"", $A$2, TODAY()), 2, FALSE), """")"),138.56) -> 138.56 | J13: =IFERROR(__xludf.DUMMYFUNCTION("IFERROR(VLOOKUP($A13, GOOGLEFINANCE(J$1, ""price"", $A$2, TODAY()), 2, FALSE), """")"),45.26) -> 45.26 | K13: =IFERROR(__xludf.DUMMYFUNCTION("IFERROR(VLOOKUP($A13, GOOGLEFINANCE(K$1, ""price"", $A$2, TODAY()), 2, FALSE), """")"),44.37) -> 44.37 | L13: =IFERROR(__xludf.DUMMYFUNCTION("IFERROR(VLOOKUP($A13, GOOGLEFINANCE(L$1, ""price"", $A$2, TODAY()), 2, FALSE), """")"),39.49) -> 39.49 | M13: =IFERROR(__xludf.DUMMYFUNCTION("IFERROR(VLOOKUP($A13, GOOGLEFINANCE(M$1, ""price"", $A$2, TODAY()), 2, FALSE), """")"),42.03) -> 42.03 | O13: 0.19527155 | P13: 0.18712077 | Q13: 0.08499628 | R13: 0.17062082 | S13: 0.24187815 | T13: 0.13199967 | U13: 0.22908159 | V13: 0.07482847 | W13: 0.073357031 | X13: 0.065288915 | Y13: 0.069488303 | AA13: -0.013820589 | AB13: 0.010888612 | AC13: -0.0037497547 | AD13: -0.004646802 | AE13: 0.023429774 | AF13: -0.0022685067 | AG13: 0.010467444 | AH13: 0.0023408771 | AI13: -0.014129875 | AJ13: 8.8136097e-05 | AK13: 0.0066667219
A14: =IFERROR(__xludf.DUMMYFUNCTION("""COMPUTED_VALUE"""),45699.66666666667) -> 45699.667 | B14: =IFERROR(__xludf.DUMMYFUNCTION("""COMPUTED_VALUE"""),605.31) -> 605.31 | C14: =IFERROR(__xludf.DUMMYFUNCTION("IFERROR(VLOOKUP($A14, GOOGLEFINANCE(C$1, ""price"", $A$2, TODAY()), 2, FALSE), """")"),118.17) -> 118.17 | D14: =IFERROR(__xludf.DUMMYFUNCTION("IFERROR(VLOOKUP($A14, GOOGLEFINANCE(D$1, ""price"", $A$2, TODAY()), 2, FALSE), """")"),111.89) -> 111.89 | E14: =IFERROR(__xludf.DUMMYFUNCTION("IFERROR(VLOOKUP($A14, GOOGLEFINANCE(E$1, ""price"", $A$2, TODAY()), 2, FALSE), """")"),51.54) -> 51.54 | F14: =IFERROR(__xludf.DUMMYFUNCTION("IFERROR(VLOOKUP($A14, GOOGLEFINANCE(F$1, ""price"", $A$2, TODAY()), 2, FALSE), """")"),103.37) -> 103.37 | G14: =IFERROR(__xludf.DUMMYFUNCTION("IFERROR(VLOOKUP($A14, GOOGLEFINANCE(G$1, ""price"", $A$2, TODAY()), 2, FALSE), """")"),146.03) -> 146.03 | H14: =IFERROR(__xludf.DUMMYFUNCTION("IFERROR(VLOOKUP($A14, GOOGLEFINANCE(H$1, ""price"", $A$2, TODAY()), 2, FALSE), """")"),80.61) -> 80.61 | I14: =IFERROR(__xludf.DUMMYFUNCTION("IFERROR(VLOOKUP($A14, GOOGLEFINANCE(I$1, ""price"", $A$2, TODAY()), 2, FALSE), """")"),138.61) -> 138.61 | J14: =IFERROR(__xludf.DUMMYFUNCTION("IFERROR(VLOOKUP($A14, GOOGLEFINANCE(J$1, ""price"", $A$2, TODAY()), 2, FALSE), """")"),45.62) -> 45.62 | K14: =IFERROR(__xludf.DUMMYFUNCTION("IFERROR(VLOOKUP($A14, GOOGLEFINANCE(K$1, ""price"", $A$2, TODAY()), 2, FALSE), """")"),44.63) -> 44.63 | L14: =IFERROR(__xludf.DUMMYFUNCTION("IFERROR(VLOOKUP($A14, GOOGLEFINANCE(L$1, ""price"", $A$2, TODAY()), 2, FALSE), """")"),39.7) -> 39.7 | M14: =IFERROR(__xludf.DUMMYFUNCTION("IFERROR(VLOOKUP($A14, GOOGLEFINANCE(M$1, ""price"", $A$2, TODAY()), 2, FALSE), """")"),42.26) -> 42.26 | O14: 0.19522228 | P14: 0.18484743 | Q14: 0.085146454 | R14: 0.170772 | S14: 0.24124829 | T14: 0.13317143 | U14: 0.2289901 | V14: 0.075366341 | W14: 0.073730816 | X14: 0.065586229 | Y14: 0.069815466 | AA14: -0.011829269 | AB14: 0.0015783013 | AC14: -2.2686749e-05 | AD14: -0.0025606761 | AE14: 0.010029453 | AF14: 0.00091681567 | AG14: 0.01142109 | AH14: 0.0040054666 | AI14: 0.0051563349 | AJ14: 0.0017385263 | AK14: 0.011870273
A15: =IFERROR(__xludf.DUMMYFUNCTION("""COMPUTED_VALUE"""),45700.66666666667) -> 45700.667 | B15: =IFERROR(__xludf.DUMMYFUNCTION("""COMPUTED_VALUE"""),603.36) -> 603.36 | C15: =IFERROR(__xludf.DUMMYFUNCTION("IFERROR(VLOOKUP($A15, GOOGLEFINANCE(C$1, ""price"", $A$2, TODAY()), 2, FALSE), """")"),117.91) -> 117.91 | D15: =IFERROR(__xludf.DUMMYFUNCTION("IFERROR(VLOOKUP($A15, GOOGLEFINANCE(D$1, ""price"", $A$2, TODAY()), 2, FALSE), """")"),111.87) -> 111.87 | E15: =IFERROR(__xludf.DUMMYFUNCTION("IFERROR(VLOOKUP($A15, GOOGLEFINANCE(E$1, ""price"", $A$2, TODAY()), 2, FALSE), """")"),51.36) -> 51.36 | F15: =IFERROR(__xludf.DUMMYFUNCTION("IFERROR(VLOOKUP($A15, GOOGLEFINANCE(F$1, ""price"", $A$2, TODAY()), 2, FALSE), """")"),103.48) -> 103.48 | G15: =IFERROR(__xludf.DUMMYFUNCTION("IFERROR(VLOOKUP($A15, GOOGLEFINANCE(G$1, ""price"", $A$2, TODAY()), 2, FALSE), """")"),145.82) -> 145.82 | H15: =IFERROR(__xludf.DUMMYFUNCTION("IFERROR(VLOOKUP($A15, GOOGLEFINANCE(H$1, ""price"", $A$2, TODAY()), 2, FALSE), """")"),80.55) -> 80.55 | I15: =IFERROR(__xludf.DUMMYFUNCTION("IFERROR(VLOOKUP($A15, GOOGLEFINANCE(I$1, ""price"", $A$2, TODAY()), 2, FALSE), """")"),137.75) -> 137.75 | J15: =IFERROR(__xludf.DUMMYFUNCTION("IFERROR(VLOOKUP($A15, GOOGLEFINANCE(J$1, ""price"", $A$2, TODAY()), 2, FALSE), """")"),44.52) -> 44.52 | K15: =IFERROR(__xludf.DUMMYFUNCTION("IFERROR(VLOOKUP($A15, GOOGLEFINANCE(K$1, ""price"", $A$2, TODAY()), 2, FALSE), """")"),44.31) -> 44.31 | L15: =IFERROR(__xludf.DUMMYFUNCTION("IFERROR(VLOOKUP($A15, GOOGLEFINANCE(L$1, ""price"", $A$2, TODAY()), 2, FALSE), """")"),39.63) -> 39.63 | M15: =IFERROR(__xludf.DUMMYFUNCTION("IFERROR(VLOOKUP($A15, GOOGLEFINANCE(M$1, ""price"", $A$2, TODAY()), 2, FALSE), """")"),41.9) -> 41.9 | O15: 0.1954223 | P15: 0.18541169 | Q15: 0.085123309 | R15: 0.17150623 | S15: 0.24167993 | T15: 0.13350239 | U15: 0.22830483 | V15: 0.073786794 | W15: 0.073438743 | X15: 0.06568218 | Y15: 0.069444444 | AA15: -0.011831128 | AB15: 0.0091091404 | AC15: 0.011044282 | AD15: 0.002240055 | AE15: 0.0020146249 | AF15: 0.0031661548 | AG15: 0.01082765 | AH15: -0.029980976 | AI15: -0.00076816816 | AJ15: -0.00096962616 | AK15: -0.0045209018
A16: =IFERROR(__xludf.DUMMYFUNCTION("""COMPUTED_VALUE"""),45701.66666666667) -> 45701.667 | B16: =IFERROR(__xludf.DUMMYFUNCTION("""COMPUTED_VALUE"""),609.73) -> 609.73 | C16: =IFERROR(__xludf.DUMMYFUNCTION("IFERROR(VLOOKUP($A16, GOOGLEFINANCE(C$1, ""price"", $A$2, TODAY()), 2, FALSE), """")"),119.58) -> 119.58 | D16: =IFERROR(__xludf.DUMMYFUNCTION("IFERROR(VLOOKUP($A16, GOOGLEFINANCE(D$1, ""price"", $A$2, TODAY()), 2, FALSE), """")"),113.55) -> 113.55 | E16: =IFERROR(__xludf.DUMMYFUNCTION("IFERROR(VLOOKUP($A16, GOOGLEFINANCE(E$1, ""price"", $A$2, TODAY()), 2, FALSE), """")"),51.7) -> 51.7 | F16: =IFERROR(__xludf.DUMMYFUNCTION("IFERROR(VLOOKUP($A16, GOOGLEFINANCE(F$1, ""price"", $A$2, TODAY()), 2, FALSE), """")"),104.67) -> 104.67 | G16: =IFERROR(__xludf.DUMMYFUNCTION("IFERROR(VLOOKUP($A16, GOOGLEFINANCE(G$1, ""price"", $A$2, TODAY()), 2, FALSE), """")"),146.39) -> 146.39 | H16: =IFERROR(__xludf.DUMMYFUNCTION("IFERROR(VLOOKUP($A16, GOOGLEFINANCE(H$1, ""price"", $A$2, TODAY()), 2, FALSE), """")"),81.42) -> 81.42 | I16: =IFERROR(__xludf.DUMMYFUNCTION("IFERROR(VLOOKUP($A16, GOOGLEFINANCE(I$1, ""price"", $A$2, TODAY()), 2, FALSE), """")"),137.89) -> 137.89 | J16: =IFERROR(__xludf.DUMMYFUNCTION("IFERROR(VLOOKUP($A16, GOOGLEFINANCE(J$1, ""price"", $A$2, TODAY()), 2, FALSE), """")"),44.86) -> 44.86 | K16: =IFERROR(__xludf.DUMMYFUNCTION("IFERROR(VLOOKUP($A16, GOOGLEFINANCE(K$1, ""price"", $A$2, TODAY()), 2, FALSE), """")"),45.08) -> 45.08 | L16: =IFERROR(__xludf.DUMMYFUNCTION("IFERROR(VLOOKUP($A16, GOOGLEFINANCE(L$1, ""price"", $A$2, TODAY()), 2, FALSE), """")"),39.72) -> 39.72 | M16: =IFERROR(__xludf.DUMMYFUNCTION("IFERROR(VLOOKUP($A16, GOOGLEFINANCE(M$1, ""price"", $A$2, TODAY()), 2, FALSE), """")"),42.23) -> 42.23 | O16: 0.19611959 | P16: 0.18622997 | Q16: 0.084791629 | R16: 0.17166615 | S16: 0.24008988 | T16: 0.13353452 | U16: 0.22614928 | V16: 0.073573549 | W16: 0.073934364 | X16: 0.065143588 | Y16: 0.069260164 | AA16: 0.0018732048 | AB16: 0.023139273 | AC16: 0.0023623636 | AD16: -0.00029714213 | AE16: -0.016325069 | AF16: -0.025155791 | AG16: 0.00619993 | AH16: -0.029256324 | AI16: 0.0071794408 | AJ16: -0.026351662 | AK16: -0.016056287
A17: =IFERROR(__xludf.DUMMYFUNCTION("""COMPUTED_VALUE"""),45702.66666666667) -> 45702.667 | B17: =IFERROR(__xludf.DUMMYFUNCTION("""COMPUTED_VALUE"""),609.7) -> 609.7 | C17: =IFERROR(__xludf.DUMMYFUNCTION("IFERROR(VLOOKUP($A17, GOOGLEFINANCE(C$1, ""price"", $A$2, TODAY()), 2, FALSE), """")"),119.99) -> 119.99 | D17: =IFERROR(__xludf.DUMMYFUNCTION("IFERROR(VLOOKUP($A17, GOOGLEFINANCE(D$1, ""price"", $A$2, TODAY()), 2, FALSE), """")"),113.5) -> 113.5 | E17: =IFERROR(__xludf.DUMMYFUNCTION("IFERROR(VLOOKUP($A17, GOOGLEFINANCE(E$1, ""price"", $A$2, TODAY()), 2, FALSE), """")"),51.8) -> 51.8 | F17: =IFERROR(__xludf.DUMMYFUNCTION("IFERROR(VLOOKUP($A17, GOOGLEFINANCE(F$1, ""price"", $A$2, TODAY()), 2, FALSE), """")"),105.31) -> 105.31 | G17: =IFERROR(__xludf.DUMMYFUNCTION("IFERROR(VLOOKUP($A17, GOOGLEFINANCE(G$1, ""price"", $A$2, TODAY()), 2, FALSE), """")"),144.8) -> 144.8 | H17: =IFERROR(__xludf.DUMMYFUNCTION("IFERROR(VLOOKUP($A17, GOOGLEFINANCE(H$1, ""price"", $A$2, TODAY()), 2, FALSE), """")"),80.61) -> 80.61 | I17: =IFERROR(__xludf.DUMMYFUNCTION("IFERROR(VLOOKUP($A17, GOOGLEFINANCE(I$1, ""price"", $A$2, TODAY()), 2, FALSE), """")"),137.55) -> 137.55 | J17: =IFERROR(__xludf.DUMMYFUNCTION("IFERROR(VLOOKUP($A17, GOOGLEFINANCE(J$1, ""price"", $A$2, TODAY()), 2, FALSE), """")"),45.04) -> 45.04 | K17: =IFERROR(__xludf.DUMMYFUNCTION("IFERROR(VLOOKUP($A17, GOOGLEFINANCE(K$1, ""price"", $A$2, TODAY()), 2, FALSE), """")"),44.93) -> 44.93 | L17: =IFERROR(__xludf.DUMMYFUNCTION("IFERROR(VLOOKUP($A17, GOOGLEFINANCE(L$1, ""price"", $A$2, TODAY()), 2, FALSE), """")"),39.55) -> 39.55 | M17: =IFERROR(__xludf.DUMMYFUNCTION("IFERROR(VLOOKUP($A17, GOOGLEFINANCE(M$1, ""price"", $A$2, TODAY()), 2, FALSE), """")"),42.06) -> 42.06 | O17: 0.19680171 | P17: 0.18615713 | Q17: 0.084959816 | R17: 0.17272429 | S17: 0.23749385 | T17: 0.13221256 | U17: 0.22560276 | V17: 0.073872396 | W17: 0.07369198 | X17: 0.064867968 | Y17: 0.068984747 | AA17: 0.015307072 | AB17: 0.021922029 | AC17: -0.0045349834 | AD17: -0.00065226109 | AE17: -0.039197251 | AF17: -0.042112519 | AG17: 0.0037415003 | AH17: -0.029961878 | AI17: 0.00044526424 | AJ17: -0.030050098 | AK17: -0.028798196
A18: =IFERROR(__xludf.DUMMYFUNCTION("""COMPUTED_VALUE"""),45706.66666666667) -> 45706.667 | B18: =IFERROR(__xludf.DUMMYFUNCTION("""COMPUTED_VALUE"""),611.49) -> 611.49 | C18: =IFERROR(__xludf.DUMMYFUNCTION("IFERROR(VLOOKUP($A18, GOOGLEFINANCE(C$1, ""price"", $A$2, TODAY()), 2, FALSE), """")"),121.08) -> 121.08 | D18: =IFERROR(__xludf.DUMMYFUNCTION("IFERROR(VLOOKUP($A18, GOOGLEFINANCE(D$1, ""price"", $A$2, TODAY()), 2, FALSE), """")"),113.19) -> 113.19 | E18: =IFERROR(__xludf.DUMMYFUNCTION("IFERROR(VLOOKUP($A18, GOOGLEFINANCE(E$1, ""price"", $A$2, TODAY()), 2, FALSE), """")"),52.17) -> 52.17 | F18: =IFERROR(__xludf.DUMMYFUNCTION("IFERROR(VLOOKUP($A18, GOOGLEFINANCE(F$1, ""price"", $A$2, TODAY()), 2, FALSE), """")"),104.82) -> 104.82 | G18: =IFERROR(__xludf.DUMMYFUNCTION("IFERROR(VLOOKUP($A18, GOOGLEFINANCE(G$1, ""price"", $A$2, TODAY()), 2, FALSE), """")"),144.52) -> 144.52 | H18: =IFERROR(__xludf.DUMMYFUNCTION("IFERROR(VLOOKUP($A18, GOOGLEFINANCE(H$1, ""price"", $A$2, TODAY()), 2, FALSE), """")"),80.9) -> 80.9 | I18: =IFERROR(__xludf.DUMMYFUNCTION("IFERROR(VLOOKUP($A18, GOOGLEFINANCE(I$1, ""price"", $A$2, TODAY()), 2, FALSE), """")"),138.63) -> 138.63 | J18: =IFERROR(__xludf.DUMMYFUNCTION("IFERROR(VLOOKUP($A18, GOOGLEFINANCE(J$1, ""price"", $A$2, TODAY()), 2, FALSE), """")"),45.65) -> 45.65 | K18: =IFERROR(__xludf.DUMMYFUNCTION("IFERROR(VLOOKUP($A18, GOOGLEFINANCE(K$1, ""price"", $A$2, TODAY()), 2, FALSE), """")"),45.5) -> 45.5 | L18: =IFERROR(__xludf.DUMMYFUNCTION("IFERROR(VLOOKUP($A18, GOOGLEFINANCE(L$1, ""price"", $A$2, TODAY()), 2, FALSE), """")"),39.92) -> 39.92 | M18: =IFERROR(__xludf.DUMMYFUNCTION("IFERROR(VLOOKUP($A18, GOOGLEFINANCE(M$1, ""price"", $A$2, TODAY()), 2, FALSE), """")"),42.21) -> 42.21 | O18: 0.19800814 | P18: 0.18510523 | Q18: 0.085316195 | R18: 0.17141736 | S18: 0.23634074 | T18: 0.13229979 | U18: 0.22670853 | V18: 0.074653715 | W18: 0.074408412 | X18: 0.065283161 | Y18: 0.069028112 | AA18: 0.02979485 | AB18: 0.016419652 | AC18: -0.0051354859 | AD18: 0.0017017463 | AE18: -0.056732338 | AF18: -0.059595352 | AG18: -0.0014877125 | AH18: -0.010213668 | AI18: -0.0025613605 | AJ18: -0.023808116 | AK18: -0.043170864
A19: =IFERROR(__xludf.DUMMYFUNCTION("""COMPUTED_VALUE"""),45707.66666666667) -> 45707.667 | B19: =IFERROR(__xludf.DUMMYFUNCTION("""COMPUTED_VALUE"""),612.93) -> 612.93 | C19: =IFERROR(__xludf.DUMMYFUNCTION("IFERROR(VLOOKUP($A19, GOOGLEFINANCE(C$1, ""price"", $A$2, TODAY()), 2, FALSE), """")"),121.09) -> 121.09 | D19: =IFERROR(__xludf.DUMMYFUNCTION("IFERROR(VLOOKUP($A19, GOOGLEFINANCE(D$1, ""price"", $A$2, TODAY()), 2, FALSE), """")"),113.12) -> 113.12 | E19: =IFERROR(__xludf.DUMMYFUNCTION("IFERROR(VLOOKUP($A19, GOOGLEFINANCE(E$1, ""price"", $A$2, TODAY()), 2, FALSE), """")"),52.19) -> 52.19 | F19: =IFERROR(__xludf.DUMMYFUNCTION("IFERROR(VLOOKUP($A19, GOOGLEFINANCE(F$1, ""price"", $A$2, TODAY()), 2, FALSE), """")"),104.94) -> 104.94 | G19: =IFERROR(__xludf.DUMMYFUNCTION("IFERROR(VLOOKUP($A19, GOOGLEFINANCE(G$1, ""price"", $A$2, TODAY()), 2, FALSE), """")"),146.4) -> 146.4 | H19: =IFERROR(__xludf.DUMMYFUNCTION("IFERROR(VLOOKUP($A19, GOOGLEFINANCE(H$1, ""price"", $A$2, TODAY()), 2, FALSE), """")"),81.55) -> 81.55 | I19: =IFERROR(__xludf.DUMMYFUNCTION("IFERROR(VLOOKUP($A19, GOOGLEFINANCE(I$1, ""price"", $A$2, TODAY()), 2, FALSE), """")"),138.77) -> 138.77 | J19: =IFERROR(__xludf.DUMMYFUNCTION("IFERROR(VLOOKUP($A19, GOOGLEFINANCE(J$1, ""price"", $A$2, TODAY()), 2, FALSE), """")"),46.01) -> 46.01 | K19: =IFERROR(__xludf.DUMMYFUNCTION("IFERROR(VLOOKUP($A19, GOOGLEFINANCE(K$1, ""price"", $A$2, TODAY()), 2, FALSE), """")"),44.96) -> 44.96 | L19: =IFERROR(__xludf.DUMMYFUNCTION("IFERROR(VLOOKUP($A19, GOOGLEFINANCE(L$1, ""price"", $A$2, TODAY()), 2, FALSE), """")"),40.13) -> 40.13 | M19: =IFERROR(__xludf.DUMMYFUNCTION("IFERROR(VLOOKUP($A19, GOOGLEFINANCE(M$1, ""price"", $A$2, TODAY()), 2, FALSE), """")"),42.29) -> 42.29 | O19: 0.19755926 | P19: 0.18455615 | Q19: 0.085148386 | R19: 0.17121042 | S19: 0.23885272 | T19: 0.13304945 | U19: 0.22640432 | V19: 0.075065668 | W19: 0.073352585 | X19: 0.065472403 | Y19: 0.06899646 | AA19: 0.016942728 | AB19: 0.018149879 | AC19: -0.0044420612 | AD19: 0.0027725392 | AE19: -0.039321483 | AF19: -0.035326578 | AG19: -0.0029153737 | AH19: 0.0013359291 | AI19: -0.015774183 | AJ19: -0.024411967 | AK19: -0.03841643
A20: =IFERROR(__xludf.DUMMYFUNCTION("""COMPUTED_VALUE"""),45708.66666666667) -> 45708.667 | B20: =IFERROR(__xludf.DUMMYFUNCTION("""COMPUTED_VALUE"""),610.38) -> 610.38 | C20: =IFERROR(__xludf.DUMMYFUNCTION("IFERROR(VLOOKUP($A20, GOOGLEFINANCE(C$1, ""price"", $A$2, TODAY()), 2, FALSE), """")"),120.71) -> 120.71 | D20: =IFERROR(__xludf.DUMMYFUNCTION("IFERROR(VLOOKUP($A20, GOOGLEFINANCE(D$1, ""price"", $A$2, TODAY()), 2, FALSE), """")"),112.15) -> 112.15 | E20: =IFERROR(__xludf.DUMMYFUNCTION("IFERROR(VLOOKUP($A20, GOOGLEFINANCE(E$1, ""price"", $A$2, TODAY()), 2, FALSE), """")"),51.39) -> 51.39 | F20: =IFERROR(__xludf.DUMMYFUNCTION("IFERROR(VLOOKUP($A20, GOOGLEFINANCE(F$1, ""price"", $A$2, TODAY()), 2, FALSE), """")"),104.45) -> 104.45 | G20: =IFERROR(__xludf.DUMMYFUNCTION("IFERROR(VLOOKUP($A20, GOOGLEFINANCE(G$1, ""price"", $A$2, TODAY()), 2, FALSE), """")"),147.22) -> 147.22 | H20: =IFERROR(__xludf.DUMMYFUNCTION("IFERROR(VLOOKUP($A20, GOOGLEFINANCE(H$1, ""price"", $A$2, TODAY()), 2, FALSE), """")"),81.23) -> 81.23 | I20: =IFERROR(__xludf.DUMMYFUNCTION("IFERROR(VLOOKUP($A20, GOOGLEFINANCE(I$1, ""price"", $A$2, TODAY()), 2, FALSE), """")"),137.86) -> 137.86 | J20: =IFERROR(__xludf.DUMMYFUNCTION("IFERROR(VLOOKUP($A20, GOOGLEFINANCE(J$1, ""price"", $A$2, TODAY()), 2, FALSE), """")"),46.43) -> 46.43 | K20: =IFERROR(__xludf.DUMMYFUNCTION("IFERROR(VLOOKUP($A20, GOOGLEFINANCE(K$1, ""price"", $A$2, TODAY()), 2, FALSE), """")"),44.86) -> 44.86 | L20: =IFERROR(__xludf.DUMMYFUNCTION("IFERROR(VLOOKUP($A20, GOOGLEFINANCE(L$1, ""price"", $A$2, TODAY()), 2, FALSE), """")"),40.13) -> 40.13 | M20: =IFERROR(__xludf.DUMMYFUNCTION("IFERROR(VLOOKUP($A20, GOOGLEFINANCE(M$1, ""price"", $A$2, TODAY()), 2, FALSE), """")"),42.58) -> 42.58 | O20: 0.19776205 | P20: 0.183738 | Q20: 0.084193453 | R20: 0.17112291 | S20: 0.24119401 | T20: 0.13308103 | U20: 0.2258593 | V20: 0.076067368 | W20: 0.0734952 | X20: 0.065745929 | Y20: 0.069759822 | AA20: 0.039538969 | AB20: 0.012012017 | AC20: -0.036624686 | AD20: -0.0041235774 | AE20: -0.041498738 | AF20: -0.050383492 | AG20: -0.017773107 | AH20: -0.0068463831 | AI20: -0.022986444 | AJ20: -0.014232301 | AK20: -0.047538303
A21: =IFERROR(__xludf.DUMMYFUNCTION("""COMPUTED_VALUE"""),45709.66666666667) -> 45709.667 | B21: =IFERROR(__xludf.DUMMYFUNCTION("""COMPUTED_VALUE"""),599.94) -> 599.94 | C21: =IFERROR(__xludf.DUMMYFUNCTION("IFERROR(VLOOKUP($A21, GOOGLEFINANCE(C$1, ""price"", $A$2, TODAY()), 2, FALSE), """")"),117.44) -> 117.44 | D21: =IFERROR(__xludf.DUMMYFUNCTION("IFERROR(VLOOKUP($A21, GOOGLEFINANCE(D$1, ""price"", $A$2, TODAY()), 2, FALSE), """")"),109.2) -> 109.2 | E21: =IFERROR(__xludf.DUMMYFUNCTION("IFERROR(VLOOKUP($A21, GOOGLEFINANCE(E$1, ""price"", $A$2, TODAY()), 2, FALSE), """")"),50.75) -> 50.75 | F21: =IFERROR(__xludf.DUMMYFUNCTION("IFERROR(VLOOKUP($A21, GOOGLEFINANCE(F$1, ""price"", $A$2, TODAY()), 2, FALSE), """")"),103.02) -> 103.02 | G21: =IFERROR(__xludf.DUMMYFUNCTION("IFERROR(VLOOKUP($A21, GOOGLEFINANCE(G$1, ""price"", $A$2, TODAY()), 2, FALSE), """")"),146.43) -> 146.43 | H21: =IFERROR(__xludf.DUMMYFUNCTION("IFERROR(VLOOKUP($A21, GOOGLEFINANCE(H$1, ""price"", $A$2, TODAY()), 2, FALSE), """")"),82.18) -> 82.18 | I21: =IFERROR(__xludf.DUMMYFUNCTION("IFERROR(VLOOKUP($A21, GOOGLEFINANCE(I$1, ""price"", $A$2, TODAY()), 2, FALSE), """")"),134.84) -> 134.84 | J21: =IFERROR(__xludf.DUMMYFUNCTION("IFERROR(VLOOKUP($A21, GOOGLEFINANCE(J$1, ""price"", $A$2, TODAY()), 2, FALSE), """")"),45.47) -> 45.47 | K21: =IFERROR(__xludf.DUMMYFUNCTION("IFERROR(VLOOKUP($A21, GOOGLEFINANCE(K$1, ""price"", $A$2, TODAY()), 2, FALSE), """")"),44.04) -> 44.04 | L21: =IFERROR(__xludf.DUMMYFUNCTION("IFERROR(VLOOKUP($A21, GOOGLEFINANCE(L$1, ""price"", $A$2, TODAY()), 2, FALSE), """")"),40.14) -> 40.14 | M21: =IFERROR(__xludf.DUMMYFUNCTION("IFERROR(VLOOKUP($A21, GOOGLEFINANCE(M$1, ""price"", $A$2, TODAY()), 2, FALSE), """")"),42.23) -> 42.23 | O21: 0.19575291 | P21: 0.1820182 | Q21: 0.084591793 | R21: 0.17171717 | S21: 0.24407441 | T21: 0.13698036 | U21: 0.22475581 | V21: 0.075790912 | W21: 0.073407341 | X21: 0.066906691 | Y21: 0.070390372 | AA21: 0.031413171 | AB21: 0.0015889531 | AC21: -0.036742981 | AD21: 0.0003030303 | AE21: -0.026226204 | AF21: -0.020329886 | AG21: -0.02042539 | AH21: -0.01025397 | AI21: -0.017188515 | AJ21: 0.0036510341 | AK21: -0.030717232
A22: =IFERROR(__xludf.DUMMYFUNCTION("""COMPUTED_VALUE"""),45712.66666666667) -> 45712.667 | B22: =IFERROR(__xludf.DUMMYFUNCTION("""COMPUTED_VALUE"""),597.21) -> 597.21 | C22: =IFERROR(__xludf.DUMMYFUNCTION("IFERROR(VLOOKUP($A22, GOOGLEFINANCE(C$1, ""price"", $A$2, TODAY()), 2, FALSE), """")"),115.76) -> 115.76 | D22: =IFERROR(__xludf.DUMMYFUNCTION("IFERROR(VLOOKUP($A22, GOOGLEFINANCE(D$1, ""price"", $A$2, TODAY()), 2, FALSE), """")"),108.79) -> 108.79 | E22: =IFERROR(__xludf.DUMMYFUNCTION("IFERROR(VLOOKUP($A22, GOOGLEFINANCE(E$1, ""price"", $A$2, TODAY()), 2, FALSE), """")"),50.97) -> 50.97 | F22: =IFERROR(__xludf.DUMMYFUNCTION("IFERROR(VLOOKUP($A22, GOOGLEFINANCE(F$1, ""price"", $A$2, TODAY()), 2, FALSE), """")"),103.22) -> 103.22 | G22: =IFERROR(__xludf.DUMMYFUNCTION("IFERROR(VLOOKUP($A22, GOOGLEFINANCE(G$1, ""price"", $A$2, TODAY()), 2, FALSE), """")"),147.62) -> 147.62 | H22: =IFERROR(__xludf.DUMMYFUNCTION("IFERROR(VLOOKUP($A22, GOOGLEFINANCE(H$1, ""price"", $A$2, TODAY()), 2, FALSE), """")"),82.43) -> 82.43 | I22: =IFERROR(__xludf.DUMMYFUNCTION("IFERROR(VLOOKUP($A22, GOOGLEFINANCE(I$1, ""price"", $A$2, TODAY()), 2, FALSE), """")"),134.23) -> 134.23 | J22: =IFERROR(__xludf.DUMMYFUNCTION("IFERROR(VLOOKUP($A22, GOOGLEFINANCE(J$1, ""price"", $A$2, TODAY()), 2, FALSE), """")"),45.48) -> 45.48 | K22: =IFERROR(__xludf.DUMMYFUNCTION("IFERROR(VLOOKUP($A22, GOOGLEFINANCE(K$1, ""price"", $A$2, TODAY()), 2, FALSE), """")"),43.99) -> 43.99 | L22: =IFERROR(__xludf.DUMMYFUNCTION("IFERROR(VLOOKUP($A22, GOOGLEFINANCE(L$1, ""price"", $A$2, TODAY()), 2, FALSE), """")"),39.94) -> 39.94 | M22: =IFERROR(__xludf.DUMMYFUNCTION("IFERROR(VLOOKUP($A22, GOOGLEFINANCE(M$1, ""price"", $A$2, TODAY()), 2, FALSE), """")"),42.42) -> 42.42 | O22: 0.19383466 | P22: 0.18216373 | Q22: 0.085346863 | R22: 0.17283703 | S22: 0.24718273 | T22: 0.13802515 | U22: 0.22476181 | V22: 0.076154117 | W22: 0.073659182 | X22: 0.066877648 | Y22: 0.071030291 | AA22: 0.034889904 | AB22: 0.0033184215 | AC22: -0.037051833 | AD22: -0.000821248 | AE22: -0.035313116 | AF22: -0.03526171 | AG22: -0.023668418 | AH22: 0.012445654 | AI22: -0.011266484 | AJ22: -0.015851666 | AK22: -0.04721156
A23: =IFERROR(__xludf.DUMMYFUNCTION("""COMPUTED_VALUE"""),45713.66666666667) -> 45713.667 | B23: =IFERROR(__xludf.DUMMYFUNCTION("""COMPUTED_VALUE"""),594.24) -> 594.24 | C23: =IFERROR(__xludf.DUMMYFUNCTION("IFERROR(VLOOKUP($A23, GOOGLEFINANCE(C$1, ""price"", $A$2, TODAY()), 2, FALSE), """")"),114.26) -> 114.26 | D23: =IFERROR(__xludf.DUMMYFUNCTION("IFERROR(VLOOKUP($A23, GOOGLEFINANCE(D$1, ""price"", $A$2, TODAY()), 2, FALSE), """")"),108.22) -> 108.22 | E23: =IFERROR(__xludf.DUMMYFUNCTION("IFERROR(VLOOKUP($A23, GOOGLEFINANCE(E$1, ""price"", $A$2, TODAY()), 2, FALSE), """")"),50.96) -> 50.96 | F23: =IFERROR(__xludf.DUMMYFUNCTION("IFERROR(VLOOKUP($A23, GOOGLEFINANCE(F$1, ""price"", $A$2, TODAY()), 2, FALSE), """")"),101.69) -> 101.69 | G23: =IFERROR(__xludf.DUMMYFUNCTION("IFERROR(VLOOKUP($A23, GOOGLEFINANCE(G$1, ""price"", $A$2, TODAY()), 2, FALSE), """")"),148.89) -> 148.89 | H23: =IFERROR(__xludf.DUMMYFUNCTION("IFERROR(VLOOKUP($A23, GOOGLEFINANCE(H$1, ""price"", $A$2, TODAY()), 2, FALSE), """")"),83.6) -> 83.6 | I23: =IFERROR(__xludf.DUMMYFUNCTION("IFERROR(VLOOKUP($A23, GOOGLEFINANCE(I$1, ""price"", $A$2, TODAY()), 2, FALSE), """")"),134.92) -> 134.92 | J23: =IFERROR(__xludf.DUMMYFUNCTION("IFERROR(VLOOKUP($A23, GOOGLEFINANCE(J$1, ""price"", $A$2, TODAY()), 2, FALSE), """")"),44.82) -> 44.82 | K23: =IFERROR(__xludf.DUMMYFUNCTION("IFERROR(VLOOKUP($A23, GOOGLEFINANCE(K$1, ""price"", $A$2, TODAY()), 2, FALSE), """")"),44.33) -> 44.33 | L23: =IFERROR(__xludf.DUMMYFUNCTION("IFERROR(VLOOKUP($A23, GOOGLEFINANCE(L$1, ""price"", $A$2, TODAY()), 2, FALSE), """")"),39.74) -> 39.74 | M23: =IFERROR(__xludf.DUMMYFUNCTION("IFERROR(VLOOKUP($A23, GOOGLEFINANCE(M$1, ""price"", $A$2, TODAY()), 2, FALSE), """")"),42.87) -> 42.87 | O23: 0.19227921 | P23: 0.18211497 | Q23: 0.085756597 | R23: 0.17112614 | S23: 0.25055533 | T23: 0.1406839 | U23: 0.22704631 | V23: 0.075424071 | W23: 0.074599488 | X23: 0.066875337 | Y23: 0.072142569 | AA23: 0.015269449 | AB23: 0.0089785038 | AC23: -0.0090234305 | AD23: -0.014615416 | AE23: -0.024661932 | AF23: -0.011511403 | AG23: -0.0060413212 | AH23: 0.00043986306 | AI23: 0.0031109765 | AJ23: -0.011335042 | AK23: -0.032632214
A24: =IFERROR(__xludf.DUMMYFUNCTION("""COMPUTED_VALUE"""),45714.66666666667) -> 45714.667 | B24: =IFERROR(__xludf.DUMMYFUNCTION("""COMPUTED_VALUE"""),594.54) -> 594.54 | C24: =IFERROR(__xludf.DUMMYFUNCTION("IFERROR(VLOOKUP($A24, GOOGLEFINANCE(C$1, ""price"", $A$2, TODAY()), 2, FALSE), """")"),115.5) -> 115.5 | D24: =IFERROR(__xludf.DUMMYFUNCTION("IFERROR(VLOOKUP($A24, GOOGLEFINANCE(D$1, ""price"", $A$2, TODAY()), 2, FALSE), """")"),107.77) -> 107.77 | E24: =IFERROR(__xludf.DUMMYFUNCTION("IFERROR(VLOOKUP($A24, GOOGLEFINANCE(E$1, ""price"", $A$2, TODAY()), 2, FALSE), """")"),50.85) -> 50.85 | F24: =IFERROR(__xludf.DUMMYFUNCTION("IFERROR(VLOOKUP($A24, GOOGLEFINANCE(F$1, ""price"", $A$2, TODAY()), 2, FALSE), """")"),101.51) -> 101.51 | G24: =IFERROR(__xludf.DUMMYFUNCTION("IFERROR(VLOOKUP($A24, GOOGLEFINANCE(G$1, ""price"", $A$2, TODAY()), 2, FALSE), """")"),147.82) -> 147.82 | H24: =IFERROR(__xludf.DUMMYFUNCTION("IFERROR(VLOOKUP($A24, GOOGLEFINANCE(H$1, ""price"", $A$2, TODAY()), 2, FALSE), """")"),82.0) -> 82 | I24: =IFERROR(__xludf.DUMMYFUNCTION("IFERROR(VLOOKUP($A24, GOOGLEFINANCE(I$1, ""price"", $A$2, TODAY()), 2, FALSE), """")"),135.0) -> 135 | J24: =IFERROR(__xludf.DUMMYFUNCTION("IFERROR(VLOOKUP($A24, GOOGLEFINANCE(J$1, ""price"", $A$2, TODAY()), 2, FALSE), """")"),44.57) -> 44.57 | K24: =IFERROR(__xludf.DUMMYFUNCTION("IFERROR(VLOOKUP($A24, GOOGLEFINANCE(K$1, ""price"", $A$2, TODAY()), 2, FALSE), """")"),44.31) -> 44.31 | L24: =IFERROR(__xludf.DUMMYFUNCTION("IFERROR(VLOOKUP($A24, GOOGLEFINANCE(L$1, ""price"", $A$2, TODAY()), 2, FALSE), """")"),39.9) -> 39.9 | M24: =IFERROR(__xludf.DUMMYFUNCTION("IFERROR(VLOOKUP($A24, GOOGLEFINANCE(M$1, ""price"", $A$2, TODAY()), 2, FALSE), """")"),42.66) -> 42.66 | O24: 0.19426784 | P24: 0.18126619 | Q24: 0.085528308 | R24: 0.17073704 | S24: 0.24862919 | T24: 0.13792175 | U24: 0.2270663 | V24: 0.07496552 | W24: 0.074528207 | X24: 0.067110707 | Y24: 0.071752952 | AA24: 0.022382934 | AB24: -0.00019804985 | AC24: -0.0068087029 | AD24: -0.018922452 | AE24: -0.031495611 | AF24: -0.024543204 | AG24: -0.010883236 | AH24: 0.020055912 | AI24: -0.012848337 | AJ24: 0.010055991 | AK24: -0.036474525
A25: =IFERROR(__xludf.DUMMYFUNCTION("""COMPUTED_VALUE"""),45715.66666666667) -> 45715.667 | B25: =IFERROR(__xludf.DUMMYFUNCTION("""COMPUTED_VALUE"""),585.05) -> 585.05 | C25: =IFERROR(__xludf.DUMMYFUNCTION("IFERROR(VLOOKUP($A25, GOOGLEFINANCE(C$1, ""price"", $A$2, TODAY()), 2, FALSE), """")"),111.3) -> 111.3 | D25: =IFERROR(__xludf.DUMMYFUNCTION("IFERROR(VLOOKUP($A25, GOOGLEFINANCE(D$1, ""price"", $A$2, TODAY()), 2, FALSE), """")"),106.22) -> 106.22 | E25: =IFERROR(__xludf.DUMMYFUNCTION("IFERROR(VLOOKUP($A25, GOOGLEFINANCE(E$1, ""price"", $A$2, TODAY()), 2, FALSE), """")"),51.13) -> 51.13 | F25: =IFERROR(__xludf.DUMMYFUNCTION("IFERROR(VLOOKUP($A25, GOOGLEFINANCE(F$1, ""price"", $A$2, TODAY()), 2, FALSE), """")"),100.53) -> 100.53 | G25: =IFERROR(__xludf.DUMMYFUNCTION("IFERROR(VLOOKUP($A25, GOOGLEFINANCE(G$1, ""price"", $A$2, TODAY()), 2, FALSE), """")"),147.22) -> 147.22 | H25: =IFERROR(__xludf.DUMMYFUNCTION("IFERROR(VLOOKUP($A25, GOOGLEFINANCE(H$1, ""price"", $A$2, TODAY()), 2, FALSE), """")"),81.99) -> 81.99 | I25: =IFERROR(__xludf.DUMMYFUNCTION("IFERROR(VLOOKUP($A25, GOOGLEFINANCE(I$1, ""price"", $A$2, TODAY()), 2, FALSE), """")"),134.53) -> 134.53 | J25: =IFERROR(__xludf.DUMMYFUNCTION("IFERROR(VLOOKUP($A25, GOOGLEFINANCE(J$1, ""price"", $A$2, TODAY()), 2, FALSE), """")"),44.81) -> 44.81 | K25: =IFERROR(__xludf.DUMMYFUNCTION("IFERROR(VLOOKUP($A25, GOOGLEFINANCE(K$1, ""price"", $A$2, TODAY()), 2, FALSE), """")"),44.01) -> 44.01 | L25: =IFERROR(__xludf.DUMMYFUNCTION("IFERROR(VLOOKUP($A25, GOOGLEFINANCE(L$1, ""price"", $A$2, TODAY()), 2, FALSE), """")"),39.02) -> 39.02 | M25: =IFERROR(__xludf.DUMMYFUNCTION("IFERROR(VLOOKUP($A25, GOOGLEFINANCE(M$1, ""price"", $A$2, TODAY()), 2, FALSE), """")"),42.85) -> 42.85 | O25: 0.19024015 | P25: 0.18155713 | Q25: 0.08739424 | R25: 0.17183147 | S25: 0.25163661 | T25: 0.14014187 | U25: 0.22994616 | V25: 0.076591744 | W25: 0.07522434 | X25: 0.066695154 | Y25: 0.073241603 | AA25: 0.011535016 | AB25: 0.0092165873 | AC25: 0.013599738 | AD25: -0.01244757 | AE25: -0.034536047 | AF25: -0.028203786 | AG25: -0.0075925817 | AH25: 0.020587666 | AI25: -0.016174203 | AJ25: 0.0067733737 | AK25: -0.0067203738
A26: =IFERROR(__xludf.DUMMYFUNCTION("""COMPUTED_VALUE"""),45716.66666666667) -> 45716.667 | B26: =IFERROR(__xludf.DUMMYFUNCTION("""COMPUTED_VALUE"""),594.18) -> 594.18 | C26: =IFERROR(__xludf.DUMMYFUNCTION("IFERROR(VLOOKUP($A26, GOOGLEFINANCE(C$1, ""price"", $A$2, TODAY()), 2, FALSE), """")"),112.77) -> 112.77 | D26: =IFERROR(__xludf.DUMMYFUNCTION("IFERROR(VLOOKUP($A26, GOOGLEFINANCE(D$1, ""price"", $A$2, TODAY()), 2, FALSE), """")"),107.98) -> 107.98 | E26: =IFERROR(__xludf.DUMMYFUNCTION("IFERROR(VLOOKUP($A26, GOOGLEFINANCE(E$1, ""price"", $A$2, TODAY()), 2, FALSE), """")"),52.18) -> 52.18 | F26: =IFERROR(__xludf.DUMMYFUNCTION("IFERROR(VLOOKUP($A26, GOOGLEFINANCE(F$1, ""price"", $A$2, TODAY()), 2, FALSE), """")"),102.0) -> 102 | G26: =IFERROR(__xludf.DUMMYFUNCTION("IFERROR(VLOOKUP($A26, GOOGLEFINANCE(G$1, ""price"", $A$2, TODAY()), 2, FALSE), """")"),148.93) -> 148.93 | H26: =IFERROR(__xludf.DUMMYFUNCTION("IFERROR(VLOOKUP($A26, GOOGLEFINANCE(H$1, ""price"", $A$2, TODAY()), 2, FALSE), """")"),83.08) -> 83.08 | I26: =IFERROR(__xludf.DUMMYFUNCTION("IFERROR(VLOOKUP($A26, GOOGLEFINANCE(I$1, ""price"", $A$2, TODAY()), 2, FALSE), """")"),136.33) -> 136.33 | J26: =IFERROR(__xludf.DUMMYFUNCTION("IFERROR(VLOOKUP($A26, GOOGLEFINANCE(J$1, ""price"", $A$2, TODAY()), 2, FALSE), """")"),45.5) -> 45.5 | K26: =IFERROR(__xludf.DUMMYFUNCTION("IFERROR(VLOOKUP($A26, GOOGLEFINANCE(K$1, ""price"", $A$2, TODAY()), 2, FALSE), """")"),44.38) -> 44.38 | L26: =IFERROR(__xludf.DUMMYFUNCTION("IFERROR(VLOOKUP($A26, GOOGLEFINANCE(L$1, ""price"", $A$2, TODAY()), 2, FALSE), """")"),39.61) -> 39.61 | M26: =IFERROR(__xludf.DUMMYFUNCTION("IFERROR(VLOOKUP($A26, GOOGLEFINANCE(M$1, ""price"", $A$2, TODAY()), 2, FALSE), """")"),43.15) -> 43.15 | O26: 0.18979097 | P26: 0.18172944 | Q26: 0.087818506 | R26: 0.17166515 | S26: 0.25064795 | T26: 0.13982295 | U26: 0.22944226 | V26: 0.076576122 | W26: 0.074691171 | X26: 0.066663301 | Y26: 0.072621091 | AA26: 0.00031497065 | AB26: 0.01771315 | AC26: 0.029650531 | AD26: -0.014204863 | AE26: -0.033003963 | AF26: -0.028157942 | AG26: -0.015714083 | AH26: 0.008731016 | AI26: -0.020356656 | AJ26: -0.006656452 | AK26: -0.015212176
A27: =IFERROR(__xludf.DUMMYFUNCTION("""COMPUTED_VALUE"""),45719.66666666667) -> 45719.667 | B27: =IFERROR(__xludf.DUMMYFUNCTION("""COMPUTED_VALUE"""),583.77) -> 583.77 | C27: =IFERROR(__xludf.DUMMYFUNCTION("IFERROR(VLOOKUP($A27, GOOGLEFINANCE(C$1, ""price"", $A$2, TODAY()), 2, FALSE), """")"),109.34) -> 109.34 | D27: =IFERROR(__xludf.DUMMYFUNCTION("IFERROR(VLOOKUP($A27, GOOGLEFINANCE(D$1, ""price"", $A$2, TODAY()), 2, FALSE), """")"),105.99) -> 105.99 | E27: =IFERROR(__xludf.DUMMYFUNCTION("IFERROR(VLOOKUP($A27, GOOGLEFINANCE(E$1, ""price"", $A$2, TODAY()), 2, FALSE), """")"),51.74) -> 51.74 | F27: =IFERROR(__xludf.DUMMYFUNCTION("IFERROR(VLOOKUP($A27, GOOGLEFINANCE(F$1, ""price"", $A$2, TODAY()), 2, FALSE), """")"),100.98) -> 100.98 | G27: =IFERROR(__xludf.DUMMYFUNCTION("IFERROR(VLOOKUP($A27, GOOGLEFINANCE(G$1, ""price"", $A$2, TODAY()), 2, FALSE), """")"),149.58) -> 149.58 | H27: =IFERROR(__xludf.DUMMYFUNCTION("IFERROR(VLOOKUP($A27, GOOGLEFINANCE(H$1, ""price"", $A$2, TODAY()), 2, FALSE), """")"),83.52) -> 83.52 | I27: =IFERROR(__xludf.DUMMYFUNCTION("IFERROR(VLOOKUP($A27, GOOGLEFINANCE(I$1, ""price"", $A$2, TODAY()), 2, FALSE), """")"),134.39) -> 134.39 | J27: =IFERROR(__xludf.DUMMYFUNCTION("IFERROR(VLOOKUP($A27, GOOGLEFINANCE(J$1, ""price"", $A$2, TODAY()), 2, FALSE), """")"),43.91) -> 43.91 | K27: =IFERROR(__xludf.DUMMYFUNCTION("IFERROR(VLOOKUP($A27, GOOGLEFINANCE(K$1, ""price"", $A$2, TODAY()), 2, FALSE), """")"),43.49) -> 43.49 | L27: =IFERROR(__xludf.DUMMYFUNCTION("IFERROR(VLOOKUP($A27, GOOGLEFINANCE(L$1, ""price"", $A$2, TODAY()), 2, FALSE), """")"),39.67) -> 39.67 | M27: =IFERROR(__xludf.DUMMYFUNCTION("IFERROR(VLOOKUP($A27, GOOGLEFINANCE(M$1, ""price"", $A$2, TODAY()), 2, FALSE), """")"),43.52) -> 43.52 | O27: 0.18729979 | P27: 0.18156123 | Q27: 0.088630796 | R27: 0.17297908 | S27: 0.25623105 | T27: 0.14307004 | U27: 0.23021053 | V27: 0.07521798 | W27: 0.074498518 | X27: 0.067954845 | Y27: 0.074549908 | AA27: 0.0035029896 | AB27: 0.02631436 | AC27: 0.034665802 | AD27: -0.0083994781 | AE27: -0.027304111 | AF27: -0.029968485 | AG27: -0.023447462 | AH27: -0.04255915 | AI27: -0.028781875 | AJ27: -0.02497755 | AK27: -0.0063911644
A28: =IFERROR(__xludf.DUMMYFUNCTION("""COMPUTED_VALUE"""),45720.66666666667) -> 45720.667 | B28: =IFERROR(__xludf.DUMMYFUNCTION("""COMPUTED_VALUE"""),576.86) -> 576.86 | C28: =IFERROR(__xludf.DUMMYFUNCTION("IFERROR(VLOOKUP($A28, GOOGLEFINANCE(C$1, ""price"", $A$2, TODAY()), 2, FALSE), """")"),109.25) -> 109.25 | D28: =IFERROR(__xludf.DUMMYFUNCTION("IFERROR(VLOOKUP($A28, GOOGLEFINANCE(D$1, ""price"", $A$2, TODAY()), 2, FALSE), """")"),104.12) -> 104.12 | E28: =IFERROR(__xludf.DUMMYFUNCTION("IFERROR(VLOOKUP($A28, GOOGLEFINANCE(E$1, ""price"", $A$2, TODAY()), 2, FALSE), """")"),49.92) -> 49.92 | F28: =IFERROR(__xludf.DUMMYFUNCTION("IFERROR(VLOOKUP($A28, GOOGLEFINANCE(F$1, ""price"", $A$2, TODAY()), 2, FALSE), """")"),100.18) -> 100.18 | G28: =IFERROR(__xludf.DUMMYFUNCTION("IFERROR(VLOOKUP($A28, GOOGLEFINANCE(G$1, ""price"", $A$2, TODAY()), 2, FALSE), """")"),148.19) -> 148.19 | H28: =IFERROR(__xludf.DUMMYFUNCTION("IFERROR(VLOOKUP($A28, GOOGLEFINANCE(H$1, ""price"", $A$2, TODAY()), 2, FALSE), """")"),82.1) -> 82.1 | I28: =IFERROR(__xludf.DUMMYFUNCTION("IFERROR(VLOOKUP($A28, GOOGLEFINANCE(I$1, ""price"", $A$2, TODAY()), 2, FALSE), """")"),131.77) -> 131.77 | J28: =IFERROR(__xludf.DUMMYFUNCTION("IFERROR(VLOOKUP($A28, GOOGLEFINANCE(J$1, ""price"", $A$2, TODAY()), 2, FALSE), """")"),43.49) -> 43.49 | K28: =IFERROR(__xludf.DUMMYFUNCTION("IFERROR(VLOOKUP($A28, GOOGLEFINANCE(K$1, ""price"", $A$2, TODAY()), 2, FALSE), """")"),42.9) -> 42.9 | L28: =IFERROR(__xludf.DUMMYFUNCTION("IFERROR(VLOOKUP($A28, GOOGLEFINANCE(L$1, ""price"", $A$2, TODAY()), 2, FALSE), """")"),39.02) -> 39.02 | M28: =IFERROR(__xludf.DUMMYFUNCTION("IFERROR(VLOOKUP($A28, GOOGLEFINANCE(M$1, ""price"", $A$2, TODAY()), 2, FALSE), """")"),43.02) -> 43.02 | O28: 0.18938737 | P28: 0.1804944 | Q28: 0.086537461 | R28: 0.17366432 | S28: 0.25689075 | T28: 0.14232223 | U28: 0.22842631 | V28: 0.075390909 | W28: 0.074368131 | X28: 0.067642062 | Y28: 0.074576154 | AA28: 0.010405263 | AB28: 0.021796815 | AC28: 0.010458004 | AD28: 0.0020079826 | AE28: -0.022246285 | AF28: -0.028847765 | AG28: -0.024079672 | AH28: -0.040711505 | AI28: -0.031105429 | AJ28: -0.028582402 | AK28: -0.0038833411
A29: =IFERROR(__xludf.DUMMYFUNCTION("""COMPUTED_VALUE"""),45721.66666666667) -> 45721.667 | B29: =IFERROR(__xludf.DUMMYFUNCTION("""COMPUTED_VALUE"""),583.06) -> 583.06 | C29: =IFERROR(__xludf.DUMMYFUNCTION("IFERROR(VLOOKUP($A29, GOOGLEFINANCE(C$1, ""price"", $A$2, TODAY()), 2, FALSE), """")"),110.79) -> 110.79 | D29: =IFERROR(__xludf.DUMMYFUNCTION("IFERROR(VLOOKUP($A29, GOOGLEFINANCE(D$1, ""price"", $A$2, TODAY()), 2, FALSE), """")"),105.71) -> 105.71 | E29: =IFERROR(__xludf.DUMMYFUNCTION("IFERROR(VLOOKUP($A29, GOOGLEFINANCE(E$1, ""price"", $A$2, TODAY()), 2, FALSE), """")"),50.21) -> 50.21 | F29: =IFERROR(__xludf.DUMMYFUNCTION("IFERROR(VLOOKUP($A29, GOOGLEFINANCE(F$1, ""price"", $A$2, TODAY()), 2, FALSE), """")"),101.47) -> 101.47 | G29: =IFERROR(__xludf.DUMMYFUNCTION("IFERROR(VLOOKUP($A29, GOOGLEFINANCE(G$1, ""price"", $A$2, TODAY()), 2, FALSE), """")"),149.68) -> 149.68 | H29: =IFERROR(__xludf.DUMMYFUNCTION("IFERROR(VLOOKUP($A29, GOOGLEFINANCE(H$1, ""price"", $A$2, TODAY()), 2, FALSE), """")"),82.44) -> 82.44 | I29: =IFERROR(__xludf.DUMMYFUNCTION("IFERROR(VLOOKUP($A29, GOOGLEFINANCE(I$1, ""price"", $A$2, TODAY()), 2, FALSE), """")"),133.85) -> 133.85 | J29: =IFERROR(__xludf.DUMMYFUNCTION("IFERROR(VLOOKUP($A29, GOOGLEFINANCE(J$1, ""price"", $A$2, TODAY()), 2, FALSE), """")"),42.85) -> 42.85 | K29: =IFERROR(__xludf.DUMMYFUNCTION("IFERROR(VLOOKUP($A29, GOOGLEFINANCE(K$1, ""price"", $A$2, TODAY()), 2, FALSE), """")"),44.02) -> 44.02 | L29: =IFERROR(__xludf.DUMMYFUNCTION("IFERROR(VLOOKUP($A29, GOOGLEFINANCE(L$1, ""price"", $A$2, TODAY()), 2, FALSE), """")"),38.74) -> 38.74 | M29: =IFERROR(__xludf.DUMMYFUNCTION("IFERROR(VLOOKUP($A29, GOOGLEFINANCE(M$1, ""price"", $A$2, TODAY()), 2, FALSE), """")"),43.42) -> 43.42 | O29: 0.19001475 | P29: 0.1813021 | Q29: 0.086114637 | R29: 0.17403012 | S29: 0.25671457 | T29: 0.14139197 | U29: 0.22956471 | V29: 0.073491579 | W29: 0.075498233 | X29: 0.066442562 | Y29: 0.07446918 | AA29: 0.0033403553 | AB29: 0.025861115 | AC29: 0.0093726288 | AD29: 0.0044429564 | AE29: -0.0078141464 | AF29: -0.0085354036 | AG29: -0.013935672 | AH29: -0.064200531 | AI29: -0.0065058222 | AJ29: -0.037762259 | AK29: 0.0035830851
A30: =IFERROR(__xludf.DUMMYFUNCTION("""COMPUTED_VALUE"""),45722.66666666667) -> 45722.667 | B30: =IFERROR(__xludf.DUMMYFUNCTION("""COMPUTED_VALUE"""),572.71) -> 572.71 | C30: =IFERROR(__xludf.DUMMYFUNCTION("IFERROR(VLOOKUP($A30, GOOGLEFINANCE(C$1, ""price"", $A$2, TODAY()), 2, FALSE), """")"),107.71) -> 107.71 | D30: =IFERROR(__xludf.DUMMYFUNCTION("IFERROR(VLOOKUP($A30, GOOGLEFINANCE(D$1, ""price"", $A$2, TODAY()), 2, FALSE), """")"),103.03) -> 103.03 | E30: =IFERROR(__xludf.DUMMYFUNCTION("IFERROR(VLOOKUP($A30, GOOGLEFINANCE(E$1, ""price"", $A$2, TODAY()), 2, FALSE), """")"),49.38) -> 49.38 | F30: =IFERROR(__xludf.DUMMYFUNCTION("IFERROR(VLOOKUP($A30, GOOGLEFINANCE(F$1, ""price"", $A$2, TODAY()), 2, FALSE), """")"),99.65) -> 99.65 | G30: =IFERROR(__xludf.DUMMYFUNCTION("IFERROR(VLOOKUP($A30, GOOGLEFINANCE(G$1, ""price"", $A$2, TODAY()), 2, FALSE), """")"),149.27) -> 149.27 | H30: =IFERROR(__xludf.DUMMYFUNCTION("IFERROR(VLOOKUP($A30, GOOGLEFINANCE(H$1, ""price"", $A$2, TODAY()), 2, FALSE), """")"),82.59) -> 82.59 | I30: =IFERROR(__xludf.DUMMYFUNCTION("IFERROR(VLOOKUP($A30, GOOGLEFINANCE(I$1, ""price"", $A$2, TODAY()), 2, FALSE), """")"),132.7) -> 132.7 | J30: =IFERROR(__xludf.DUMMYFUNCTION("IFERROR(VLOOKUP($A30, GOOGLEFINANCE(J$1, ""price"", $A$2, TODAY()), 2, FALSE), """")"),42.98) -> 42.98 | K30: =IFERROR(__xludf.DUMMYFUNCTION("IFERROR(VLOOKUP($A30, GOOGLEFINANCE(K$1, ""price"", $A$2, TODAY()), 2, FALSE), """")"),43.79) -> 43.79 | L30: =IFERROR(__xludf.DUMMYFUNCTION("IFERROR(VLOOKUP($A30, GOOGLEFINANCE(L$1, ""price"", $A$2, TODAY()), 2, FALSE), """")"),37.94) -> 37.94 | M30: =IFERROR(__xludf.DUMMYFUNCTION("IFERROR(VLOOKUP($A30, GOOGLEFINANCE(M$1, ""price"", $A$2, TODAY()), 2, FALSE), """")"),42.23) -> 42.23 | O30: 0.18807075 | P30: 0.17989908 | Q30: 0.086221648 | R30: 0.17399731 | S30: 0.26063802 | T30: 0.14420911 | U30: 0.2317054 | V30: 0.075046708 | W30: 0.076461036 | X30: 0.066246442 | Y30: 0.073737144 | AA30: -0.0011945131 | AB30: 0.030113693 | AC30: 0.0026221239 | AD30: 0.011657499 | AE30: -0.00075772391 | AF30: 0.0023923866 | AG30: -0.0078661902 | AH30: -0.050647956 | AI30: -0.0065470184 | AJ30: -0.05559428 | AK30: 3.3495963e-06
A31: =IFERROR(__xludf.DUMMYFUNCTION("""COMPUTED_VALUE"""),45723.66666666667) -> 45723.667 | B31: =IFERROR(__xludf.DUMMYFUNCTION("""COMPUTED_VALUE"""),575.92) -> 575.92 | C31: =IFERROR(__xludf.DUMMYFUNCTION("IFERROR(VLOOKUP($A31, GOOGLEFINANCE(C$1, ""price"", $A$2, TODAY()), 2, FALSE), """")"),109.27) -> 109.27 | D31: =IFERROR(__xludf.DUMMYFUNCTION("IFERROR(VLOOKUP($A31, GOOGLEFINANCE(D$1, ""price"", $A$2, TODAY()), 2, FALSE), """")"),102.84) -> 102.84 | E31: =IFERROR(__xludf.DUMMYFUNCTION("IFERROR(VLOOKUP($A31, GOOGLEFINANCE(E$1, ""price"", $A$2, TODAY()), 2, FALSE), """")"),49.12) -> 49.12 | F31: =IFERROR(__xludf.DUMMYFUNCTION("IFERROR(VLOOKUP($A31, GOOGLEFINANCE(F$1, ""price"", $A$2, TODAY()), 2, FALSE), """")"),100.29) -> 100.29 | G31: =IFERROR(__xludf.DUMMYFUNCTION("IFERROR(VLOOKUP($A31, GOOGLEFINANCE(G$1, ""price"", $A$2, TODAY()), 2, FALSE), """")"),149.28) -> 149.28 | H31: =IFERROR(__xludf.DUMMYFUNCTION("IFERROR(VLOOKUP($A31, GOOGLEFINANCE(H$1, ""price"", $A$2, TODAY()), 2, FALSE), """")"),82.86) -> 82.86 | I31: =IFERROR(__xludf.DUMMYFUNCTION("IFERROR(VLOOKUP($A31, GOOGLEFINANCE(I$1, ""price"", $A$2, TODAY()), 2, FALSE), """")"),134.25) -> 134.25 | J31: =IFERROR(__xludf.DUMMYFUNCTION("IFERROR(VLOOKUP($A31, GOOGLEFINANCE(J$1, ""price"", $A$2, TODAY()), 2, FALSE), """")"),43.72) -> 43.72 | K31: =IFERROR(__xludf.DUMMYFUNCTION("IFERROR(VLOOKUP($A31, GOOGLEFINANCE(K$1, ""price"", $A$2, TODAY()), 2, FALSE), """")"),43.91) -> 43.91 | L31: =IFERROR(__xludf.DUMMYFUNCTION("IFERROR(VLOOKUP($A31, GOOGLEFINANCE(L$1, ""price"", $A$2, TODAY()), 2, FALSE), """")"),38.65) -> 38.65 | M31: =IFERROR(__xludf.DUMMYFUNCTION("IFERROR(VLOOKUP($A31, GOOGLEFINANCE(M$1, ""price"", $A$2, TODAY()), 2, FALSE), """")"),42.47) -> 42.47 | O31: 0.18973121 | P31: 0.17856647 | Q31: 0.085289624 | R31: 0.17413877 | S31: 0.25920267 | T31: 0.14387415 | U31: 0.23310529 | V31: 0.075913321 | W31: 0.076243228 | X31: 0.067110015 | Y31: 0.073742881 | AA31: -0.0017516705 | AB31: 0.021850469 | AC31: -0.010679039 | AD31: 0.014775738 | AE31: 0.0065676743 | AF31: 0.018410387 | AG31: 0.00048798609 | AH31: -0.048021917 | AI31: -0.0018504006 | AJ31: -0.04233804 | AK31: 0.0012842179
A32: =IFERROR(__xludf.DUMMYFUNCTION("""COMPUTED_VALUE"""),45726.66666666667) -> 45726.667 | B32: =IFERROR(__xludf.DUMMYFUNCTION("""COMPUTED_VALUE"""),560.58) -> 560.58 | C32: =IFERROR(__xludf.DUMMYFUNCTION("IFERROR(VLOOKUP($A32, GOOGLEFINANCE(C$1, ""price"", $A$2, TODAY()), 2, FALSE), """")"),104.63) -> 104.63 | D32: =IFERROR(__xludf.DUMMYFUNCTION("IFERROR(VLOOKUP($A32, GOOGLEFINANCE(D$1, ""price"", $A$2, TODAY()), 2, FALSE), """")"),99.17) -> 99.17 | E32: =IFERROR(__xludf.DUMMYFUNCTION("IFERROR(VLOOKUP($A32, GOOGLEFINANCE(E$1, ""price"", $A$2, TODAY()), 2, FALSE), """")"),48.02) -> 48.02 | F32: =IFERROR(__xludf.DUMMYFUNCTION("IFERROR(VLOOKUP($A32, GOOGLEFINANCE(F$1, ""price"", $A$2, TODAY()), 2, FALSE), """")"),97.79) -> 97.79 | G32: =IFERROR(__xludf.DUMMYFUNCTION("IFERROR(VLOOKUP($A32, GOOGLEFINANCE(G$1, ""price"", $A$2, TODAY()), 2, FALSE), """")"),147.67) -> 147.67 | H32: =IFERROR(__xludf.DUMMYFUNCTION("IFERROR(VLOOKUP($A32, GOOGLEFINANCE(H$1, ""price"", $A$2, TODAY()), 2, FALSE), """")"),82.68) -> 82.68 | I32: =IFERROR(__xludf.DUMMYFUNCTION("IFERROR(VLOOKUP($A32, GOOGLEFINANCE(I$1, ""price"", $A$2, TODAY()), 2, FALSE), """")"),132.15) -> 132.15 | J32: =IFERROR(__xludf.DUMMYFUNCTION("IFERROR(VLOOKUP($A32, GOOGLEFINANCE(J$1, ""price"", $A$2, TODAY()), 2, FALSE), """")"),44.04) -> 44.04 | K32: =IFERROR(__xludf.DUMMYFUNCTION("IFERROR(VLOOKUP($A32, GOOGLEFINANCE(K$1, ""price"", $A$2, TODAY()), 2, FALSE), """")"),43.0) -> 43 | L32: =IFERROR(__xludf.DUMMYFUNCTION("IFERROR(VLOOKUP($A32, GOOGLEFINANCE(L$1, ""price"", $A$2, TODAY()), 2, FALSE), """")"),39.07) -> 39.07 | M32: =IFERROR(__xludf.DUMMYFUNCTION("IFERROR(VLOOKUP($A32, GOOGLEFINANCE(M$1, ""price"", $A$2, TODAY()), 2, FALSE), """")"),42.06) -> 42.06 | O32: 0.18664597 | P32: 0.17690606 | Q32: 0.085661279 | R32: 0.17444433 | S32: 0.2634236 | T32: 0.1474901 | U32: 0.23573799 | V32: 0.07856149 | W32: 0.076706269 | X32: 0.069695672 | Y32: 0.075029434 | AA32: -0.017301671 | AB32: 0.018498354 | AC32: -0.010332153 | AD32: 0.017128603 | AE32: 0.017923915 | AF32: 0.036928349 | AG32: 0.0057078273 | AH32: -0.02289147 | AI32: -0.0005982039 | AJ32: -0.0018206927 | AK32: 0.0088417112
A33: =IFERROR(__xludf.DUMMYFUNCTION("""COMPUTED_VALUE"""),45727.66666666667) -> 45727.667 | B33: =IFERROR(__xludf.DUMMYFUNCTION("""COMPUTED_VALUE"""),555.92) -> 555.92 | C33: =IFERROR(__xludf.DUMMYFUNCTION("IFERROR(VLOOKUP($A33, GOOGLEFINANCE(C$1, ""price"", $A$2, TODAY()), 2, FALSE), """")"),104.2) -> 104.2 | D33: =IFERROR(__xludf.DUMMYFUNCTION("IFERROR(VLOOKUP($A33, GOOGLEFINANCE(D$1, ""price"", $A$2, TODAY()), 2, FALSE), """")"),98.2) -> 98.2 | E33: =IFERROR(__xludf.DUMMYFUNCTION("IFERROR(VLOOKUP($A33, GOOGLEFINANCE(E$1, ""price"", $A$2, TODAY()), 2, FALSE), """")"),47.61) -> 47.61 | F33: =IFERROR(__xludf.DUMMYFUNCTION("IFERROR(VLOOKUP($A33, GOOGLEFINANCE(F$1, ""price"", $A$2, TODAY()), 2, FALSE), """")"),96.35) -> 96.35 | G33: =IFERROR(__xludf.DUMMYFUNCTION("IFERROR(VLOOKUP($A33, GOOGLEFINANCE(G$1, ""price"", $A$2, TODAY()), 2, FALSE), """")"),146.06) -> 146.06 | H33: =IFERROR(__xludf.DUMMYFUNCTION("IFERROR(VLOOKUP($A33, GOOGLEFINANCE(H$1, ""price"", $A$2, TODAY()), 2, FALSE), """")"),81.47) -> 81.47 | I33: =IFERROR(__xludf.DUMMYFUNCTION("IFERROR(VLOOKUP($A33, GOOGLEFINANCE(I$1, ""price"", $A$2, TODAY()), 2, FALSE), """")"),130.12) -> 130.12 | J33: =IFERROR(__xludf.DUMMYFUNCTION("IFERROR(VLOOKUP($A33, GOOGLEFINANCE(J$1, ""price"", $A$2, TODAY()), 2, FALSE), """")"),43.69) -> 43.69 | K33: =IFERROR(__xludf.DUMMYFUNCTION("IFERROR(VLOOKUP($A33, GOOGLEFINANCE(K$1, ""price"", $A$2, TODAY()), 2, FALSE), """")"),42.67) -> 42.67 | L33: =IFERROR(__xludf.DUMMYFUNCTION("IFERROR(VLOOKUP($A33, GOOGLEFINANCE(L$1, ""price"", $A$2, TODAY()), 2, FALSE), """")"),38.71) -> 38.71 | M33: =IFERROR(__xludf.DUMMYFUNCTION("IFERROR(VLOOKUP($A33, GOOGLEFINANCE(M$1, ""price"", $A$2, TODAY()), 2, FALSE), """")"),41.62) -> 41.62 | O33: 0.18743704 | P33: 0.17664412 | Q33: 0.085641819 | R33: 0.1733163 | S33: 0.26273565 | T33: 0.14654986 | U33: 0.23406246 | V33: 0.078590445 | W33: 0.076755648 | X33: 0.069632321 | Y33: 0.074866887 | AA33: -0.0087110774 | AB33: 0.024298553 | AC33: -0.020053574 | AD33: 0.013803703 | AE33: 0.0038133464 | AF33: 0.030939239 | AG33: -0.0042939148 | AH33: -0.034578251 | AI33: -0.009170414 | AJ33: -0.006734685 | AK33: 0.0019518398
A34: =IFERROR(__xludf.DUMMYFUNCTION("""COMPUTED_VALUE"""),45728.66666666667) -> 45728.667 | B34: =IFERROR(__xludf.DUMMYFUNCTION("""COMPUTED_VALUE"""),558.87) -> 558.87 | C34: =IFERROR(__xludf.DUMMYFUNCTION("IFERROR(VLOOKUP($A34, GOOGLEFINANCE(C$1, ""price"", $A$2, TODAY()), 2, FALSE), """")"),105.84) -> 105.84 | D34: =IFERROR(__xludf.DUMMYFUNCTION("IFERROR(VLOOKUP($A34, GOOGLEFINANCE(D$1, ""price"", $A$2, TODAY()), 2, FALSE), """")"),98.77) -> 98.77 | E34: =IFERROR(__xludf.DUMMYFUNCTION("IFERROR(VLOOKUP($A34, GOOGLEFINANCE(E$1, ""price"", $A$2, TODAY()), 2, FALSE), """")"),47.68) -> 47.68 | F34: =IFERROR(__xludf.DUMMYFUNCTION("IFERROR(VLOOKUP($A34, GOOGLEFINANCE(F$1, ""price"", $A$2, TODAY()), 2, FALSE), """")"),96.83) -> 96.83 | G34: =IFERROR(__xludf.DUMMYFUNCTION("IFERROR(VLOOKUP($A34, GOOGLEFINANCE(G$1, ""price"", $A$2, TODAY()), 2, FALSE), """")"),144.6) -> 144.6 | H34: =IFERROR(__xludf.DUMMYFUNCTION("IFERROR(VLOOKUP($A34, GOOGLEFINANCE(H$1, ""price"", $A$2, TODAY()), 2, FALSE), """")"),79.7) -> 79.7 | I34: =IFERROR(__xludf.DUMMYFUNCTION("IFERROR(VLOOKUP($A34, GOOGLEFINANCE(I$1, ""price"", $A$2, TODAY()), 2, FALSE), """")"),130.11) -> 130.11 | J34: =IFERROR(__xludf.DUMMYFUNCTION("IFERROR(VLOOKUP($A34, GOOGLEFINANCE(J$1, ""price"", $A$2, TODAY()), 2, FALSE), """")"),43.89) -> 43.89 | K34: =IFERROR(__xludf.DUMMYFUNCTION("IFERROR(VLOOKUP($A34, GOOGLEFINANCE(K$1, ""price"", $A$2, TODAY()), 2, FALSE), """")"),42.47) -> 42.47 | L34: =IFERROR(__xludf.DUMMYFUNCTION("IFERROR(VLOOKUP($A34, GOOGLEFINANCE(L$1, ""price"", $A$2, TODAY()), 2, FALSE), """")"),38.59) -> 38.59 | M34: =IFERROR(__xludf.DUMMYFUNCTION("IFERROR(VLOOKUP($A34, GOOGLEFINANCE(M$1, ""price"", $A$2, TODAY()), 2, FALSE), """")"),41.47) -> 41.47 | O34: 0.18938215 | P34: 0.17673162 | Q34: 0.085315011 | R34: 0.17326033 | S34: 0.25873638 | T34: 0.14260919 | U34: 0.23280906 | V34: 0.078533469 | W34: 0.075992628 | X34: 0.069050047 | Y34: 0.074203303 | AA34: -0.00051836472 | AB34: 0.016426358 | AC34: -0.0239116 | AD34: 0.012479447 | AE34: -0.0012444699 | AF34: 0.014143598 | AG34: -0.011950888 | AH34: -0.040528082 | AI34: -0.011520663 | AJ34: -0.007845113 | AK34: 0.0026904761
A35: =IFERROR(__xludf.DUMMYFUNCTION("""COMPUTED_VALUE"""),45729.66666666667) -> 45729.667 | B35: =IFERROR(__xludf.DUMMYFUNCTION("""COMPUTED_VALUE"""),551.42) -> 551.42 | C35: =IFERROR(__xludf.DUMMYFUNCTION("IFERROR(VLOOKUP($A35, GOOGLEFINANCE(C$1, ""price"", $A$2, TODAY()), 2, FALSE), """")"),103.83) -> 103.83 | D35: =IFERROR(__xludf.DUMMYFUNCTION("IFERROR(VLOOKUP($A35, GOOGLEFINANCE(D$1, ""price"", $A$2, TODAY()), 2, FALSE), """")"),96.3) -> 96.3 | E35: =IFERROR(__xludf.DUMMYFUNCTION("IFERROR(VLOOKUP($A35, GOOGLEFINANCE(E$1, ""price"", $A$2, TODAY()), 2, FALSE), """")"),47.42) -> 47.42 | F35: =IFERROR(__xludf.DUMMYFUNCTION("IFERROR(VLOOKUP($A35, GOOGLEFINANCE(F$1, ""price"", $A$2, TODAY()), 2, FALSE), """")"),94.84) -> 94.84 | G35: =IFERROR(__xludf.DUMMYFUNCTION("IFERROR(VLOOKUP($A35, GOOGLEFINANCE(G$1, ""price"", $A$2, TODAY()), 2, FALSE), """")"),143.83) -> 143.83 | H35: =IFERROR(__xludf.DUMMYFUNCTION("IFERROR(VLOOKUP($A35, GOOGLEFINANCE(H$1, ""price"", $A$2, TODAY()), 2, FALSE), """")"),79.33) -> 79.33 | I35: =IFERROR(__xludf.DUMMYFUNCTION("IFERROR(VLOOKUP($A35, GOOGLEFINANCE(I$1, ""price"", $A$2, TODAY()), 2, FALSE), """")"),128.78) -> 128.78 | J35: =IFERROR(__xludf.DUMMYFUNCTION("IFERROR(VLOOKUP($A35, GOOGLEFINANCE(J$1, ""price"", $A$2, TODAY()), 2, FALSE), """")"),43.59) -> 43.59 | K35: =IFERROR(__xludf.DUMMYFUNCTION("IFERROR(VLOOKUP($A35, GOOGLEFINANCE(K$1, ""price"", $A$2, TODAY()), 2, FALSE), """")"),42.44) -> 42.44 | L35: =IFERROR(__xludf.DUMMYFUNCTION("IFERROR(VLOOKUP($A35, GOOGLEFINANCE(L$1, ""price"", $A$2, TODAY()), 2, FALSE), """")"),38.68) -> 38.68 | M35: =IFERROR(__xludf.DUMMYFUNCTION("IFERROR(VLOOKUP($A35, GOOGLEFINANCE(M$1, ""price"", $A$2, TODAY()), 2, FALSE), """")"),40.66) -> 40.66 | O35: 0.18829567 | P35: 0.17464002 | Q35: 0.085996155 | R35: 0.17199231 | S35: 0.26083566 | T35: 0.14386493 | U35: 0.23354249 | V35: 0.079050452 | W35: 0.076964927 | X35: 0.070146168 | Y35: 0.073736897 | AA35: -0.0019746919 | AB35: 0.0039360078 | AC35: -0.020347182 | AD35: 0.0043363467 | AE35: 0.0033328192 | AF35: 0.025128271 | AG35: -0.0067242566 | AH35: -0.040518569 | AI35: 0.0044518006 | AJ35: 0.00093254062 | AK35: -0.0053082503
A36: =IFERROR(__xludf.DUMMYFUNCTION("""COMPUTED_VALUE"""),45730.66666666667) -> 45730.667 | B36: =IFERROR(__xludf.DUMMYFUNCTION("""COMPUTED_VALUE"""),562.81) -> 562.81 | C36: =IFERROR(__xludf.DUMMYFUNCTION("IFERROR(VLOOKUP($A36, GOOGLEFINANCE(C$1, ""price"", $A$2, TODAY()), 2, FALSE), """")"),106.97) -> 106.97 | D36: =IFERROR(__xludf.DUMMYFUNCTION("IFERROR(VLOOKUP($A36, GOOGLEFINANCE(D$1, ""price"", $A$2, TODAY()), 2, FALSE), """")"),98.35) -> 98.35 | E36: =IFERROR(__xludf.DUMMYFUNCTION("IFERROR(VLOOKUP($A36, GOOGLEFINANCE(E$1, ""price"", $A$2, TODAY()), 2, FALSE), """")"),48.52) -> 48.52 | F36: =IFERROR(__xludf.DUMMYFUNCTION("IFERROR(VLOOKUP($A36, GOOGLEFINANCE(F$1, ""price"", $A$2, TODAY()), 2, FALSE), """")"),96.58) -> 96.58 | G36: =IFERROR(__xludf.DUMMYFUNCTION("IFERROR(VLOOKUP($A36, GOOGLEFINANCE(G$1, ""price"", $A$2, TODAY()), 2, FALSE), """")"),144.93) -> 144.93 | H36: =IFERROR(__xludf.DUMMYFUNCTION("IFERROR(VLOOKUP($A36, GOOGLEFINANCE(H$1, ""price"", $A$2, TODAY()), 2, FALSE), """")"),79.51) -> 79.51 | I36: =IFERROR(__xludf.DUMMYFUNCTION("IFERROR(VLOOKUP($A36, GOOGLEFINANCE(I$1, ""price"", $A$2, TODAY()), 2, FALSE), """")"),131.13) -> 131.13 | J36: =IFERROR(__xludf.DUMMYFUNCTION("IFERROR(VLOOKUP($A36, GOOGLEFINANCE(J$1, ""price"", $A$2, TODAY()), 2, FALSE), """")"),44.88) -> 44.88 | K36: =IFERROR(__xludf.DUMMYFUNCTION("IFERROR(VLOOKUP($A36, GOOGLEFINANCE(K$1, ""price"", $A$2, TODAY()), 2, FALSE), """")"),42.99) -> 42.99 | L36: =IFERROR(__xludf.DUMMYFUNCTION("IFERROR(VLOOKUP($A36, GOOGLEFINANCE(L$1, ""price"", $A$2, TODAY()), 2, FALSE), """")"),39.44) -> 39.44 | M36: =IFERROR(__xludf.DUMMYFUNCTION("IFERROR(VLOOKUP($A36, GOOGLEFINANCE(M$1, ""price"", $A$2, TODAY()), 2, FALSE), """")"),41.45) -> 41.45 | O36: 0.19006414 | P36: 0.17474814 | Q36: 0.086210266 | R36: 0.17160321 | S36: 0.25751142 | T36: 0.14127325 | U36: 0.2329916 | V36: 0.07974272 | W36: 0.07638457 | X36: 0.070076935 | Y36: 0.0736483 | AA36: 0.0019851846 | AB36: -0.0017780277 | AC36: -0.016965912 | AD36: -0.0083936911 | AE36: -0.0093363686 | AF36: 0.0043525741 | AG36: -0.0064075602 | AH36: -0.027814549 | AI36: 0.0041811177 | AJ36: 0.0036056377 | AK36: 0.00063041464
A37: =IFERROR(__xludf.DUMMYFUNCTION("""COMPUTED_VALUE"""),45733.66666666667) -> 45733.667 | B37: =IFERROR(__xludf.DUMMYFUNCTION("""COMPUTED_VALUE"""),567.15) -> 567.15 | C37: =IFERROR(__xludf.DUMMYFUNCTION("IFERROR(VLOOKUP($A37, GOOGLEFINANCE(C$1, ""price"", $A$2, TODAY()), 2, FALSE), """")"),107.72) -> 107.72 | D37: =IFERROR(__xludf.DUMMYFUNCTION("IFERROR(VLOOKUP($A37, GOOGLEFINANCE(D$1, ""price"", $A$2, TODAY()), 2, FALSE), """")"),98.51) -> 98.51 | E37: =IFERROR(__xludf.DUMMYFUNCTION("IFERROR(VLOOKUP($A37, GOOGLEFINANCE(E$1, ""price"", $A$2, TODAY()), 2, FALSE), """")"),49.09) -> 49.09 | F37: =IFERROR(__xludf.DUMMYFUNCTION("IFERROR(VLOOKUP($A37, GOOGLEFINANCE(F$1, ""price"", $A$2, TODAY()), 2, FALSE), """")"),97.27) -> 97.27 | G37: =IFERROR(__xludf.DUMMYFUNCTION("IFERROR(VLOOKUP($A37, GOOGLEFINANCE(G$1, ""price"", $A$2, TODAY()), 2, FALSE), """")"),146.77) -> 146.77 | H37: =IFERROR(__xludf.DUMMYFUNCTION("IFERROR(VLOOKUP($A37, GOOGLEFINANCE(H$1, ""price"", $A$2, TODAY()), 2, FALSE), """")"),80.67) -> 80.67 | I37: =IFERROR(__xludf.DUMMYFUNCTION("IFERROR(VLOOKUP($A37, GOOGLEFINANCE(I$1, ""price"", $A$2, TODAY()), 2, FALSE), """")"),132.94) -> 132.94 | J37: =IFERROR(__xludf.DUMMYFUNCTION("IFERROR(VLOOKUP($A37, GOOGLEFINANCE(J$1, ""price"", $A$2, TODAY()), 2, FALSE), """")"),45.6) -> 45.6 | K37: =IFERROR(__xludf.DUMMYFUNCTION("IFERROR(VLOOKUP($A37, GOOGLEFINANCE(K$1, ""price"", $A$2, TODAY()), 2, FALSE), """")"),43.53) -> 43.53 | L37: =IFERROR(__xludf.DUMMYFUNCTION("IFERROR(VLOOKUP($A37, GOOGLEFINANCE(L$1, ""price"", $A$2, TODAY()), 2, FALSE), """")"),39.6) -> 39.6 | M37: =IFERROR(__xludf.DUMMYFUNCTION("IFERROR(VLOOKUP($A37, GOOGLEFINANCE(M$1, ""price"", $A$2, TODAY()), 2, FALSE), """")"),42.18) -> 42.18 | O37: 0.18993212 | P37: 0.17369303 | Q37: 0.086555585 | R37: 0.17150666 | S37: 0.25878515 | T37: 0.1422375 | U37: 0.23440007 | V37: 0.08040201 | W37: 0.076752182 | X37: 0.069822798 | Y37: 0.074371859 | AA37: 0.0019870389 | AB37: -0.023850292 | AC37: -0.0091758683 | AD37: -0.0023453123 | AE37: 0.0096050365 | AF37: 0.028409394 | AG37: 0.0020432831 | AH37: -0.0058758146 | AI37: 0.018301193 | AJ37: 0.025425224 | AK37: 0.020932496
A38: =IFERROR(__xludf.DUMMYFUNCTION("""COMPUTED_VALUE"""),45734.66666666667) -> 45734.667 | B38: =IFERROR(__xludf.DUMMYFUNCTION("""COMPUTED_VALUE"""),561.02) -> 561.02 | C38: =IFERROR(__xludf.DUMMYFUNCTION("IFERROR(VLOOKUP($A38, GOOGLEFINANCE(C$1, ""price"", $A$2, TODAY()), 2, FALSE), """")"),106.08) -> 106.08 | D38: =IFERROR(__xludf.DUMMYFUNCTION("IFERROR(VLOOKUP($A38, GOOGLEFINANCE(D$1, ""price"", $A$2, TODAY()), 2, FALSE), """")"),96.75) -> 96.75 | E38: =IFERROR(__xludf.DUMMYFUNCTION("IFERROR(VLOOKUP($A38, GOOGLEFINANCE(E$1, ""price"", $A$2, TODAY()), 2, FALSE), """")"),49.03) -> 49.03 | F38: =IFERROR(__xludf.DUMMYFUNCTION("IFERROR(VLOOKUP($A38, GOOGLEFINANCE(F$1, ""price"", $A$2, TODAY()), 2, FALSE), """")"),95.91) -> 95.91 | G38: =IFERROR(__xludf.DUMMYFUNCTION("IFERROR(VLOOKUP($A38, GOOGLEFINANCE(G$1, ""price"", $A$2, TODAY()), 2, FALSE), """")"),146.84) -> 146.84 | H38: =IFERROR(__xludf.DUMMYFUNCTION("IFERROR(VLOOKUP($A38, GOOGLEFINANCE(H$1, ""price"", $A$2, TODAY()), 2, FALSE), """")"),79.75) -> 79.75 | I38: =IFERROR(__xludf.DUMMYFUNCTION("IFERROR(VLOOKUP($A38, GOOGLEFINANCE(I$1, ""price"", $A$2, TODAY()), 2, FALSE), """")"),131.88) -> 131.88 | J38: =IFERROR(__xludf.DUMMYFUNCTION("IFERROR(VLOOKUP($A38, GOOGLEFINANCE(J$1, ""price"", $A$2, TODAY()), 2, FALSE), """")"),45.67) -> 45.67 | K38: =IFERROR(__xludf.DUMMYFUNCTION("IFERROR(VLOOKUP($A38, GOOGLEFINANCE(K$1, ""price"", $A$2, TODAY()), 2, FALSE), """")"),43.46) -> 43.46 | L38: =IFERROR(__xludf.DUMMYFUNCTION("IFERROR(VLOOKUP($A38, GOOGLEFINANCE(L$1, ""price"", $A$2, TODAY()), 2, FALSE), """")"),39.33) -> 39.33 | M38: =IFERROR(__xludf.DUMMYFUNCTION("IFERROR(VLOOKUP($A38, GOOGLEFINANCE(M$1, ""price"", $A$2, TODAY()), 2, FALSE), """")"),41.92) -> 41.92 | O38: 0.18908417 | P38: 0.17245374 | Q38: 0.087394389 | R38: 0.17095647 | S38: 0.26173755 | T38: 0.14215179 | U38: 0.23507183 | V38: 0.081405297 | W38: 0.077466044 | X38: 0.070104453 | Y38: 0.074721044 | AA38: -0.0033854608 | AB38: -0.036128282 | AC38: -0.0027369626 | AD38: -0.015623259 | AE38: 0.036824466 | AF38: 0.039688255 | AG38: 0.0058326811 | AH38: 0.0048368189 | AI38: 0.030481037 | AJ38: 0.048941973 | AK38: 0.040633395
A39: =IFERROR(__xludf.DUMMYFUNCTION("""COMPUTED_VALUE"""),45735.66666666667) -> 45735.667 | B39: =IFERROR(__xludf.DUMMYFUNCTION("""COMPUTED_VALUE"""),567.13) -> 567.13 | C39: =IFERROR(__xludf.DUMMYFUNCTION("IFERROR(VLOOKUP($A39, GOOGLEFINANCE(C$1, ""price"", $A$2, TODAY()), 2, FALSE), """")"),107.46) -> 107.46 | D39: =IFERROR(__xludf.DUMMYFUNCTION("IFERROR(VLOOKUP($A39, GOOGLEFINANCE(D$1, ""price"", $A$2, TODAY()), 2, FALSE), """")"),98.61) -> 98.61 | E39: =IFERROR(__xludf.DUMMYFUNCTION("IFERROR(VLOOKUP($A39, GOOGLEFINANCE(E$1, ""price"", $A$2, TODAY()), 2, FALSE), """")"),49.57) -> 49.57 | F39: =IFERROR(__xludf.DUMMYFUNCTION("IFERROR(VLOOKUP($A39, GOOGLEFINANCE(F$1, ""price"", $A$2, TODAY()), 2, FALSE), """")"),97.05) -> 97.05 | G39: =IFERROR(__xludf.DUMMYFUNCTION("IFERROR(VLOOKUP($A39, GOOGLEFINANCE(G$1, ""price"", $A$2, TODAY()), 2, FALSE), """")"),146.92) -> 146.92 | H39: =IFERROR(__xludf.DUMMYFUNCTION("IFERROR(VLOOKUP($A39, GOOGLEFINANCE(H$1, ""price"", $A$2, TODAY()), 2, FALSE), """")"),79.75) -> 79.75 | I39: =IFERROR(__xludf.DUMMYFUNCTION("IFERROR(VLOOKUP($A39, GOOGLEFINANCE(I$1, ""price"", $A$2, TODAY()), 2, FALSE), """")"),133.63) -> 133.63 | J39: =IFERROR(__xludf.DUMMYFUNCTION("IFERROR(VLOOKUP($A39, GOOGLEFINANCE(J$1, ""price"", $A$2, TODAY()), 2, FALSE), """")"),46.42) -> 46.42 | K39: =IFERROR(__xludf.DUMMYFUNCTION("IFERROR(VLOOKUP($A39, GOOGLEFINANCE(K$1, ""price"", $A$2, TODAY()), 2, FALSE), """")"),43.6) -> 43.6 | L39: =IFERROR(__xludf.DUMMYFUNCTION("IFERROR(VLOOKUP($A39, GOOGLEFINANCE(L$1, ""price"", $A$2, TODAY()), 2, FALSE), """")"),39.47) -> 39.47 | M39: =IFERROR(__xludf.DUMMYFUNCTION("IFERROR(VLOOKUP($A39, GOOGLEFINANCE(M$1, ""price"", $A$2, TODAY()), 2, FALSE), """")"),41.97) -> 41.97 | O39: 0.18948037 | P39: 0.17387548 | Q39: 0.087405004 | R39: 0.17112479 | S39: 0.25905877 | T39: 0.14062032 | U39: 0.23562499 | V39: 0.081850722 | W39: 0.076878317 | X39: 0.069596036 | Y39: 0.074004197 | AA39: 0.0093370933 | AB39: -0.027122041 | AC39: -0.01158291 | AD39: -0.018065979 | AE39: 0.017674629 | AF39: 0.00069218601 | AG39: 0.0027994946 | AH39: -0.0074748975 | AI39: 0.0085888865 | AJ39: 0.021994065 | AK39: 0.013196391
A40: =IFERROR(__xludf.DUMMYFUNCTION("""COMPUTED_VALUE"""),45736.66666666667) -> 45736.667 | B40: =IFERROR(__xludf.DUMMYFUNCTION("""COMPUTED_VALUE"""),565.49) -> 565.49 | C40: =IFERROR(__xludf.DUMMYFUNCTION("IFERROR(VLOOKUP($A40, GOOGLEFINANCE(C$1, ""price"", $A$2, TODAY()), 2, FALSE), """")"),106.69) -> 106.69 | D40: =IFERROR(__xludf.DUMMYFUNCTION("IFERROR(VLOOKUP($A40, GOOGLEFINANCE(D$1, ""price"", $A$2, TODAY()), 2, FALSE), """")"),98.37) -> 98.37 | E40: =IFERROR(__xludf.DUMMYFUNCTION("IFERROR(VLOOKUP($A40, GOOGLEFINANCE(E$1, ""price"", $A$2, TODAY()), 2, FALSE), """")"),49.64) -> 49.64 | F40: =IFERROR(__xludf.DUMMYFUNCTION("IFERROR(VLOOKUP($A40, GOOGLEFINANCE(F$1, ""price"", $A$2, TODAY()), 2, FALSE), """")"),96.84) -> 96.84 | G40: =IFERROR(__xludf.DUMMYFUNCTION("IFERROR(VLOOKUP($A40, GOOGLEFINANCE(G$1, ""price"", $A$2, TODAY()), 2, FALSE), """")"),147.01) -> 147.01 | H40: =IFERROR(__xludf.DUMMYFUNCTION("IFERROR(VLOOKUP($A40, GOOGLEFINANCE(H$1, ""price"", $A$2, TODAY()), 2, FALSE), """")"),79.36) -> 79.36 | I40: =IFERROR(__xludf.DUMMYFUNCTION("IFERROR(VLOOKUP($A40, GOOGLEFINANCE(I$1, ""price"", $A$2, TODAY()), 2, FALSE), """")"),132.96) -> 132.96 | J40: =IFERROR(__xludf.DUMMYFUNCTION("IFERROR(VLOOKUP($A40, GOOGLEFINANCE(J$1, ""price"", $A$2, TODAY()), 2, FALSE), """")"),46.59) -> 46.59 | K40: =IFERROR(__xludf.DUMMYFUNCTION("IFERROR(VLOOKUP($A40, GOOGLEFINANCE(K$1, ""price"", $A$2, TODAY()), 2, FALSE), """")"),43.33) -> 43.33 | L40: =IFERROR(__xludf.DUMMYFUNCTION("IFERROR(VLOOKUP($A40, GOOGLEFINANCE(L$1, ""price"", $A$2, TODAY()), 2, FALSE), """")"),39.63) -> 39.63 | M40: =IFERROR(__xludf.DUMMYFUNCTION("IFERROR(VLOOKUP($A40, GOOGLEFINANCE(M$1, ""price"", $A$2, TODAY()), 2, FALSE), """")"),41.92) -> 41.92 | O40: 0.18866823 | P40: 0.17395533 | Q40: 0.087782277 | R40: 0.17124971 | S40: 0.25996923 | T40: 0.14033847 | U40: 0.23512352 | V40: 0.082388725 | W40: 0.076623813 | X40: 0.070080815 | Y40: 0.0741304 | AA40: 0.01162994 | AB40: -0.029832917 | AC40: -0.0079797963 | AD40: -0.015587562 | AE40: 0.016923164 | AF40: -0.015182055 | AG40: 0.0033399533 | AH40: 0.0060507768 | AI40: 0.0030432101 | AJ40: 0.026645014 | AK40: 0.014672154
A41: =IFERROR(__xludf.DUMMYFUNCTION("""COMPUTED_VALUE"""),45737.66666666667) -> 45737.667 | B41: =IFERROR(__xludf.DUMMYFUNCTION("""COMPUTED_VALUE"""),563.98) -> 563.98 | C41: =IFERROR(__xludf.DUMMYFUNCTION("IFERROR(VLOOKUP($A41, GOOGLEFINANCE(C$1, ""price"", $A$2, TODAY()), 2, FALSE), """")"),106.98) -> 106.98 | D41: =IFERROR(__xludf.DUMMYFUNCTION("IFERROR(VLOOKUP($A41, GOOGLEFINANCE(D$1, ""price"", $A$2, TODAY()), 2, FALSE), """")"),98.73) -> 98.73 | E41: =IFERROR(__xludf.DUMMYFUNCTION("IFERROR(VLOOKUP($A41, GOOGLEFINANCE(E$1, ""price"", $A$2, TODAY()), 2, FALSE), """")"),49.46) -> 49.46 | F41: =IFERROR(__xludf.DUMMYFUNCTION("IFERROR(VLOOKUP($A41, GOOGLEFINANCE(F$1, ""price"", $A$2, TODAY()), 2, FALSE), """")"),97.6) -> 97.6 | G41: =IFERROR(__xludf.DUMMYFUNCTION("IFERROR(VLOOKUP($A41, GOOGLEFINANCE(G$1, ""price"", $A$2, TODAY()), 2, FALSE), """")"),146.6) -> 146.6 | H41: =IFERROR(__xludf.DUMMYFUNCTION("IFERROR(VLOOKUP($A41, GOOGLEFINANCE(H$1, ""price"", $A$2, TODAY()), 2, FALSE), """")"),79.33) -> 79.33 | I41: =IFERROR(__xludf.DUMMYFUNCTION("IFERROR(VLOOKUP($A41, GOOGLEFINANCE(I$1, ""price"", $A$2, TODAY()), 2, FALSE), """")"),132.25) -> 132.25 | J41: =IFERROR(__xludf.DUMMYFUNCTION("IFERROR(VLOOKUP($A41, GOOGLEFINANCE(J$1, ""price"", $A$2, TODAY()), 2, FALSE), """")"),46.26) -> 46.26 | K41: =IFERROR(__xludf.DUMMYFUNCTION("IFERROR(VLOOKUP($A41, GOOGLEFINANCE(K$1, ""price"", $A$2, TODAY()), 2, FALSE), """")"),42.9) -> 42.9 | L41: =IFERROR(__xludf.DUMMYFUNCTION("IFERROR(VLOOKUP($A41, GOOGLEFINANCE(L$1, ""price"", $A$2, TODAY()), 2, FALSE), """")"),39.38) -> 39.38 | M41: =IFERROR(__xludf.DUMMYFUNCTION("IFERROR(VLOOKUP($A41, GOOGLEFINANCE(M$1, ""price"", $A$2, TODAY()), 2, FALSE), """")"),41.51) -> 41.51 | O41: 0.18968758 | P41: 0.1750594 | Q41: 0.087698145 | R41: 0.17305578 | S41: 0.2599383 | T41: 0.14066102 | U41: 0.23449413 | V41: 0.082024185 | W41: 0.076066527 | X41: 0.069825171 | Y41: 0.073601901 | AA41: 0.021434241 | AB41: -0.012652194 | AC41: -0.0097469736 | AD41: 0.0043887183 | AE41: -0.00057214655 | AF41: -0.027985321 | AG41: 0.0011449007 | AH41: -0.013899637 | AI41: -0.006180896 | AJ41: -0.0048972922 | AK41: -0.012373046
A42: =IFERROR(__xludf.DUMMYFUNCTION("""COMPUTED_VALUE"""),45740.66666666667) -> 45740.667 | B42: =IFERROR(__xludf.DUMMYFUNCTION("""COMPUTED_VALUE"""),574.08) -> 574.08 | C42: =IFERROR(__xludf.DUMMYFUNCTION("IFERROR(VLOOKUP($A42, GOOGLEFINANCE(C$1, ""price"", $A$2, TODAY()), 2, FALSE), """")"),108.82) -> 108.82 | D42: =IFERROR(__xludf.DUMMYFUNCTION("IFERROR(VLOOKUP($A42, GOOGLEFINANCE(D$1, ""price"", $A$2, TODAY()), 2, FALSE), """")"),102.15) -> 102.15 | E42: =IFERROR(__xludf.DUMMYFUNCTION("IFERROR(VLOOKUP($A42, GOOGLEFINANCE(E$1, ""price"", $A$2, TODAY()), 2, FALSE), """")"),50.15) -> 50.15 | F42: =IFERROR(__xludf.DUMMYFUNCTION("IFERROR(VLOOKUP($A42, GOOGLEFINANCE(F$1, ""price"", $A$2, TODAY()), 2, FALSE), """")"),98.69) -> 98.69 | G42: =IFERROR(__xludf.DUMMYFUNCTION("IFERROR(VLOOKUP($A42, GOOGLEFINANCE(G$1, ""price"", $A$2, TODAY()), 2, FALSE), """")"),147.15) -> 147.15 | H42: =IFERROR(__xludf.DUMMYFUNCTION("IFERROR(VLOOKUP($A42, GOOGLEFINANCE(H$1, ""price"", $A$2, TODAY()), 2, FALSE), """")"),79.4) -> 79.4 | I42: =IFERROR(__xludf.DUMMYFUNCTION("IFERROR(VLOOKUP($A42, GOOGLEFINANCE(I$1, ""price"", $A$2, TODAY()), 2, FALSE), """")"),134.29) -> 134.29 | J42: =IFERROR(__xludf.DUMMYFUNCTION("IFERROR(VLOOKUP($A42, GOOGLEFINANCE(J$1, ""price"", $A$2, TODAY()), 2, FALSE), """")"),46.43) -> 46.43 | K42: =IFERROR(__xludf.DUMMYFUNCTION("IFERROR(VLOOKUP($A42, GOOGLEFINANCE(K$1, ""price"", $A$2, TODAY()), 2, FALSE), """")"),43.27) -> 43.27 | L42: =IFERROR(__xludf.DUMMYFUNCTION("IFERROR(VLOOKUP($A42, GOOGLEFINANCE(L$1, ""price"", $A$2, TODAY()), 2, FALSE), """")"),39.09) -> 39.09 | M42: =IFERROR(__xludf.DUMMYFUNCTION("IFERROR(VLOOKUP($A42, GOOGLEFINANCE(M$1, ""price"", $A$2, TODAY()), 2, FALSE), """")"),41.82) -> 41.82 | O42: 0.18955546 | P42: 0.17793687 | Q42: 0.087357163 | R42: 0.17190984 | S42: 0.25632316 | T42: 0.13830825 | U42: 0.2339221 | V42: 0.08087723 | W42: 0.07537277 | X42: 0.068091555 | Y42: 0.07284699 | AA42: 0.027077007 | AB42: 0.0081647659 | AC42: -0.018937497 | AD42: -0.002958585 | AE42: -0.017980873 | AF42: -0.052672318 | AG42: -0.0016503828 | AH42: -0.031844351 | AI42: -0.019242289 | AJ42: -0.03374594 | AK42: -0.026287271
A43: =IFERROR(__xludf.DUMMYFUNCTION("""COMPUTED_VALUE"""),45741.66666666667) -> 45741.667 | B43: =IFERROR(__xludf.DUMMYFUNCTION("""COMPUTED_VALUE"""),575.46) -> 575.46 | C43: =IFERROR(__xludf.DUMMYFUNCTION("IFERROR(VLOOKUP($A43, GOOGLEFINANCE(C$1, ""price"", $A$2, TODAY()), 2, FALSE), """")"),109.18) -> 109.18 | D43: =IFERROR(__xludf.DUMMYFUNCTION("IFERROR(VLOOKUP($A43, GOOGLEFINANCE(D$1, ""price"", $A$2, TODAY()), 2, FALSE), """")"),102.96) -> 102.96 | E43: =IFERROR(__xludf.DUMMYFUNCTION("IFERROR(VLOOKUP($A43, GOOGLEFINANCE(E$1, ""price"", $A$2, TODAY()), 2, FALSE), """")"),50.43) -> 50.43 | F43: =IFERROR(__xludf.DUMMYFUNCTION("IFERROR(VLOOKUP($A43, GOOGLEFINANCE(F$1, ""price"", $A$2, TODAY()), 2, FALSE), """")"),99.94) -> 99.94 | G43: =IFERROR(__xludf.DUMMYFUNCTION("IFERROR(VLOOKUP($A43, GOOGLEFINANCE(G$1, ""price"", $A$2, TODAY()), 2, FALSE), """")"),145.27) -> 145.27 | H43: =IFERROR(__xludf.DUMMYFUNCTION("IFERROR(VLOOKUP($A43, GOOGLEFINANCE(H$1, ""price"", $A$2, TODAY()), 2, FALSE), """")"),78.68) -> 78.68 | I43: =IFERROR(__xludf.DUMMYFUNCTION("IFERROR(VLOOKUP($A43, GOOGLEFINANCE(I$1, ""price"", $A$2, TODAY()), 2, FALSE), """")"),134.49) -> 134.49 | J43: =IFERROR(__xludf.DUMMYFUNCTION("IFERROR(VLOOKUP($A43, GOOGLEFINANCE(J$1, ""price"", $A$2, TODAY()), 2, FALSE), """")"),46.62) -> 46.62 | K43: =IFERROR(__xludf.DUMMYFUNCTION("IFERROR(VLOOKUP($A43, GOOGLEFINANCE(K$1, ""price"", $A$2, TODAY()), 2, FALSE), """")"),43.26) -> 43.26 | L43: =IFERROR(__xludf.DUMMYFUNCTION("IFERROR(VLOOKUP($A43, GOOGLEFINANCE(L$1, ""price"", $A$2, TODAY()), 2, FALSE), """")"),38.46) -> 38.46 | M43: =IFERROR(__xludf.DUMMYFUNCTION("IFERROR(VLOOKUP($A43, GOOGLEFINANCE(M$1, ""price"", $A$2, TODAY()), 2, FALSE), """")"),41.32) -> 41.32 | O43: 0.18972648 | P43: 0.17891774 | Q43: 0.08763424 | R43: 0.17366976 | S43: 0.25244153 | T43: 0.1367254 | U43: 0.23370869 | V43: 0.08101345 | W43: 0.075174643 | X43: 0.06683349 | Y43: 0.071803427 | AA43: 0.023373686 | AB43: 0.0060894348 | AC43: -0.011855681 | AD43: 0.0094656013 | AE43: -0.0120544 | AF43: -0.06224662 | AG43: -0.0053595239 | AH43: -0.033061381 | AI43: -0.022694799 | AJ43: -0.051566336 | AK43: -0.0382147
A44: =IFERROR(__xludf.DUMMYFUNCTION("""COMPUTED_VALUE"""),45742.66666666667) -> 45742.667 | B44: =IFERROR(__xludf.DUMMYFUNCTION("""COMPUTED_VALUE"""),568.59) -> 568.59 | C44: =IFERROR(__xludf.DUMMYFUNCTION("IFERROR(VLOOKUP($A44, GOOGLEFINANCE(C$1, ""price"", $A$2, TODAY()), 2, FALSE), """")"),106.74) -> 106.74 | D44: =IFERROR(__xludf.DUMMYFUNCTION("IFERROR(VLOOKUP($A44, GOOGLEFINANCE(D$1, ""price"", $A$2, TODAY()), 2, FALSE), """")"),101.62) -> 101.62 | E44: =IFERROR(__xludf.DUMMYFUNCTION("IFERROR(VLOOKUP($A44, GOOGLEFINANCE(E$1, ""price"", $A$2, TODAY()), 2, FALSE), """")"),50.28) -> 50.28 | F44: =IFERROR(__xludf.DUMMYFUNCTION("IFERROR(VLOOKUP($A44, GOOGLEFINANCE(F$1, ""price"", $A$2, TODAY()), 2, FALSE), """")"),99.09) -> 99.09 | G44: =IFERROR(__xludf.DUMMYFUNCTION("IFERROR(VLOOKUP($A44, GOOGLEFINANCE(G$1, ""price"", $A$2, TODAY()), 2, FALSE), """")"),144.74) -> 144.74 | H44: =IFERROR(__xludf.DUMMYFUNCTION("IFERROR(VLOOKUP($A44, GOOGLEFINANCE(H$1, ""price"", $A$2, TODAY()), 2, FALSE), """")"),79.9) -> 79.9 | I44: =IFERROR(__xludf.DUMMYFUNCTION("IFERROR(VLOOKUP($A44, GOOGLEFINANCE(I$1, ""price"", $A$2, TODAY()), 2, FALSE), """")"),133.6) -> 133.6 | J44: =IFERROR(__xludf.DUMMYFUNCTION("IFERROR(VLOOKUP($A44, GOOGLEFINANCE(J$1, ""price"", $A$2, TODAY()), 2, FALSE), """")"),46.89) -> 46.89 | K44: =IFERROR(__xludf.DUMMYFUNCTION("IFERROR(VLOOKUP($A44, GOOGLEFINANCE(K$1, ""price"", $A$2, TODAY()), 2, FALSE), """")"),43.34) -> 43.34 | L44: =IFERROR(__xludf.DUMMYFUNCTION("IFERROR(VLOOKUP($A44, GOOGLEFINANCE(L$1, ""price"", $A$2, TODAY()), 2, FALSE), """")"),38.72) -> 38.72 | M44: =IFERROR(__xludf.DUMMYFUNCTION("IFERROR(VLOOKUP($A44, GOOGLEFINANCE(M$1, ""price"", $A$2, TODAY()), 2, FALSE), """")"),41.53) -> 41.53 | O44: 0.18772754 | P44: 0.17872281 | Q44: 0.088429272 | R44: 0.1742732 | S44: 0.25455952 | T44: 0.14052305 | U44: 0.2349672 | V44: 0.082467156 | W44: 0.076223641 | X44: 0.068098278 | Y44: 0.073040328 | AA44: 0.011510441 | AB44: -0.0075487096 | AC44: -0.0047828377 | AD44: 0.015804936 | AE44: -0.004130681 | AF44: -0.027246215 | AG44: -0.0030538632 | AH44: -0.010954776 | AI44: -0.011037238 | AJ44: -0.03191035 | AK44: -0.020134842
A45: =IFERROR(__xludf.DUMMYFUNCTION("""COMPUTED_VALUE"""),45743.66666666667) -> 45743.667 | B45: =IFERROR(__xludf.DUMMYFUNCTION("""COMPUTED_VALUE"""),567.08) -> 567.08 | C45: =IFERROR(__xludf.DUMMYFUNCTION("IFERROR(VLOOKUP($A45, GOOGLEFINANCE(C$1, ""price"", $A$2, TODAY()), 2, FALSE), """")"),105.76) -> 105.76 | D45: =IFERROR(__xludf.DUMMYFUNCTION("IFERROR(VLOOKUP($A45, GOOGLEFINANCE(D$1, ""price"", $A$2, TODAY()), 2, FALSE), """")"),101.68) -> 101.68 | E45: =IFERROR(__xludf.DUMMYFUNCTION("IFERROR(VLOOKUP($A45, GOOGLEFINANCE(E$1, ""price"", $A$2, TODAY()), 2, FALSE), """")"),50.18) -> 50.18 | F45: =IFERROR(__xludf.DUMMYFUNCTION("IFERROR(VLOOKUP($A45, GOOGLEFINANCE(F$1, ""price"", $A$2, TODAY()), 2, FALSE), """")"),98.65) -> 98.65 | G45: =IFERROR(__xludf.DUMMYFUNCTION("IFERROR(VLOOKUP($A45, GOOGLEFINANCE(G$1, ""price"", $A$2, TODAY()), 2, FALSE), """")"),144.97) -> 144.97 | H45: =IFERROR(__xludf.DUMMYFUNCTION("IFERROR(VLOOKUP($A45, GOOGLEFINANCE(H$1, ""price"", $A$2, TODAY()), 2, FALSE), """")"),80.81) -> 80.81 | I45: =IFERROR(__xludf.DUMMYFUNCTION("IFERROR(VLOOKUP($A45, GOOGLEFINANCE(I$1, ""price"", $A$2, TODAY()), 2, FALSE), """")"),132.89) -> 132.89 | J45: =IFERROR(__xludf.DUMMYFUNCTION("IFERROR(VLOOKUP($A45, GOOGLEFINANCE(J$1, ""price"", $A$2, TODAY()), 2, FALSE), """")"),46.44) -> 46.44 | K45: =IFERROR(__xludf.DUMMYFUNCTION("IFERROR(VLOOKUP($A45, GOOGLEFINANCE(K$1, ""price"", $A$2, TODAY()), 2, FALSE), """")"),43.32) -> 43.32 | L45: =IFERROR(__xludf.DUMMYFUNCTION("IFERROR(VLOOKUP($A45, GOOGLEFINANCE(L$1, ""price"", $A$2, TODAY()), 2, FALSE), """")"),38.71) -> 38.71 | M45: =IFERROR(__xludf.DUMMYFUNCTION("IFERROR(VLOOKUP($A45, GOOGLEFINANCE(M$1, ""price"", $A$2, TODAY()), 2, FALSE), """")"),41.43) -> 41.43 | O45: 0.18649926 | P45: 0.17930451 | Q45: 0.088488397 | R45: 0.17396135 | S45: 0.25564294 | T45: 0.14250194 | U45: 0.23434083 | V45: 0.081893207 | W45: 0.076391338 | X45: 0.068261974 | Y45: 0.073058475 | AA45: 0.02534473 | AB45: 0.007461569 | AC45: -0.0041576325 | AD45: 0.0090246873 | AE45: -0.041405943 | AF45: -0.067534856 | AG45: -0.00062991283 | AH45: 0.01342136 | AI45: -0.013018027 | AJ45: -0.071561043 | AK45: -0.039429605
A46: =IFERROR(__xludf.DUMMYFUNCTION("""COMPUTED_VALUE"""),45744.66666666667) -> 45744.667 | B46: =IFERROR(__xludf.DUMMYFUNCTION("""COMPUTED_VALUE"""),555.66) -> 555.66 | C46: =IFERROR(__xludf.DUMMYFUNCTION("IFERROR(VLOOKUP($A46, GOOGLEFINANCE(C$1, ""price"", $A$2, TODAY()), 2, FALSE), """")"),103.19) -> 103.19 | D46: =IFERROR(__xludf.DUMMYFUNCTION("IFERROR(VLOOKUP($A46, GOOGLEFINANCE(D$1, ""price"", $A$2, TODAY()), 2, FALSE), """")"),98.52) -> 98.52 | E46: =IFERROR(__xludf.DUMMYFUNCTION("IFERROR(VLOOKUP($A46, GOOGLEFINANCE(E$1, ""price"", $A$2, TODAY()), 2, FALSE), """")"),49.21) -> 49.21 | F46: =IFERROR(__xludf.DUMMYFUNCTION("IFERROR(VLOOKUP($A46, GOOGLEFINANCE(F$1, ""price"", $A$2, TODAY()), 2, FALSE), """")"),95.74) -> 95.74 | G46: =IFERROR(__xludf.DUMMYFUNCTION("IFERROR(VLOOKUP($A46, GOOGLEFINANCE(G$1, ""price"", $A$2, TODAY()), 2, FALSE), """")"),144.52) -> 144.52 | H46: =IFERROR(__xludf.DUMMYFUNCTION("IFERROR(VLOOKUP($A46, GOOGLEFINANCE(H$1, ""price"", $A$2, TODAY()), 2, FALSE), """")"),80.41) -> 80.41 | I46: =IFERROR(__xludf.DUMMYFUNCTION("IFERROR(VLOOKUP($A46, GOOGLEFINANCE(I$1, ""price"", $A$2, TODAY()), 2, FALSE), """")"),130.15) -> 130.15 | J46: =IFERROR(__xludf.DUMMYFUNCTION("IFERROR(VLOOKUP($A46, GOOGLEFINANCE(J$1, ""price"", $A$2, TODAY()), 2, FALSE), """")"),46.22) -> 46.22 | K46: =IFERROR(__xludf.DUMMYFUNCTION("IFERROR(VLOOKUP($A46, GOOGLEFINANCE(K$1, ""price"", $A$2, TODAY()), 2, FALSE), """")"),42.53) -> 42.53 | L46: =IFERROR(__xludf.DUMMYFUNCTION("IFERROR(VLOOKUP($A46, GOOGLEFINANCE(L$1, ""price"", $A$2, TODAY()), 2, FALSE), """")"),38.99) -> 38.99 | M46: =IFERROR(__xludf.DUMMYFUNCTION("IFERROR(VLOOKUP($A46, GOOGLEFINANCE(M$1, ""price"", $A$2, TODAY()), 2, FALSE), """")"),41.41) -> 41.41 | O46: 0.18570709 | P46: 0.17730267 | Q46: 0.08856135 | R46: 0.17229961 | S46: 0.2600871 | T46: 0.14471079 | U46: 0.23422597 | V46: 0.083180362 | W46: 0.076539611 | X46: 0.070168808 | Y46: 0.074523989 | AA46: 0.028995251 | AB46: -0.019830507 | AC46: 0.012404506 | AD46: -0.0019540781 | AE46: -0.02855698 | AF46: -0.068066911 | AG46: 0.0034737651 | AH46: 0.067277129 | AI46: -0.0068327062 | AJ46: -0.048701491 | AK46: -0.033483537
A47: =IFERROR(__xludf.DUMMYFUNCTION("""COMPUTED_VALUE"""),45747.66666666667) -> 45747.667 | B47: =IFERROR(__xludf.DUMMYFUNCTION("""COMPUTED_VALUE"""),559.39) -> 559.39 | C47: =IFERROR(__xludf.DUMMYFUNCTION("IFERROR(VLOOKUP($A47, GOOGLEFINANCE(C$1, ""price"", $A$2, TODAY()), 2, FALSE), """")"),103.24) -> 103.24 | D47: =IFERROR(__xludf.DUMMYFUNCTION("IFERROR(VLOOKUP($A47, GOOGLEFINANCE(D$1, ""price"", $A$2, TODAY()), 2, FALSE), """")"),98.73) -> 98.73 | E47: =IFERROR(__xludf.DUMMYFUNCTION("IFERROR(VLOOKUP($A47, GOOGLEFINANCE(E$1, ""price"", $A$2, TODAY()), 2, FALSE), """")"),49.81) -> 49.81 | F47: =IFERROR(__xludf.DUMMYFUNCTION("IFERROR(VLOOKUP($A47, GOOGLEFINANCE(F$1, ""price"", $A$2, TODAY()), 2, FALSE), """")"),96.45) -> 96.45 | G47: =IFERROR(__xludf.DUMMYFUNCTION("IFERROR(VLOOKUP($A47, GOOGLEFINANCE(G$1, ""price"", $A$2, TODAY()), 2, FALSE), """")"),146.01) -> 146.01 | H47: =IFERROR(__xludf.DUMMYFUNCTION("IFERROR(VLOOKUP($A47, GOOGLEFINANCE(H$1, ""price"", $A$2, TODAY()), 2, FALSE), """")"),81.67) -> 81.67 | I47: =IFERROR(__xludf.DUMMYFUNCTION("IFERROR(VLOOKUP($A47, GOOGLEFINANCE(I$1, ""price"", $A$2, TODAY()), 2, FALSE), """")"),131.07) -> 131.07 | J47: =IFERROR(__xludf.DUMMYFUNCTION("IFERROR(VLOOKUP($A47, GOOGLEFINANCE(J$1, ""price"", $A$2, TODAY()), 2, FALSE), """")"),46.73) -> 46.73 | K47: =IFERROR(__xludf.DUMMYFUNCTION("IFERROR(VLOOKUP($A47, GOOGLEFINANCE(K$1, ""price"", $A$2, TODAY()), 2, FALSE), """")"),42.99) -> 42.99 | L47: =IFERROR(__xludf.DUMMYFUNCTION("IFERROR(VLOOKUP($A47, GOOGLEFINANCE(L$1, ""price"", $A$2, TODAY()), 2, FALSE), """")"),39.42) -> 39.42 | M47: =IFERROR(__xludf.DUMMYFUNCTION("IFERROR(VLOOKUP($A47, GOOGLEFINANCE(M$1, ""price"", $A$2, TODAY()), 2, FALSE), """")"),41.85) -> 41.85 | O47: 0.18455818 | P47: 0.17649583 | Q47: 0.089043422 | R47: 0.17241996 | S47: 0.26101646 | T47: 0.14599832 | U47: 0.2343088 | V47: 0.083537425 | W47: 0.07685157 | X47: 0.070469619 | Y47: 0.074813636 | AA47: 0.014798371 | AB47: -0.014382588 | AC47: 0.018637363 | AD47: -0.0044055164 | AE47: -0.020960182 | AF47: -0.050436719 | AG47: 0.0067354364 | AH47: 0.076785236 | AI47: 0.011544758 | AJ47: -0.03151318 | AK47: -0.0075091565
A48: =IFERROR(__xludf.DUMMYFUNCTION("""COMPUTED_VALUE"""),45748.66666666667) -> 45748.667 | B48: =IFERROR(__xludf.DUMMYFUNCTION("""COMPUTED_VALUE"""),560.97) -> 560.97 | C48: =IFERROR(__xludf.DUMMYFUNCTION("IFERROR(VLOOKUP($A48, GOOGLEFINANCE(C$1, ""price"", $A$2, TODAY()), 2, FALSE), """")"),104.0) -> 104 | D48: =IFERROR(__xludf.DUMMYFUNCTION("IFERROR(VLOOKUP($A48, GOOGLEFINANCE(D$1, ""price"", $A$2, TODAY()), 2, FALSE), """")"),99.76) -> 99.76 | E48: =IFERROR(__xludf.DUMMYFUNCTION("IFERROR(VLOOKUP($A48, GOOGLEFINANCE(E$1, ""price"", $A$2, TODAY()), 2, FALSE), """")"),49.75) -> 49.75 | F48: =IFERROR(__xludf.DUMMYFUNCTION("IFERROR(VLOOKUP($A48, GOOGLEFINANCE(F$1, ""price"", $A$2, TODAY()), 2, FALSE), """")"),96.51) -> 96.51 | G48: =IFERROR(__xludf.DUMMYFUNCTION("IFERROR(VLOOKUP($A48, GOOGLEFINANCE(G$1, ""price"", $A$2, TODAY()), 2, FALSE), """")"),143.34) -> 143.34 | H48: =IFERROR(__xludf.DUMMYFUNCTION("IFERROR(VLOOKUP($A48, GOOGLEFINANCE(H$1, ""price"", $A$2, TODAY()), 2, FALSE), """")"),81.79) -> 81.79 | I48: =IFERROR(__xludf.DUMMYFUNCTION("IFERROR(VLOOKUP($A48, GOOGLEFINANCE(I$1, ""price"", $A$2, TODAY()), 2, FALSE), """")"),131.81) -> 131.81 | J48: =IFERROR(__xludf.DUMMYFUNCTION("IFERROR(VLOOKUP($A48, GOOGLEFINANCE(J$1, ""price"", $A$2, TODAY()), 2, FALSE), """")"),47.0) -> 47 | K48: =IFERROR(__xludf.DUMMYFUNCTION("IFERROR(VLOOKUP($A48, GOOGLEFINANCE(K$1, ""price"", $A$2, TODAY()), 2, FALSE), """")"),43.15) -> 43.15 | L48: =IFERROR(__xludf.DUMMYFUNCTION("IFERROR(VLOOKUP($A48, GOOGLEFINANCE(L$1, ""price"", $A$2, TODAY()), 2, FALSE), """")"),39.53) -> 39.53 | M48: =IFERROR(__xludf.DUMMYFUNCTION("IFERROR(VLOOKUP($A48, GOOGLEFINANCE(M$1, ""price"", $A$2, TODAY()), 2, FALSE), """")"),41.88) -> 41.88 | O48: 0.18539316 | P48: 0.17783482 | Q48: 0.088685669 | R48: 0.17204129 | S48: 0.25552169 | T48: 0.14580102 | U48: 0.234968 | V48: 0.083783447 | W48: 0.076920334 | X48: 0.070467226 | Y48: 0.074656399 | AA48: 0.024190444 | AB48: 0.0013772524 | AC48: 0.0025196078 | AD48: -0.0083007374 | AE48: -0.046011381 | AF48: -0.051901873 | AG48: 0.0020349902 | AH48: 0.088351793 | AI48: 0.028255456 | AJ48: -0.042802502 | AK48: -0.00039350471
A49: =IFERROR(__xludf.DUMMYFUNCTION("""COMPUTED_VALUE"""),45749.66666666667) -> 45749.667 | B49: =IFERROR(__xludf.DUMMYFUNCTION("""COMPUTED_VALUE"""),564.52) -> 564.52 | C49: =IFERROR(__xludf.DUMMYFUNCTION("IFERROR(VLOOKUP($A49, GOOGLEFINANCE(C$1, ""price"", $A$2, TODAY()), 2, FALSE), """")"),104.77) -> 104.77 | D49: =IFERROR(__xludf.DUMMYFUNCTION("IFERROR(VLOOKUP($A49, GOOGLEFINANCE(D$1, ""price"", $A$2, TODAY()), 2, FALSE), """")"),101.66) -> 101.66 | E49: =IFERROR(__xludf.DUMMYFUNCTION("IFERROR(VLOOKUP($A49, GOOGLEFINANCE(E$1, ""price"", $A$2, TODAY()), 2, FALSE), """")"),50.16) -> 50.16 | F49: =IFERROR(__xludf.DUMMYFUNCTION("IFERROR(VLOOKUP($A49, GOOGLEFINANCE(F$1, ""price"", $A$2, TODAY()), 2, FALSE), """")"),96.85) -> 96.85 | G49: =IFERROR(__xludf.DUMMYFUNCTION("IFERROR(VLOOKUP($A49, GOOGLEFINANCE(G$1, ""price"", $A$2, TODAY()), 2, FALSE), """")"),144.3) -> 144.3 | H49: =IFERROR(__xludf.DUMMYFUNCTION("IFERROR(VLOOKUP($A49, GOOGLEFINANCE(H$1, ""price"", $A$2, TODAY()), 2, FALSE), """")"),81.55) -> 81.55 | I49: =IFERROR(__xludf.DUMMYFUNCTION("IFERROR(VLOOKUP($A49, GOOGLEFINANCE(I$1, ""price"", $A$2, TODAY()), 2, FALSE), """")"),133.05) -> 133.05 | J49: =IFERROR(__xludf.DUMMYFUNCTION("IFERROR(VLOOKUP($A49, GOOGLEFINANCE(J$1, ""price"", $A$2, TODAY()), 2, FALSE), """")"),47.07) -> 47.07 | K49: =IFERROR(__xludf.DUMMYFUNCTION("IFERROR(VLOOKUP($A49, GOOGLEFINANCE(K$1, ""price"", $A$2, TODAY()), 2, FALSE), """")"),43.51) -> 43.51 | L49: =IFERROR(__xludf.DUMMYFUNCTION("IFERROR(VLOOKUP($A49, GOOGLEFINANCE(L$1, ""price"", $A$2, TODAY()), 2, FALSE), """")"),39.71) -> 39.71 | M49: =IFERROR(__xludf.DUMMYFUNCTION("IFERROR(VLOOKUP($A49, GOOGLEFINANCE(M$1, ""price"", $A$2, TODAY()), 2, FALSE), """")"),42.08) -> 42.08 | O49: 0.1855913 | P49: 0.18008219 | Q49: 0.088854248 | R49: 0.17156168 | S49: 0.25561539 | T49: 0.14445901 | U49: 0.23568696 | V49: 0.083380571 | W49: 0.077074329 | X49: 0.070342946 | Y49: 0.074541203 | AA49: -0.0010880178 | AB49: 0.010501106 | AC49: 0.03212402 | AD49: 0.0040769072 | AE49: 0.010635019 | AF49: -0.00071741583 | AG49: 0.0200582 | AH49: 0.11083654 | AI49: 0.047164888 | AJ49: 0.015834355 | AK49: 0.0429685
A50: =IFERROR(__xludf.DUMMYFUNCTION("""COMPUTED_VALUE"""),45750.66666666667) -> 45750.667 | B50: =IFERROR(__xludf.DUMMYFUNCTION("""COMPUTED_VALUE"""),536.7) -> 536.7 | C50: =IFERROR(__xludf.DUMMYFUNCTION("IFERROR(VLOOKUP($A50, GOOGLEFINANCE(C$1, ""price"", $A$2, TODAY()), 2, FALSE), """")"),97.62) -> 97.62 | D50: =IFERROR(__xludf.DUMMYFUNCTION("IFERROR(VLOOKUP($A50, GOOGLEFINANCE(D$1, ""price"", $A$2, TODAY()), 2, FALSE), """")"),95.52) -> 95.52 | E50: =IFERROR(__xludf.DUMMYFUNCTION("IFERROR(VLOOKUP($A50, GOOGLEFINANCE(E$1, ""price"", $A$2, TODAY()), 2, FALSE), """")"),47.69) -> 47.69 | F50: =IFERROR(__xludf.DUMMYFUNCTION("IFERROR(VLOOKUP($A50, GOOGLEFINANCE(F$1, ""price"", $A$2, TODAY()), 2, FALSE), """")"),92.53) -> 92.53 | G50: =IFERROR(__xludf.DUMMYFUNCTION("IFERROR(VLOOKUP($A50, GOOGLEFINANCE(G$1, ""price"", $A$2, TODAY()), 2, FALSE), """")"),143.13) -> 143.13 | H50: =IFERROR(__xludf.DUMMYFUNCTION("IFERROR(VLOOKUP($A50, GOOGLEFINANCE(H$1, ""price"", $A$2, TODAY()), 2, FALSE), """")"),82.02) -> 82.02 | I50: =IFERROR(__xludf.DUMMYFUNCTION("IFERROR(VLOOKUP($A50, GOOGLEFINANCE(I$1, ""price"", $A$2, TODAY()), 2, FALSE), """")"),125.85) -> 125.85 | J50: =IFERROR(__xludf.DUMMYFUNCTION("IFERROR(VLOOKUP($A50, GOOGLEFINANCE(J$1, ""price"", $A$2, TODAY()), 2, FALSE), """")"),43.37) -> 43.37 | K50: =IFERROR(__xludf.DUMMYFUNCTION("IFERROR(VLOOKUP($A50, GOOGLEFINANCE(K$1, ""price"", $A$2, TODAY()), 2, FALSE), """")"),41.54) -> 41.54 | L50: =IFERROR(__xludf.DUMMYFUNCTION("IFERROR(VLOOKUP($A50, GOOGLEFINANCE(L$1, ""price"", $A$2, TODAY()), 2, FALSE), """")"),39.46) -> 39.46 | M50: =IFERROR(__xludf.DUMMYFUNCTION("IFERROR(VLOOKUP($A50, GOOGLEFINANCE(M$1, ""price"", $A$2, TODAY()), 2, FALSE), """")"),40.82) -> 40.82 | O50: 0.18188932 | P50: 0.17797652 | Q50: 0.088857835 | R50: 0.17240544 | S50: 0.2666853 | T50: 0.15282281 | U50: 0.23448854 | V50: 0.080808645 | W50: 0.077398919 | X50: 0.073523384 | Y50: 0.076057388 | AA50: -0.018258037 | AB50: -0.0062488075 | AC50: 0.015313506 | AD50: -0.00065805459 | AE50: 0.037124873 | AF50: 0.010306082 | AG50: -0.0039031591 | AH50: 0.10134059 | AI50: 0.038678053 | AJ50: 0.023047655 | AK50: 0.039556656
A51: =IFERROR(__xludf.DUMMYFUNCTION("""COMPUTED_VALUE"""),45751.66666666667) -> 45751.667 | B51: =IFERROR(__xludf.DUMMYFUNCTION("""COMPUTED_VALUE"""),505.28) -> 505.28 | C51: =IFERROR(__xludf.DUMMYFUNCTION("IFERROR(VLOOKUP($A51, GOOGLEFINANCE(C$1, ""price"", $A$2, TODAY()), 2, FALSE), """")"),91.19) -> 91.19 | D51: =IFERROR(__xludf.DUMMYFUNCTION("IFERROR(VLOOKUP($A51, GOOGLEFINANCE(D$1, ""price"", $A$2, TODAY()), 2, FALSE), """")"),91.4) -> 91.4 | E51: =IFERROR(__xludf.DUMMYFUNCTION("IFERROR(VLOOKUP($A51, GOOGLEFINANCE(E$1, ""price"", $A$2, TODAY()), 2, FALSE), """")"),44.2) -> 44.2 | F51: =IFERROR(__xludf.DUMMYFUNCTION("IFERROR(VLOOKUP($A51, GOOGLEFINANCE(F$1, ""price"", $A$2, TODAY()), 2, FALSE), """")"),87.23) -> 87.23 | G51: =IFERROR(__xludf.DUMMYFUNCTION("IFERROR(VLOOKUP($A51, GOOGLEFINANCE(G$1, ""price"", $A$2, TODAY()), 2, FALSE), """")"),135.28) -> 135.28 | H51: =IFERROR(__xludf.DUMMYFUNCTION("IFERROR(VLOOKUP($A51, GOOGLEFINANCE(H$1, ""price"", $A$2, TODAY()), 2, FALSE), """")"),78.46) -> 78.46 | I51: =IFERROR(__xludf.DUMMYFUNCTION("IFERROR(VLOOKUP($A51, GOOGLEFINANCE(I$1, ""price"", $A$2, TODAY()), 2, FALSE), """")"),117.94) -> 117.94 | J51: =IFERROR(__xludf.DUMMYFUNCTION("IFERROR(VLOOKUP($A51, GOOGLEFINANCE(J$1, ""price"", $A$2, TODAY()), 2, FALSE), """")"),39.38) -> 39.38 | K51: =IFERROR(__xludf.DUMMYFUNCTION("IFERROR(VLOOKUP($A51, GOOGLEFINANCE(K$1, ""price"", $A$2, TODAY()), 2, FALSE), """")"),38.94) -> 38.94 | L51: =IFERROR(__xludf.DUMMYFUNCTION("IFERROR(VLOOKUP($A51, GOOGLEFINANCE(L$1, ""price"", $A$2, TODAY()), 2, FALSE), """")"),37.27) -> 37.27 | M51: =IFERROR(__xludf.DUMMYFUNCTION("IFERROR(VLOOKUP($A51, GOOGLEFINANCE(M$1, ""price"", $A$2, TODAY()), 2, FALSE), """")"),38.96) -> 38.96 | O51: 0.18047419 | P51: 0.1808898 | Q51: 0.087476251 | R51: 0.17263695 | S51: 0.26773274 | T51: 0.15528024 | U51: 0.23341514 | V51: 0.077936985 | W51: 0.077066181 | X51: 0.073761083 | Y51: 0.077105763 | AA51: -0.028409051 | AB51: 0.018177333 | AC51: 0.00079428643 | AD51: 0.0099460403 | AE51: 0.044445243 | AF51: 0.031864738 | AG51: -0.0082782064 | AH51: 0.054845982 | AI51: 0.022328366 | AJ51: 0.032075279 | AK51: 0.05780707
A52: =IFERROR(__xludf.DUMMYFUNCTION("""COMPUTED_VALUE"""),45754.66666666667) -> 45754.667 | B52: =IFERROR(__xludf.DUMMYFUNCTION("""COMPUTED_VALUE"""),504.38) -> 504.38 | C52: =IFERROR(__xludf.DUMMYFUNCTION("IFERROR(VLOOKUP($A52, GOOGLEFINANCE(C$1, ""price"", $A$2, TODAY()), 2, FALSE), """")"),91.73) -> 91.73 | D52: =IFERROR(__xludf.DUMMYFUNCTION("IFERROR(VLOOKUP($A52, GOOGLEFINANCE(D$1, ""price"", $A$2, TODAY()), 2, FALSE), """")"),90.32) -> 90.32 | E52: =IFERROR(__xludf.DUMMYFUNCTION("IFERROR(VLOOKUP($A52, GOOGLEFINANCE(E$1, ""price"", $A$2, TODAY()), 2, FALSE), """")"),44.09) -> 44.09 | F52: =IFERROR(__xludf.DUMMYFUNCTION("IFERROR(VLOOKUP($A52, GOOGLEFINANCE(F$1, ""price"", $A$2, TODAY()), 2, FALSE), """")"),87.35) -> 87.35 | G52: =IFERROR(__xludf.DUMMYFUNCTION("IFERROR(VLOOKUP($A52, GOOGLEFINANCE(G$1, ""price"", $A$2, TODAY()), 2, FALSE), """")"),134.47) -> 134.47 | H52: =IFERROR(__xludf.DUMMYFUNCTION("IFERROR(VLOOKUP($A52, GOOGLEFINANCE(H$1, ""price"", $A$2, TODAY()), 2, FALSE), """")"),77.55) -> 77.55 | I52: =IFERROR(__xludf.DUMMYFUNCTION("IFERROR(VLOOKUP($A52, GOOGLEFINANCE(I$1, ""price"", $A$2, TODAY()), 2, FALSE), """")"),117.39) -> 117.39 | J52: =IFERROR(__xludf.DUMMYFUNCTION("IFERROR(VLOOKUP($A52, GOOGLEFINANCE(J$1, ""price"", $A$2, TODAY()), 2, FALSE), """")"),39.13) -> 39.13 | K52: =IFERROR(__xludf.DUMMYFUNCTION("IFERROR(VLOOKUP($A52, GOOGLEFINANCE(K$1, ""price"", $A$2, TODAY()), 2, FALSE), """")"),38.32) -> 38.32 | L52: =IFERROR(__xludf.DUMMYFUNCTION("IFERROR(VLOOKUP($A52, GOOGLEFINANCE(L$1, ""price"", $A$2, TODAY()), 2, FALSE), """")"),36.7) -> 36.7 | M52: =IFERROR(__xludf.DUMMYFUNCTION("IFERROR(VLOOKUP($A52, GOOGLEFINANCE(M$1, ""price"", $A$2, TODAY()), 2, FALSE), """")"),38.02) -> 38.02 | O52: 0.18186685 | P52: 0.17907134 | Q52: 0.087414251 | R52: 0.17318292 | S52: 0.26660454 | T52: 0.15375312 | U52: 0.23274119 | V52: 0.077580396 | W52: 0.075974464 | X52: 0.0727626 | Y52: 0.075379674 | AA52: -0.020303215 | AB52: 0.014725018 | AC52: -0.00049265991 | AD52: 0.016177346 | AE52: 0.0374754 | AF52: 0.01433411 | AG52: -0.011848883 | AH52: 0.056457261 | AI52: 0.0053842138 | AJ52: 0.0097238793 | AK52: 0.02158597
A53: =IFERROR(__xludf.DUMMYFUNCTION("""COMPUTED_VALUE"""),45755.66666666667) -> 45755.667 | B53: =IFERROR(__xludf.DUMMYFUNCTION("""COMPUTED_VALUE"""),496.48) -> 496.48 | C53: =IFERROR(__xludf.DUMMYFUNCTION("IFERROR(VLOOKUP($A53, GOOGLEFINANCE(C$1, ""price"", $A$2, TODAY()), 2, FALSE), """")"),89.87) -> 89.87 | D53: =IFERROR(__xludf.DUMMYFUNCTION("IFERROR(VLOOKUP($A53, GOOGLEFINANCE(D$1, ""price"", $A$2, TODAY()), 2, FALSE), """")"),88.17) -> 88.17 | E53: =IFERROR(__xludf.DUMMYFUNCTION("IFERROR(VLOOKUP($A53, GOOGLEFINANCE(E$1, ""price"", $A$2, TODAY()), 2, FALSE), """")"),43.92) -> 43.92 | F53: =IFERROR(__xludf.DUMMYFUNCTION("IFERROR(VLOOKUP($A53, GOOGLEFINANCE(F$1, ""price"", $A$2, TODAY()), 2, FALSE), """")"),86.13) -> 86.13 | G53: =IFERROR(__xludf.DUMMYFUNCTION("IFERROR(VLOOKUP($A53, GOOGLEFINANCE(G$1, ""price"", $A$2, TODAY()), 2, FALSE), """")"),132.98) -> 132.98 | H53: =IFERROR(__xludf.DUMMYFUNCTION("IFERROR(VLOOKUP($A53, GOOGLEFINANCE(H$1, ""price"", $A$2, TODAY()), 2, FALSE), """")"),76.35) -> 76.35 | I53: =IFERROR(__xludf.DUMMYFUNCTION("IFERROR(VLOOKUP($A53, GOOGLEFINANCE(I$1, ""price"", $A$2, TODAY()), 2, FALSE), """")"),116.42) -> 116.42 | J53: =IFERROR(__xludf.DUMMYFUNCTION("IFERROR(VLOOKUP($A53, GOOGLEFINANCE(J$1, ""price"", $A$2, TODAY()), 2, FALSE), """")"),38.22) -> 38.22 | K53: =IFERROR(__xludf.DUMMYFUNCTION("IFERROR(VLOOKUP($A53, GOOGLEFINANCE(K$1, ""price"", $A$2, TODAY()), 2, FALSE), """")"),37.14) -> 37.14 | L53: =IFERROR(__xludf.DUMMYFUNCTION("IFERROR(VLOOKUP($A53, GOOGLEFINANCE(L$1, ""price"", $A$2, TODAY()), 2, FALSE), """")"),36.55) -> 36.55 | M53: =IFERROR(__xludf.DUMMYFUNCTION("IFERROR(VLOOKUP($A53, GOOGLEFINANCE(M$1, ""price"", $A$2, TODAY()), 2, FALSE), """")"),37.08) -> 37.08 | O53: 0.18101434 | P53: 0.17759024 | Q53: 0.088462778 | R53: 0.17348131 | S53: 0.26784563 | T53: 0.15378263 | U53: 0.23449082 | V53: 0.076981953 | W53: 0.074806639 | X53: 0.073618273 | Y53: 0.074685788 | AA53: -0.031208364 | AB53: 0.010844747 | AC53: 0.0061026879 | AD53: 0.012542462 | AE53: 0.045802098 | AF53: 0.020302105 | AG53: -0.0022587476 | AH53: 0.046958455 | AI53: -0.0050272872 | AJ53: 0.018998959 | AK53: 0.0078269693
A54: =IFERROR(__xludf.DUMMYFUNCTION("""COMPUTED_VALUE"""),45756.66666666667) -> 45756.667 | B54: =IFERROR(__xludf.DUMMYFUNCTION("""COMPUTED_VALUE"""),548.62) -> 548.62 | C54: =IFERROR(__xludf.DUMMYFUNCTION("IFERROR(VLOOKUP($A54, GOOGLEFINANCE(C$1, ""price"", $A$2, TODAY()), 2, FALSE), """")"),101.93) -> 101.93 | D54: =IFERROR(__xludf.DUMMYFUNCTION("IFERROR(VLOOKUP($A54, GOOGLEFINANCE(D$1, ""price"", $A$2, TODAY()), 2, FALSE), """")"),97.77) -> 97.77 | E54: =IFERROR(__xludf.DUMMYFUNCTION("IFERROR(VLOOKUP($A54, GOOGLEFINANCE(E$1, ""price"", $A$2, TODAY()), 2, FALSE), """")"),47.23) -> 47.23 | F54: =IFERROR(__xludf.DUMMYFUNCTION("IFERROR(VLOOKUP($A54, GOOGLEFINANCE(F$1, ""price"", $A$2, TODAY()), 2, FALSE), """")"),93.74) -> 93.74 | G54: =IFERROR(__xludf.DUMMYFUNCTION("IFERROR(VLOOKUP($A54, GOOGLEFINANCE(G$1, ""price"", $A$2, TODAY()), 2, FALSE), """")"),138.76) -> 138.76 | H54: =IFERROR(__xludf.DUMMYFUNCTION("IFERROR(VLOOKUP($A54, GOOGLEFINANCE(H$1, ""price"", $A$2, TODAY()), 2, FALSE), """")"),79.31) -> 79.31 | I54: =IFERROR(__xludf.DUMMYFUNCTION("IFERROR(VLOOKUP($A54, GOOGLEFINANCE(I$1, ""price"", $A$2, TODAY()), 2, FALSE), """")"),126.76) -> 126.76 | J54: =IFERROR(__xludf.DUMMYFUNCTION("IFERROR(VLOOKUP($A54, GOOGLEFINANCE(J$1, ""price"", $A$2, TODAY()), 2, FALSE), """")"),41.18) -> 41.18 | K54: =IFERROR(__xludf.DUMMYFUNCTION("IFERROR(VLOOKUP($A54, GOOGLEFINANCE(K$1, ""price"", $A$2, TODAY()), 2, FALSE), """")"),40.38) -> 40.38 | L54: =IFERROR(__xludf.DUMMYFUNCTION("IFERROR(VLOOKUP($A54, GOOGLEFINANCE(L$1, ""price"", $A$2, TODAY()), 2, FALSE), """")"),37.99) -> 37.99 | M54: =IFERROR(__xludf.DUMMYFUNCTION("IFERROR(VLOOKUP($A54, GOOGLEFINANCE(M$1, ""price"", $A$2, TODAY()), 2, FALSE), """")"),39.21) -> 39.21 | O54: 0.18579345 | P54: 0.17821078 | Q54: 0.086088732 | R54: 0.17086508 | S54: 0.25292552 | T54: 0.14456272 | U54: 0.23105246 | V54: 0.075061062 | W54: 0.073602858 | X54: 0.069246473 | Y54: 0.071470234 | AA54: 0.0072626082 | AB54: 0.016915767 | AC54: -0.027436004 | AD54: 0.0020856607 | AE54: -0.024485802 | AF54: -0.05201048 | AG54: -0.025396922 | AH54: -0.00987207 | AI54: -0.03516014 | AJ54: -0.054297195 | AK54: -0.056528292
A55: =IFERROR(__xludf.DUMMYFUNCTION("""COMPUTED_VALUE"""),45757.66666666667) -> 45757.667 | B55: =IFERROR(__xludf.DUMMYFUNCTION("""COMPUTED_VALUE"""),524.58) -> 524.58 | C55: =IFERROR(__xludf.DUMMYFUNCTION("IFERROR(VLOOKUP($A55, GOOGLEFINANCE(C$1, ""price"", $A$2, TODAY()), 2, FALSE), """")"),97.19) -> 97.19 | D55: =IFERROR(__xludf.DUMMYFUNCTION("IFERROR(VLOOKUP($A55, GOOGLEFINANCE(D$1, ""price"", $A$2, TODAY()), 2, FALSE), """")"),93.95) -> 93.95 | E55: =IFERROR(__xludf.DUMMYFUNCTION("IFERROR(VLOOKUP($A55, GOOGLEFINANCE(E$1, ""price"", $A$2, TODAY()), 2, FALSE), """")"),45.91) -> 45.91 | F55: =IFERROR(__xludf.DUMMYFUNCTION("IFERROR(VLOOKUP($A55, GOOGLEFINANCE(F$1, ""price"", $A$2, TODAY()), 2, FALSE), """")"),90.5) -> 90.5 | G55: =IFERROR(__xludf.DUMMYFUNCTION("IFERROR(VLOOKUP($A55, GOOGLEFINANCE(G$1, ""price"", $A$2, TODAY()), 2, FALSE), """")"),134.89) -> 134.89 | H55: =IFERROR(__xludf.DUMMYFUNCTION("IFERROR(VLOOKUP($A55, GOOGLEFINANCE(H$1, ""price"", $A$2, TODAY()), 2, FALSE), """")"),79.35) -> 79.35 | I55: =IFERROR(__xludf.DUMMYFUNCTION("IFERROR(VLOOKUP($A55, GOOGLEFINANCE(I$1, ""price"", $A$2, TODAY()), 2, FALSE), """")"),123.49) -> 123.49 | J55: =IFERROR(__xludf.DUMMYFUNCTION("IFERROR(VLOOKUP($A55, GOOGLEFINANCE(J$1, ""price"", $A$2, TODAY()), 2, FALSE), """")"),38.49) -> 38.49 | K55: =IFERROR(__xludf.DUMMYFUNCTION("IFERROR(VLOOKUP($A55, GOOGLEFINANCE(K$1, ""price"", $A$2, TODAY()), 2, FALSE), """")"),39.09) -> 39.09 | L55: =IFERROR(__xludf.DUMMYFUNCTION("IFERROR(VLOOKUP($A55, GOOGLEFINANCE(L$1, ""price"", $A$2, TODAY()), 2, FALSE), """")"),37.7) -> 37.7 | M55: =IFERROR(__xludf.DUMMYFUNCTION("IFERROR(VLOOKUP($A55, GOOGLEFINANCE(M$1, ""price"", $A$2, TODAY()), 2, FALSE), """")"),38.38) -> 38.38 | O55: 0.18527203 | P55: 0.17909566 | Q55: 0.087517633 | R55: 0.17251897 | S55: 0.25713904 | T55: 0.15126387 | U55: 0.23540737 | V55: 0.073372984 | W55: 0.074516756 | X55: 0.071867017 | Y55: 0.073163293 | AA55: 0.011397364 | AB55: 0.017019903 | AC55: -0.012429641 | AD55: 0.0067144409 | AE55: -0.0009553144 | AF55: -0.027399379 | AG55: -0.011007219 | AH55: -0.052165091 | AI55: -0.028569449 | AJ55: -0.027217366 | AK55: -0.047864306
